Workbook

Sheet SwapDesk — Assumptions · Commer
A1: SwapDesk — Assumptions · Commercial and cost controls
A2: Financial model (4 pages) · Main Scenario
A4: Variable / dimension | B4: Value
A5: Subscription price | B5: =49 -> 49
A6: Included resolutions | B6: =100 -> 100
A7: Overage price | B7: =0.5 -> 0.5
A8: Cost per execution | B8: =0.03 -> 0.03
A9: Technical support hourly cost | B9: =25 -> 25
A10: Onboarding minutes | B10: =90 -> 90
A11: Customer acquisition cost | B11: =100 -> 100
A12: Fixed infrastructure cost | B12: =75 -> 75
A13: Infrastructure cost per store | B13: =1 -> 1
A14: Other monthly overhead | B14: =150 -> 150
A15: Opening cash assumption | B15: =15000 -> 15000
A16: Founder annual pay | B16: =24000 -> 24000

Sheet SwapDesk — Assumptions · Mercha
A1: SwapDesk — Assumptions · Merchant segment assumptions
A2: Financial model (4 pages) · Main Scenario
A4: Variable / dimension | B4: New stores per month | C4: Monthly store churn | D4: Cases per store | E4: Verified resolution rate | F4: Extra execution factor | G4: Support minutes per store
A5: Growing shop | B5: =0.5 -> 0.5 | C5: =0.02 -> 0.02 | D5: =400 -> 400 | E5: =0.65 -> 0.65 | F5: =0.15 -> 0.15 | G5: =30 -> 30
A6: Small shop | B6: =1 -> 1 | C6: =0.03 -> 0.03 | D6: =120 -> 120 | E6: =0.65 -> 0.65 | F6: =0.15 -> 0.15 | G6: =15 -> 15

Sheet SwapDesk — Assumptions · Placeh
A1: SwapDesk — Assumptions · Placeholder founder compensation
A2: Financial model (4 pages) · Main Scenario
A4: Variable / dimension | B4: Founder start date | C4: Planned annual compensation
A5: Placeholder founder 1 | B5: =DATE(2027,1,1) -> 46388 | C5: =IF('SwapDesk — Assumptions · Commer'!B16="","",'SwapDesk — Assumptions · Commer'!B16) -> 24000

Sheet SwapDesk — Assumptions · Simula
A1: SwapDesk — Assumptions · Simulator baseline rates
A2: Financial model (4 pages) · Main Scenario
A4: Variable / dimension | B4: Value
A5: Simulator resolution rate | B5: =IF('SwapDesk — Assumptions · Mercha'!E6="","",'SwapDesk — Assumptions · Mercha'!E6) -> 0.65
A6: Simulator extra execution factor | B6: =IF('SwapDesk — Assumptions · Mercha'!F6="","",'SwapDesk — Assumptions · Mercha'!F6) -> 0.15

Sheet SwapDesk — Operations · Merchan
A1: SwapDesk — Operations · Merchant and execution forecast
A2: Financial model (4 pages) · Main Scenario
A4: Variable / dimension | B4: 2026-09 | C4: 2026-10 | D4: 2026-11 | E4: 2026-12 | F4: 2027-01 | G4: 2027-02 | H4: 2027-03 | I4: 2027-04 | J4: 2027-05 | K4: 2027-06 | L4: 2027-07 | M4: 2027-08 | N4: 2027-09 | O4: 2027-10 | P4: 2027-11 | Q4: 2027-12 | R4: 2028-01 | S4: 2028-02 | T4: 2028-03 | U4: 2028-04 | V4: 2028-05 | W4: 2028-06 | X4: 2028-07 | Y4: 2028-08 | Z4: 2028-09
A5: Opening stores | B5: =SUM('SwapDesk — Operations · Merchan'!B6,'SwapDesk — Operations · Merchan'!B7) -> 0 | C5: =SUM('SwapDesk — Operations · Merchan'!C6,'SwapDesk — Operations · Merchan'!C7) -> 7 | D5: =SUM('SwapDesk — Operations · Merchan'!D6,'SwapDesk — Operations · Merchan'!D7) -> 8.31 | E5: =SUM('SwapDesk — Operations · Merchan'!E6,'SwapDesk — Operations · Merchan'!E7) -> 9.5853 | F5: =SUM('SwapDesk — Operations · Merchan'!F6,'SwapDesk — Operations · Merchan'!F7) -> 10.826849 | G5: =SUM('SwapDesk — Operations · Merchan'!G6,'SwapDesk — Operations · Merchan'!G7) -> 12.035569 | H5: =SUM('SwapDesk — Operations · Merchan'!H6,'SwapDesk — Operations · Merchan'!H7) -> 13.212358 | I5: =SUM('SwapDesk — Operations · Merchan'!I6,'SwapDesk — Operations · Merchan'!I7) -> 14.358085 | ... Z5: =SUM('SwapDesk — Operations · Merchan'!Z6,'SwapDesk — Operations · Merchan'!Z7) -> 29.819331
A6: Growing shop | B6: =0 -> 0 | C6: =IF('SwapDesk — Operations · Merchan'!B15="","",'SwapDesk — Operations · Merchan'!B15) -> 2 | D6: =IF('SwapDesk — Operations · Merchan'!C15="","",'SwapDesk — Operations · Merchan'!C15) -> 2.46 | E6: =IF('SwapDesk — Operations · Merchan'!D15="","",'SwapDesk — Operations · Merchan'!D15) -> 2.9108 | F6: =IF('SwapDesk — Operations · Merchan'!E15="","",'SwapDesk — Operations · Merchan'!E15) -> 3.352584 | G6: =IF('SwapDesk — Operations · Merchan'!F15="","",'SwapDesk — Operations · Merchan'!F15) -> 3.7855323 | H6: =IF('SwapDesk — Operations · Merchan'!G15="","",'SwapDesk — Operations · Merchan'!G15) -> 4.2098217 | I6: =IF('SwapDesk — Operations · Merchan'!H15="","",'SwapDesk — Operations · Merchan'!H15) -> 4.6256252 | J6: =IF('SwapDesk — Operations · Merchan'!I15="","",'SwapDesk — Operations · Merchan'!I15) -> 5.0331127 | ... Z6: =IF('SwapDesk — Operations · Merchan'!Y15="","",'SwapDesk — Operations · Merchan'!Y15) -> 10.548013
A7: Small shop | B7: =0 -> 0 | C7: =IF('SwapDesk — Operations · Merchan'!B16="","",'SwapDesk — Operations · Merchan'!B16) -> 5 | D7: =IF('SwapDesk — Operations · Merchan'!C16="","",'SwapDesk — Operations · Merchan'!C16) -> 5.85 | E7: =IF('SwapDesk — Operations · Merchan'!D16="","",'SwapDesk — Operations · Merchan'!D16) -> 6.6745 | F7: =IF('SwapDesk — Operations · Merchan'!E16="","",'SwapDesk — Operations · Merchan'!E16) -> 7.474265 | G7: =IF('SwapDesk — Operations · Merchan'!F16="","",'SwapDesk — Operations · Merchan'!F16) -> 8.250037 | H7: =IF('SwapDesk — Operations · Merchan'!G16="","",'SwapDesk — Operations · Merchan'!G16) -> 9.0025359 | I7: =IF('SwapDesk — Operations · Merchan'!H16="","",'SwapDesk — Operations · Merchan'!H16) -> 9.7324599 | J7: =IF('SwapDesk — Operations · Merchan'!I16="","",'SwapDesk — Operations · Merchan'!I16) -> 10.440486 | ... Z7: =IF('SwapDesk — Operations · Merchan'!Y16="","",'SwapDesk — Operations · Merchan'!Y16) -> 19.271318
A8: New stores | B8: =SUM('SwapDesk — Operations · Merchan'!B9,'SwapDesk — Operations · Merchan'!B10) -> 0 | C8: =SUM('SwapDesk — Operations · Merchan'!C9,'SwapDesk — Operations · Merchan'!C10) -> 1.5 | D8: =SUM('SwapDesk — Operations · Merchan'!D9,'SwapDesk — Operations · Merchan'!D10) -> 1.5 | E8: =SUM('SwapDesk — Operations · Merchan'!E9,'SwapDesk — Operations · Merchan'!E10) -> 1.5 | F8: =SUM('SwapDesk — Operations · Merchan'!F9,'SwapDesk — Operations · Merchan'!F10) -> 1.5 | G8: =SUM('SwapDesk — Operations · Merchan'!G9,'SwapDesk — Operations · Merchan'!G10) -> 1.5 | H8: =SUM('SwapDesk — Operations · Merchan'!H9,'SwapDesk — Operations · Merchan'!H10) -> 1.5 | I8: =SUM('SwapDesk — Operations · Merchan'!I9,'SwapDesk — Operations · Merchan'!I10) -> 1.5 | ... Z8: =SUM('SwapDesk — Operations · Merchan'!Z9,'SwapDesk — Operations · Merchan'!Z10) -> 1.5
A9: Growing shop | B9: =0 -> 0 | C9: =IF('SwapDesk — Assumptions · Mercha'!B5="","",'SwapDesk — Assumptions · Mercha'!B5) -> 0.5 | D9: =IF('SwapDesk — Assumptions · Mercha'!B5="","",'SwapDesk — Assumptions · Mercha'!B5) -> 0.5 | E9: =IF('SwapDesk — Assumptions · Mercha'!B5="","",'SwapDesk — Assumptions · Mercha'!B5) -> 0.5 | F9: =IF('SwapDesk — Assumptions · Mercha'!B5="","",'SwapDesk — Assumptions · Mercha'!B5) -> 0.5 | G9: =IF('SwapDesk — Assumptions · Mercha'!B5="","",'SwapDesk — Assumptions · Mercha'!B5) -> 0.5 | H9: =IF('SwapDesk — Assumptions · Mercha'!B5="","",'SwapDesk — Assumptions · Mercha'!B5) -> 0.5 | I9: =IF('SwapDesk — Assumptions · Mercha'!B5="","",'SwapDesk — Assumptions · Mercha'!B5) -> 0.5 | J9: =IF('SwapDesk — Assumptions · Mercha'!B5="","",'SwapDesk — Assumptions · Mercha'!B5) -> 0.5 | K9: =IF('SwapDesk — Assumptions · Mercha'!B5="","",'SwapDesk — Assumptions · Mercha'!B5) -> 0.5 | L9: =IF('SwapDesk — Assumptions · Mercha'!B5="","",'SwapDesk — Assumptions · Mercha'!B5) -> 0.5 | M9: =IF('SwapDesk — Assumptions · Mercha'!B5="","",'SwapDesk — Assumptions · Mercha'!B5) -> 0.5 | N9: =IF('SwapDesk — Assumptions · Mercha'!B5="","",'SwapDesk — Assumptions · Mercha'!B5) -> 0.5 | O9: =IF('SwapDesk — Assumptions · Mercha'!B5="","",'SwapDesk — Assumptions · Mercha'!B5) -> 0.5 | P9: =IF('SwapDesk — Assumptions · Mercha'!B5="","",'SwapDesk — Assumptions · Mercha'!B5) -> 0.5 | Q9: =IF('SwapDesk — Assumptions · Mercha'!B5="","",'SwapDesk — Assumptions · Mercha'!B5) -> 0.5 | R9: =IF('SwapDesk — Assumptions · Mercha'!B5="","",'SwapDesk — Assumptions · Mercha'!B5) -> 0.5 | S9: =IF('SwapDesk — Assumptions · Mercha'!B5="","",'SwapDesk — Assumptions · Mercha'!B5) -> 0.5 | T9: =IF('SwapDesk — Assumptions · Mercha'!B5="","",'SwapDesk — Assumptions · Mercha'!B5) -> 0.5 | U9: =IF('SwapDesk — Assumptions · Mercha'!B5="","",'SwapDesk — Assumptions · Mercha'!B5) -> 0.5 | V9: =IF('SwapDesk — Assumptions · Mercha'!B5="","",'SwapDesk — Assumptions · Mercha'!B5) -> 0.5 | W9: =IF('SwapDesk — Assumptions · Mercha'!B5="","",'SwapDesk — Assumptions · Mercha'!B5) -> 0.5 | X9: =IF('SwapDesk — Assumptions · Mercha'!B5="","",'SwapDesk — Assumptions · Mercha'!B5) -> 0.5 | Y9: =IF('SwapDesk — Assumptions · Mercha'!B5="","",'SwapDesk — Assumptions · Mercha'!B5) -> 0.5 | Z9: =IF('SwapDesk — Assumptions · Mercha'!B5="","",'SwapDesk — Assumptions · Mercha'!B5) -> 0.5
A10: Small shop | B10: =0 -> 0 | C10: =IF('SwapDesk — Assumptions · Mercha'!B6="","",'SwapDesk — Assumptions · Mercha'!B6) -> 1 | D10: =IF('SwapDesk — Assumptions · Mercha'!B6="","",'SwapDesk — Assumptions · Mercha'!B6) -> 1 | E10: =IF('SwapDesk — Assumptions · Mercha'!B6="","",'SwapDesk — Assumptions · Mercha'!B6) -> 1 | F10: =IF('SwapDesk — Assumptions · Mercha'!B6="","",'SwapDesk — Assumptions · Mercha'!B6) -> 1 | G10: =IF('SwapDesk — Assumptions · Mercha'!B6="","",'SwapDesk — Assumptions · Mercha'!B6) -> 1 | H10: =IF('SwapDesk — Assumptions · Mercha'!B6="","",'SwapDesk — Assumptions · Mercha'!B6) -> 1 | I10: =IF('SwapDesk — Assumptions · Mercha'!B6="","",'SwapDesk — Assumptions · Mercha'!B6) -> 1 | J10: =IF('SwapDesk — Assumptions · Mercha'!B6="","",'SwapDesk — Assumptions · Mercha'!B6) -> 1 | K10: =IF('SwapDesk — Assumptions · Mercha'!B6="","",'SwapDesk — Assumptions · Mercha'!B6) -> 1 | L10: =IF('SwapDesk — Assumptions · Mercha'!B6="","",'SwapDesk — Assumptions · Mercha'!B6) -> 1 | M10: =IF('SwapDesk — Assumptions · Mercha'!B6="","",'SwapDesk — Assumptions · Mercha'!B6) -> 1 | N10: =IF('SwapDesk — Assumptions · Mercha'!B6="","",'SwapDesk — Assumptions · Mercha'!B6) -> 1 | O10: =IF('SwapDesk — Assumptions · Mercha'!B6="","",'SwapDesk — Assumptions · Mercha'!B6) -> 1 | P10: =IF('SwapDesk — Assumptions · Mercha'!B6="","",'SwapDesk — Assumptions · Mercha'!B6) -> 1 | Q10: =IF('SwapDesk — Assumptions · Mercha'!B6="","",'SwapDesk — Assumptions · Mercha'!B6) -> 1 | R10: =IF('SwapDesk — Assumptions · Mercha'!B6="","",'SwapDesk — Assumptions · Mercha'!B6) -> 1 | S10: =IF('SwapDesk — Assumptions · Mercha'!B6="","",'SwapDesk — Assumptions · Mercha'!B6) -> 1 | T10: =IF('SwapDesk — Assumptions · Mercha'!B6="","",'SwapDesk — Assumptions · Mercha'!B6) -> 1 | U10: =IF('SwapDesk — Assumptions · Mercha'!B6="","",'SwapDesk — Assumptions · Mercha'!B6) -> 1 | V10: =IF('SwapDesk — Assumptions · Mercha'!B6="","",'SwapDesk — Assumptions · Mercha'!B6) -> 1 | W10: =IF('SwapDesk — Assumptions · Mercha'!B6="","",'SwapDesk — Assumptions · Mercha'!B6) -> 1 | X10: =IF('SwapDesk — Assumptions · Mercha'!B6="","",'SwapDesk — Assumptions · Mercha'!B6) -> 1 | Y10: =IF('SwapDesk — Assumptions · Mercha'!B6="","",'SwapDesk — Assumptions · Mercha'!B6) -> 1 | Z10: =IF('SwapDesk — Assumptions · Mercha'!B6="","",'SwapDesk — Assumptions · Mercha'!B6) -> 1
A11: Lost stores | B11: =SUM('SwapDesk — Operations · Merchan'!B12,'SwapDesk — Operations · Merchan'!B13) -> 0 | C11: =SUM('SwapDesk — Operations · Merchan'!C12,'SwapDesk — Operations · Merchan'!C13) -> 0.19 | D11: =SUM('SwapDesk — Operations · Merchan'!D12,'SwapDesk — Operations · Merchan'!D13) -> 0.2247 | E11: =SUM('SwapDesk — Operations · Merchan'!E12,'SwapDesk — Operations · Merchan'!E13) -> 0.258451 | F11: =SUM('SwapDesk — Operations · Merchan'!F12,'SwapDesk — Operations · Merchan'!F13) -> 0.29127963 | G11: =SUM('SwapDesk — Operations · Merchan'!G12,'SwapDesk — Operations · Merchan'!G13) -> 0.32321176 | H11: =SUM('SwapDesk — Operations · Merchan'!H12,'SwapDesk — Operations · Merchan'!H13) -> 0.35427251 | I11: =SUM('SwapDesk — Operations · Merchan'!I12,'SwapDesk — Operations · Merchan'!I13) -> 0.3844863 | ... Z11: =SUM('SwapDesk — Operations · Merchan'!Z12,'SwapDesk — Operations · Merchan'!Z13) -> 0.7890998
A12: Growing shop | B12: =0 -> 0 | C12: ='SwapDesk — Operations · Merchan'!C6*'SwapDesk — Assumptions · Mercha'!C5 -> 0.04 | D12: ='SwapDesk — Operations · Merchan'!D6*'SwapDesk — Assumptions · Mercha'!C5 -> 0.0492 | E12: ='SwapDesk — Operations · Merchan'!E6*'SwapDesk — Assumptions · Mercha'!C5 -> 0.058216 | F12: ='SwapDesk — Operations · Merchan'!F6*'SwapDesk — Assumptions · Mercha'!C5 -> 0.06705168 | G12: ='SwapDesk — Operations · Merchan'!G6*'SwapDesk — Assumptions · Mercha'!C5 -> 0.075710646 | H12: ='SwapDesk — Operations · Merchan'!H6*'SwapDesk — Assumptions · Mercha'!C5 -> 0.084196433 | I12: ='SwapDesk — Operations · Merchan'!I6*'SwapDesk — Assumptions · Mercha'!C5 -> 0.092512505 | J12: ='SwapDesk — Operations · Merchan'!J6*'SwapDesk — Assumptions · Mercha'!C5 -> 0.10066225 | K12: ='SwapDesk — Operations · Merchan'!K6*'SwapDesk — Assumptions · Mercha'!C5 -> 0.10864901 | L12: ='SwapDesk — Operations · Merchan'!L6*'SwapDesk — Assumptions · Mercha'!C5 -> 0.11647603 | M12: ='SwapDesk — Operations · Merchan'!M6*'SwapDesk — Assumptions · Mercha'!C5 -> 0.12414651 | N12: ='SwapDesk — Operations · Merchan'!N6*'SwapDesk — Assumptions · Mercha'!C5 -> 0.13166358 | O12: ='SwapDesk — Operations · Merchan'!O6*'SwapDesk — Assumptions · Mercha'!C5 -> 0.13903031 | P12: ='SwapDesk — Operations · Merchan'!P6*'SwapDesk — Assumptions · Mercha'!C5 -> 0.1462497 | Q12: ='SwapDesk — Operations · Merchan'!Q6*'SwapDesk — Assumptions · Mercha'!C5 -> 0.15332471 | R12: ='SwapDesk — Operations · Merchan'!R6*'SwapDesk — Assumptions · Mercha'!C5 -> 0.16025821 | S12: ='SwapDesk — Operations · Merchan'!S6*'SwapDesk — Assumptions · Mercha'!C5 -> 0.16705305 | T12: ='SwapDesk — Operations · Merchan'!T6*'SwapDesk — Assumptions · Mercha'!C5 -> 0.17371199 | U12: ='SwapDesk — Operations · Merchan'!U6*'SwapDesk — Assumptions · Mercha'!C5 -> 0.18023775 | V12: ='SwapDesk — Operations · Merchan'!V6*'SwapDesk — Assumptions · Mercha'!C5 -> 0.18663299 | W12: ='SwapDesk — Operations · Merchan'!W6*'SwapDesk — Assumptions · Mercha'!C5 -> 0.19290033 | X12: ='SwapDesk — Operations · Merchan'!X6*'SwapDesk — Assumptions · Mercha'!C5 -> 0.19904233 | Y12: ='SwapDesk — Operations · Merchan'!Y6*'SwapDesk — Assumptions · Mercha'!C5 -> 0.20506148 | Z12: ='SwapDesk — Operations · Merchan'!Z6*'SwapDesk — Assumptions · Mercha'!C5 -> 0.21096025
A13: Small shop | B13: =0 -> 0 | C13: ='SwapDesk — Operations · Merchan'!C7*'SwapDesk — Assumptions · Mercha'!C6 -> 0.15 | D13: ='SwapDesk — Operations · Merchan'!D7*'SwapDesk — Assumptions · Mercha'!C6 -> 0.1755 | E13: ='SwapDesk — Operations · Merchan'!E7*'SwapDesk — Assumptions · Mercha'!C6 -> 0.200235 | F13: ='SwapDesk — Operations · Merchan'!F7*'SwapDesk — Assumptions · Mercha'!C6 -> 0.22422795 | G13: ='SwapDesk — Operations · Merchan'!G7*'SwapDesk — Assumptions · Mercha'!C6 -> 0.24750111 | H13: ='SwapDesk — Operations · Merchan'!H7*'SwapDesk — Assumptions · Mercha'!C6 -> 0.27007608 | I13: ='SwapDesk — Operations · Merchan'!I7*'SwapDesk — Assumptions · Mercha'!C6 -> 0.2919738 | J13: ='SwapDesk — Operations · Merchan'!J7*'SwapDesk — Assumptions · Mercha'!C6 -> 0.31321458 | K13: ='SwapDesk — Operations · Merchan'!K7*'SwapDesk — Assumptions · Mercha'!C6 -> 0.33381814 | L13: ='SwapDesk — Operations · Merchan'!L7*'SwapDesk — Assumptions · Mercha'!C6 -> 0.3538036 | M13: ='SwapDesk — Operations · Merchan'!M7*'SwapDesk — Assumptions · Mercha'!C6 -> 0.37318949 | N13: ='SwapDesk — Operations · Merchan'!N7*'SwapDesk — Assumptions · Mercha'!C6 -> 0.39199381 | O13: ='SwapDesk — Operations · Merchan'!O7*'SwapDesk — Assumptions · Mercha'!C6 -> 0.41023399 | P13: ='SwapDesk — Operations · Merchan'!P7*'SwapDesk — Assumptions · Mercha'!C6 -> 0.42792697 | Q13: ='SwapDesk — Operations · Merchan'!Q7*'SwapDesk — Assumptions · Mercha'!C6 -> 0.44508916 | R13: ='SwapDesk — Operations · Merchan'!R7*'SwapDesk — Assumptions · Mercha'!C6 -> 0.46173649 | S13: ='SwapDesk — Operations · Merchan'!S7*'SwapDesk — Assumptions · Mercha'!C6 -> 0.47788439 | T13: ='SwapDesk — Operations · Merchan'!T7*'SwapDesk — Assumptions · Mercha'!C6 -> 0.49354786 | U13: ='SwapDesk — Operations · Merchan'!U7*'SwapDesk — Assumptions · Mercha'!C6 -> 0.50874143 | V13: ='SwapDesk — Operations · Merchan'!V7*'SwapDesk — Assumptions · Mercha'!C6 -> 0.52347918 | W13: ='SwapDesk — Operations · Merchan'!W7*'SwapDesk — Assumptions · Mercha'!C6 -> 0.53777481 | X13: ='SwapDesk — Operations · Merchan'!X7*'SwapDesk — Assumptions · Mercha'!C6 -> 0.55164156 | Y13: ='SwapDesk — Operations · Merchan'!Y7*'SwapDesk — Assumptions · Mercha'!C6 -> 0.56509232 | Z13: ='SwapDesk — Operations · Merchan'!Z7*'SwapDesk — Assumptions · Mercha'!C6 -> 0.57813955
A14: Ending stores | B14: =SUM('SwapDesk — Operations · Merchan'!B15,'SwapDesk — Operations · Merchan'!B16) -> 7 | C14: =SUM('SwapDesk — Operations · Merchan'!C15,'SwapDesk — Operations · Merchan'!C16) -> 8.31 | D14: =SUM('SwapDesk — Operations · Merchan'!D15,'SwapDesk — Operations · Merchan'!D16) -> 9.5853 | E14: =SUM('SwapDesk — Operations · Merchan'!E15,'SwapDesk — Operations · Merchan'!E16) -> 10.826849 | F14: =SUM('SwapDesk — Operations · Merchan'!F15,'SwapDesk — Operations · Merchan'!F16) -> 12.035569 | G14: =SUM('SwapDesk — Operations · Merchan'!G15,'SwapDesk — Operations · Merchan'!G16) -> 13.212358 | H14: =SUM('SwapDesk — Operations · Merchan'!H15,'SwapDesk — Operations · Merchan'!H16) -> 14.358085 | I14: =SUM('SwapDesk — Operations · Merchan'!I15,'SwapDesk — Operations · Merchan'!I16) -> 15.473599 | ... Z14: =SUM('SwapDesk — Operations · Merchan'!Z15,'SwapDesk — Operations · Merchan'!Z16) -> 30.530231
A15: Growing shop | B15: =2 -> 2 | C15: ='SwapDesk — Operations · Merchan'!C6+'SwapDesk — Operations · Merchan'!C9-'SwapDesk — Operations · Merchan'!C12 -> 2.46 | D15: ='SwapDesk — Operations · Merchan'!D6+'SwapDesk — Operations · Merchan'!D9-'SwapDesk — Operations · Merchan'!D12 -> 2.9108 | E15: ='SwapDesk — Operations · Merchan'!E6+'SwapDesk — Operations · Merchan'!E9-'SwapDesk — Operations · Merchan'!E12 -> 3.352584 | F15: ='SwapDesk — Operations · Merchan'!F6+'SwapDesk — Operations · Merchan'!F9-'SwapDesk — Operations · Merchan'!F12 -> 3.7855323 | G15: ='SwapDesk — Operations · Merchan'!G6+'SwapDesk — Operations · Merchan'!G9-'SwapDesk — Operations · Merchan'!G12 -> 4.2098217 | H15: ='SwapDesk — Operations · Merchan'!H6+'SwapDesk — Operations · Merchan'!H9-'SwapDesk — Operations · Merchan'!H12 -> 4.6256252 | I15: ='SwapDesk — Operations · Merchan'!I6+'SwapDesk — Operations · Merchan'!I9-'SwapDesk — Operations · Merchan'!I12 -> 5.0331127 | J15: ='SwapDesk — Operations · Merchan'!J6+'SwapDesk — Operations · Merchan'!J9-'SwapDesk — Operations · Merchan'!J12 -> 5.4324505 | ... Z15: ='SwapDesk — Operations · Merchan'!Z6+'SwapDesk — Operations · Merchan'!Z9-'SwapDesk — Operations · Merchan'!Z12 -> 10.837052
A16: Small shop | B16: =5 -> 5 | C16: ='SwapDesk — Operations · Merchan'!C7+'SwapDesk — Operations · Merchan'!C10-'SwapDesk — Operations · Merchan'!C13 -> 5.85 | D16: ='SwapDesk — Operations · Merchan'!D7+'SwapDesk — Operations · Merchan'!D10-'SwapDesk — Operations · Merchan'!D13 -> 6.6745 | E16: ='SwapDesk — Operations · Merchan'!E7+'SwapDesk — Operations · Merchan'!E10-'SwapDesk — Operations · Merchan'!E13 -> 7.474265 | F16: ='SwapDesk — Operations · Merchan'!F7+'SwapDesk — Operations · Merchan'!F10-'SwapDesk — Operations · Merchan'!F13 -> 8.250037 | G16: ='SwapDesk — Operations · Merchan'!G7+'SwapDesk — Operations · Merchan'!G10-'SwapDesk — Operations · Merchan'!G13 -> 9.0025359 | H16: ='SwapDesk — Operations · Merchan'!H7+'SwapDesk — Operations · Merchan'!H10-'SwapDesk — Operations · Merchan'!H13 -> 9.7324599 | I16: ='SwapDesk — Operations · Merchan'!I7+'SwapDesk — Operations · Merchan'!I10-'SwapDesk — Operations · Merchan'!I13 -> 10.440486 | J16: ='SwapDesk — Operations · Merchan'!J7+'SwapDesk — Operations · Merchan'!J10-'SwapDesk — Operations · Merchan'!J13 -> 11.127271 | ... Z16: ='SwapDesk — Operations · Merchan'!Z7+'SwapDesk — Operations · Merchan'!Z10-'SwapDesk — Operations · Merchan'!Z13 -> 19.693179
A17: Attempted cases | B17: =SUM('SwapDesk — Operations · Merchan'!B18,'SwapDesk — Operations · Merchan'!B19) -> 0 | C17: =SUM('SwapDesk — Operations · Merchan'!C18,'SwapDesk — Operations · Merchan'!C19) -> 1686 | D17: =SUM('SwapDesk — Operations · Merchan'!D18,'SwapDesk — Operations · Merchan'!D19) -> 1965.26 | E17: =SUM('SwapDesk — Operations · Merchan'!E18,'SwapDesk — Operations · Merchan'!E19) -> 2237.9454 | F17: =SUM('SwapDesk — Operations · Merchan'!F18,'SwapDesk — Operations · Merchan'!F19) -> 2504.2174 | G17: =SUM('SwapDesk — Operations · Merchan'!G18,'SwapDesk — Operations · Merchan'!G19) -> 2764.233 | H17: =SUM('SwapDesk — Operations · Merchan'!H18,'SwapDesk — Operations · Merchan'!H19) -> 3018.1453 | I17: =SUM('SwapDesk — Operations · Merchan'!I18,'SwapDesk — Operations · Merchan'!I19) -> 3266.1034 | ... Z17: =SUM('SwapDesk — Operations · Merchan'!Z18,'SwapDesk — Operations · Merchan'!Z19) -> 6698.0023
A18: Growing shop | B18: =0 -> 0 | C18: ='SwapDesk — Operations · Merchan'!C15*'SwapDesk — Assumptions · Mercha'!D5 -> 984 | D18: ='SwapDesk — Operations · Merchan'!D15*'SwapDesk — Assumptions · Mercha'!D5 -> 1164.32 | E18: ='SwapDesk — Operations · Merchan'!E15*'SwapDesk — Assumptions · Mercha'!D5 -> 1341.0336 | F18: ='SwapDesk — Operations · Merchan'!F15*'SwapDesk — Assumptions · Mercha'!D5 -> 1514.2129 | G18: ='SwapDesk — Operations · Merchan'!G15*'SwapDesk — Assumptions · Mercha'!D5 -> 1683.9287 | H18: ='SwapDesk — Operations · Merchan'!H15*'SwapDesk — Assumptions · Mercha'!D5 -> 1850.2501 | I18: ='SwapDesk — Operations · Merchan'!I15*'SwapDesk — Assumptions · Mercha'!D5 -> 2013.2451 | J18: ='SwapDesk — Operations · Merchan'!J15*'SwapDesk — Assumptions · Mercha'!D5 -> 2172.9802 | K18: ='SwapDesk — Operations · Merchan'!K15*'SwapDesk — Assumptions · Mercha'!D5 -> 2329.5206 | L18: ='SwapDesk — Operations · Merchan'!L15*'SwapDesk — Assumptions · Mercha'!D5 -> 2482.9302 | M18: ='SwapDesk — Operations · Merchan'!M15*'SwapDesk — Assumptions · Mercha'!D5 -> 2633.2716 | N18: ='SwapDesk — Operations · Merchan'!N15*'SwapDesk — Assumptions · Mercha'!D5 -> 2780.6061 | O18: ='SwapDesk — Operations · Merchan'!O15*'SwapDesk — Assumptions · Mercha'!D5 -> 2924.994 | P18: ='SwapDesk — Operations · Merchan'!P15*'SwapDesk — Assumptions · Mercha'!D5 -> 3066.4941 | Q18: ='SwapDesk — Operations · Merchan'!Q15*'SwapDesk — Assumptions · Mercha'!D5 -> 3205.1643 | R18: ='SwapDesk — Operations · Merchan'!R15*'SwapDesk — Assumptions · Mercha'!D5 -> 3341.061 | S18: ='SwapDesk — Operations · Merchan'!S15*'SwapDesk — Assumptions · Mercha'!D5 -> 3474.2398 | T18: ='SwapDesk — Operations · Merchan'!T15*'SwapDesk — Assumptions · Mercha'!D5 -> 3604.755 | U18: ='SwapDesk — Operations · Merchan'!U15*'SwapDesk — Assumptions · Mercha'!D5 -> 3732.6599 | V18: ='SwapDesk — Operations · Merchan'!V15*'SwapDesk — Assumptions · Mercha'!D5 -> 3858.0067 | W18: ='SwapDesk — Operations · Merchan'!W15*'SwapDesk — Assumptions · Mercha'!D5 -> 3980.8465 | X18: ='SwapDesk — Operations · Merchan'!X15*'SwapDesk — Assumptions · Mercha'!D5 -> 4101.2296 | Y18: ='SwapDesk — Operations · Merchan'!Y15*'SwapDesk — Assumptions · Mercha'!D5 -> 4219.205 | Z18: ='SwapDesk — Operations · Merchan'!Z15*'SwapDesk — Assumptions · Mercha'!D5 -> 4334.8209
A19: Small shop | B19: =0 -> 0 | C19: ='SwapDesk — Operations · Merchan'!C16*'SwapDesk — Assumptions · Mercha'!D6 -> 702 | D19: ='SwapDesk — Operations · Merchan'!D16*'SwapDesk — Assumptions · Mercha'!D6 -> 800.94 | E19: ='SwapDesk — Operations · Merchan'!E16*'SwapDesk — Assumptions · Mercha'!D6 -> 896.9118 | F19: ='SwapDesk — Operations · Merchan'!F16*'SwapDesk — Assumptions · Mercha'!D6 -> 990.00445 | G19: ='SwapDesk — Operations · Merchan'!G16*'SwapDesk — Assumptions · Mercha'!D6 -> 1080.3043 | H19: ='SwapDesk — Operations · Merchan'!H16*'SwapDesk — Assumptions · Mercha'!D6 -> 1167.8952 | I19: ='SwapDesk — Operations · Merchan'!I16*'SwapDesk — Assumptions · Mercha'!D6 -> 1252.8583 | J19: ='SwapDesk — Operations · Merchan'!J16*'SwapDesk — Assumptions · Mercha'!D6 -> 1335.2726 | K19: ='SwapDesk — Operations · Merchan'!K16*'SwapDesk — Assumptions · Mercha'!D6 -> 1415.2144 | L19: ='SwapDesk — Operations · Merchan'!L16*'SwapDesk — Assumptions · Mercha'!D6 -> 1492.758 | M19: ='SwapDesk — Operations · Merchan'!M16*'SwapDesk — Assumptions · Mercha'!D6 -> 1567.9752 | N19: ='SwapDesk — Operations · Merchan'!N16*'SwapDesk — Assumptions · Mercha'!D6 -> 1640.936 | O19: ='SwapDesk — Operations · Merchan'!O16*'SwapDesk — Assumptions · Mercha'!D6 -> 1711.7079 | P19: ='SwapDesk — Operations · Merchan'!P16*'SwapDesk — Assumptions · Mercha'!D6 -> 1780.3567 | Q19: ='SwapDesk — Operations · Merchan'!Q16*'SwapDesk — Assumptions · Mercha'!D6 -> 1846.946 | R19: ='SwapDesk — Operations · Merchan'!R16*'SwapDesk — Assumptions · Mercha'!D6 -> 1911.5376 | S19: ='SwapDesk — Operations · Merchan'!S16*'SwapDesk — Assumptions · Mercha'!D6 -> 1974.1915 | T19: ='SwapDesk — Operations · Merchan'!T16*'SwapDesk — Assumptions · Mercha'!D6 -> 2034.9657 | U19: ='SwapDesk — Operations · Merchan'!U16*'SwapDesk — Assumptions · Mercha'!D6 -> 2093.9167 | V19: ='SwapDesk — Operations · Merchan'!V16*'SwapDesk — Assumptions · Mercha'!D6 -> 2151.0992 | W19: ='SwapDesk — Operations · Merchan'!W16*'SwapDesk — Assumptions · Mercha'!D6 -> 2206.5663 | X19: ='SwapDesk — Operations · Merchan'!X16*'SwapDesk — Assumptions · Mercha'!D6 -> 2260.3693 | Y19: ='SwapDesk — Operations · Merchan'!Y16*'SwapDesk — Assumptions · Mercha'!D6 -> 2312.5582 | Z19: ='SwapDesk — Operations · Merchan'!Z16*'SwapDesk — Assumptions · Mercha'!D6 -> 2363.1814
A20: Verified arrangements | B20: =SUM('SwapDesk — Operations · Merchan'!B21,'SwapDesk — Operations · Merchan'!B22) -> 0 | C20: =SUM('SwapDesk — Operations · Merchan'!C21,'SwapDesk — Operations · Merchan'!C22) -> 1095.9 | D20: =SUM('SwapDesk — Operations · Merchan'!D21,'SwapDesk — Operations · Merchan'!D22) -> 1277.419 | E20: =SUM('SwapDesk — Operations · Merchan'!E21,'SwapDesk — Operations · Merchan'!E22) -> 1454.6645 | F20: =SUM('SwapDesk — Operations · Merchan'!F21,'SwapDesk — Operations · Merchan'!F22) -> 1627.7413 | G20: =SUM('SwapDesk — Operations · Merchan'!G21,'SwapDesk — Operations · Merchan'!G22) -> 1796.7514 | H20: =SUM('SwapDesk — Operations · Merchan'!H21,'SwapDesk — Operations · Merchan'!H22) -> 1961.7944 | I20: =SUM('SwapDesk — Operations · Merchan'!I21,'SwapDesk — Operations · Merchan'!I22) -> 2122.9672 | ... Z20: =SUM('SwapDesk — Operations · Merchan'!Z21,'SwapDesk — Operations · Merchan'!Z22) -> 4353.7015
A21: Growing shop | B21: =0 -> 0 | C21: ='SwapDesk — Operations · Merchan'!C18*'SwapDesk — Assumptions · Mercha'!E5 -> 639.6 | D21: ='SwapDesk — Operations · Merchan'!D18*'SwapDesk — Assumptions · Mercha'!E5 -> 756.808 | E21: ='SwapDesk — Operations · Merchan'!E18*'SwapDesk — Assumptions · Mercha'!E5 -> 871.67184 | F21: ='SwapDesk — Operations · Merchan'!F18*'SwapDesk — Assumptions · Mercha'!E5 -> 984.2384 | G21: ='SwapDesk — Operations · Merchan'!G18*'SwapDesk — Assumptions · Mercha'!E5 -> 1094.5536 | H21: ='SwapDesk — Operations · Merchan'!H18*'SwapDesk — Assumptions · Mercha'!E5 -> 1202.6626 | I21: ='SwapDesk — Operations · Merchan'!I18*'SwapDesk — Assumptions · Mercha'!E5 -> 1308.6093 | J21: ='SwapDesk — Operations · Merchan'!J18*'SwapDesk — Assumptions · Mercha'!E5 -> 1412.4371 | K21: ='SwapDesk — Operations · Merchan'!K18*'SwapDesk — Assumptions · Mercha'!E5 -> 1514.1884 | L21: ='SwapDesk — Operations · Merchan'!L18*'SwapDesk — Assumptions · Mercha'!E5 -> 1613.9046 | M21: ='SwapDesk — Operations · Merchan'!M18*'SwapDesk — Assumptions · Mercha'!E5 -> 1711.6265 | N21: ='SwapDesk — Operations · Merchan'!N18*'SwapDesk — Assumptions · Mercha'!E5 -> 1807.394 | O21: ='SwapDesk — Operations · Merchan'!O18*'SwapDesk — Assumptions · Mercha'!E5 -> 1901.2461 | P21: ='SwapDesk — Operations · Merchan'!P18*'SwapDesk — Assumptions · Mercha'!E5 -> 1993.2212 | Q21: ='SwapDesk — Operations · Merchan'!Q18*'SwapDesk — Assumptions · Mercha'!E5 -> 2083.3568 | R21: ='SwapDesk — Operations · Merchan'!R18*'SwapDesk — Assumptions · Mercha'!E5 -> 2171.6896 | S21: ='SwapDesk — Operations · Merchan'!S18*'SwapDesk — Assumptions · Mercha'!E5 -> 2258.2558 | T21: ='SwapDesk — Operations · Merchan'!T18*'SwapDesk — Assumptions · Mercha'!E5 -> 2343.0907 | U21: ='SwapDesk — Operations · Merchan'!U18*'SwapDesk — Assumptions · Mercha'!E5 -> 2426.2289 | V21: ='SwapDesk — Operations · Merchan'!V18*'SwapDesk — Assumptions · Mercha'!E5 -> 2507.7043 | W21: ='SwapDesk — Operations · Merchan'!W18*'SwapDesk — Assumptions · Mercha'!E5 -> 2587.5502 | X21: ='SwapDesk — Operations · Merchan'!X18*'SwapDesk — Assumptions · Mercha'!E5 -> 2665.7992 | Y21: ='SwapDesk — Operations · Merchan'!Y18*'SwapDesk — Assumptions · Mercha'!E5 -> 2742.4833 | Z21: ='SwapDesk — Operations · Merchan'!Z18*'SwapDesk — Assumptions · Mercha'!E5 -> 2817.6336
A22: Small shop | B22: =0 -> 0 | C22: ='SwapDesk — Operations · Merchan'!C19*'SwapDesk — Assumptions · Mercha'!E6 -> 456.3 | D22: ='SwapDesk — Operations · Merchan'!D19*'SwapDesk — Assumptions · Mercha'!E6 -> 520.611 | E22: ='SwapDesk — Operations · Merchan'!E19*'SwapDesk — Assumptions · Mercha'!E6 -> 582.99267 | F22: ='SwapDesk — Operations · Merchan'!F19*'SwapDesk — Assumptions · Mercha'!E6 -> 643.50289 | G22: ='SwapDesk — Operations · Merchan'!G19*'SwapDesk — Assumptions · Mercha'!E6 -> 702.1978 | H22: ='SwapDesk — Operations · Merchan'!H19*'SwapDesk — Assumptions · Mercha'!E6 -> 759.13187 | I22: ='SwapDesk — Operations · Merchan'!I19*'SwapDesk — Assumptions · Mercha'!E6 -> 814.35791 | J22: ='SwapDesk — Operations · Merchan'!J19*'SwapDesk — Assumptions · Mercha'!E6 -> 867.92718 | K22: ='SwapDesk — Operations · Merchan'!K19*'SwapDesk — Assumptions · Mercha'!E6 -> 919.88936 | L22: ='SwapDesk — Operations · Merchan'!L19*'SwapDesk — Assumptions · Mercha'!E6 -> 970.29268 | M22: ='SwapDesk — Operations · Merchan'!M19*'SwapDesk — Assumptions · Mercha'!E6 -> 1019.1839 | N22: ='SwapDesk — Operations · Merchan'!N19*'SwapDesk — Assumptions · Mercha'!E6 -> 1066.6084 | O22: ='SwapDesk — Operations · Merchan'!O19*'SwapDesk — Assumptions · Mercha'!E6 -> 1112.6101 | P22: ='SwapDesk — Operations · Merchan'!P19*'SwapDesk — Assumptions · Mercha'!E6 -> 1157.2318 | Q22: ='SwapDesk — Operations · Merchan'!Q19*'SwapDesk — Assumptions · Mercha'!E6 -> 1200.5149 | R22: ='SwapDesk — Operations · Merchan'!R19*'SwapDesk — Assumptions · Mercha'!E6 -> 1242.4994 | S22: ='SwapDesk — Operations · Merchan'!S19*'SwapDesk — Assumptions · Mercha'!E6 -> 1283.2244 | T22: ='SwapDesk — Operations · Merchan'!T19*'SwapDesk — Assumptions · Mercha'!E6 -> 1322.7277 | U22: ='SwapDesk — Operations · Merchan'!U19*'SwapDesk — Assumptions · Mercha'!E6 -> 1361.0459 | V22: ='SwapDesk — Operations · Merchan'!V19*'SwapDesk — Assumptions · Mercha'!E6 -> 1398.2145 | W22: ='SwapDesk — Operations · Merchan'!W19*'SwapDesk — Assumptions · Mercha'!E6 -> 1434.2681 | X22: ='SwapDesk — Operations · Merchan'!X19*'SwapDesk — Assumptions · Mercha'!E6 -> 1469.24 | Y22: ='SwapDesk — Operations · Merchan'!Y19*'SwapDesk — Assumptions · Mercha'!E6 -> 1503.1628 | Z22: ='SwapDesk — Operations · Merchan'!Z19*'SwapDesk — Assumptions · Mercha'!E6 -> 1536.0679
A23: Nonbillable cases | B23: =SUM('SwapDesk — Operations · Merchan'!B24,'SwapDesk — Operations · Merchan'!B25) -> 0 | C23: =SUM('SwapDesk — Operations · Merchan'!C24,'SwapDesk — Operations · Merchan'!C25) -> 590.1 | D23: =SUM('SwapDesk — Operations · Merchan'!D24,'SwapDesk — Operations · Merchan'!D25) -> 687.841 | E23: =SUM('SwapDesk — Operations · Merchan'!E24,'SwapDesk — Operations · Merchan'!E25) -> 783.28089 | F23: =SUM('SwapDesk — Operations · Merchan'!F24,'SwapDesk — Operations · Merchan'!F25) -> 876.47608 | G23: =SUM('SwapDesk — Operations · Merchan'!G24,'SwapDesk — Operations · Merchan'!G25) -> 967.48154 | H23: =SUM('SwapDesk — Operations · Merchan'!H24,'SwapDesk — Operations · Merchan'!H25) -> 1056.3508 | I23: =SUM('SwapDesk — Operations · Merchan'!I24,'SwapDesk — Operations · Merchan'!I25) -> 1143.1362 | ... Z23: =SUM('SwapDesk — Operations · Merchan'!Z24,'SwapDesk — Operations · Merchan'!Z25) -> 2344.3008
A24: Growing shop | B24: =0 -> 0 | C24: ='SwapDesk — Operations · Merchan'!C18-'SwapDesk — Operations · Merchan'!C21 -> 344.4 | D24: ='SwapDesk — Operations · Merchan'!D18-'SwapDesk — Operations · Merchan'!D21 -> 407.512 | E24: ='SwapDesk — Operations · Merchan'!E18-'SwapDesk — Operations · Merchan'!E21 -> 469.36176 | F24: ='SwapDesk — Operations · Merchan'!F18-'SwapDesk — Operations · Merchan'!F21 -> 529.97452 | G24: ='SwapDesk — Operations · Merchan'!G18-'SwapDesk — Operations · Merchan'!G21 -> 589.37503 | H24: ='SwapDesk — Operations · Merchan'!H18-'SwapDesk — Operations · Merchan'!H21 -> 647.58753 | I24: ='SwapDesk — Operations · Merchan'!I18-'SwapDesk — Operations · Merchan'!I21 -> 704.63578 | J24: ='SwapDesk — Operations · Merchan'!J18-'SwapDesk — Operations · Merchan'!J21 -> 760.54307 | ... Z24: ='SwapDesk — Operations · Merchan'!Z18-'SwapDesk — Operations · Merchan'!Z21 -> 1517.1873
A25: Small shop | B25: =0 -> 0 | C25: ='SwapDesk — Operations · Merchan'!C19-'SwapDesk — Operations · Merchan'!C22 -> 245.7 | D25: ='SwapDesk — Operations · Merchan'!D19-'SwapDesk — Operations · Merchan'!D22 -> 280.329 | E25: ='SwapDesk — Operations · Merchan'!E19-'SwapDesk — Operations · Merchan'!E22 -> 313.91913 | F25: ='SwapDesk — Operations · Merchan'!F19-'SwapDesk — Operations · Merchan'!F22 -> 346.50156 | G25: ='SwapDesk — Operations · Merchan'!G19-'SwapDesk — Operations · Merchan'!G22 -> 378.10651 | H25: ='SwapDesk — Operations · Merchan'!H19-'SwapDesk — Operations · Merchan'!H22 -> 408.76331 | I25: ='SwapDesk — Operations · Merchan'!I19-'SwapDesk — Operations · Merchan'!I22 -> 438.50041 | J25: ='SwapDesk — Operations · Merchan'!J19-'SwapDesk — Operations · Merchan'!J22 -> 467.3454 | ... Z25: ='SwapDesk — Operations · Merchan'!Z19-'SwapDesk — Operations · Merchan'!Z22 -> 827.11351
A26: Extra executions | B26: =SUM('SwapDesk — Operations · Merchan'!B27,'SwapDesk — Operations · Merchan'!B28) -> 0 | C26: =SUM('SwapDesk — Operations · Merchan'!C27,'SwapDesk — Operations · Merchan'!C28) -> 252.9 | D26: =SUM('SwapDesk — Operations · Merchan'!D27,'SwapDesk — Operations · Merchan'!D28) -> 294.789 | E26: =SUM('SwapDesk — Operations · Merchan'!E27,'SwapDesk — Operations · Merchan'!E28) -> 335.69181 | F26: =SUM('SwapDesk — Operations · Merchan'!F27,'SwapDesk — Operations · Merchan'!F28) -> 375.63261 | G26: =SUM('SwapDesk — Operations · Merchan'!G27,'SwapDesk — Operations · Merchan'!G28) -> 414.63495 | H26: =SUM('SwapDesk — Operations · Merchan'!H27,'SwapDesk — Operations · Merchan'!H28) -> 452.72179 | I26: =SUM('SwapDesk — Operations · Merchan'!I27,'SwapDesk — Operations · Merchan'!I28) -> 489.91551 | ... Z26: =SUM('SwapDesk — Operations · Merchan'!Z27,'SwapDesk — Operations · Merchan'!Z28) -> 1004.7004
A27: Growing shop | B27: =0 -> 0 | C27: ='SwapDesk — Operations · Merchan'!C18*'SwapDesk — Assumptions · Mercha'!F5 -> 147.6 | D27: ='SwapDesk — Operations · Merchan'!D18*'SwapDesk — Assumptions · Mercha'!F5 -> 174.648 | E27: ='SwapDesk — Operations · Merchan'!E18*'SwapDesk — Assumptions · Mercha'!F5 -> 201.15504 | F27: ='SwapDesk — Operations · Merchan'!F18*'SwapDesk — Assumptions · Mercha'!F5 -> 227.13194 | G27: ='SwapDesk — Operations · Merchan'!G18*'SwapDesk — Assumptions · Mercha'!F5 -> 252.5893 | H27: ='SwapDesk — Operations · Merchan'!H18*'SwapDesk — Assumptions · Mercha'!F5 -> 277.53751 | I27: ='SwapDesk — Operations · Merchan'!I18*'SwapDesk — Assumptions · Mercha'!F5 -> 301.98676 | J27: ='SwapDesk — Operations · Merchan'!J18*'SwapDesk — Assumptions · Mercha'!F5 -> 325.94703 | K27: ='SwapDesk — Operations · Merchan'!K18*'SwapDesk — Assumptions · Mercha'!F5 -> 349.42809 | L27: ='SwapDesk — Operations · Merchan'!L18*'SwapDesk — Assumptions · Mercha'!F5 -> 372.43953 | M27: ='SwapDesk — Operations · Merchan'!M18*'SwapDesk — Assumptions · Mercha'!F5 -> 394.99074 | N27: ='SwapDesk — Operations · Merchan'!N18*'SwapDesk — Assumptions · Mercha'!F5 -> 417.09092 | O27: ='SwapDesk — Operations · Merchan'!O18*'SwapDesk — Assumptions · Mercha'!F5 -> 438.7491 | P27: ='SwapDesk — Operations · Merchan'!P18*'SwapDesk — Assumptions · Mercha'!F5 -> 459.97412 | Q27: ='SwapDesk — Operations · Merchan'!Q18*'SwapDesk — Assumptions · Mercha'!F5 -> 480.77464 | R27: ='SwapDesk — Operations · Merchan'!R18*'SwapDesk — Assumptions · Mercha'!F5 -> 501.15915 | S27: ='SwapDesk — Operations · Merchan'!S18*'SwapDesk — Assumptions · Mercha'!F5 -> 521.13596 | T27: ='SwapDesk — Operations · Merchan'!T18*'SwapDesk — Assumptions · Mercha'!F5 -> 540.71324 | U27: ='SwapDesk — Operations · Merchan'!U18*'SwapDesk — Assumptions · Mercha'!F5 -> 559.89898 | V27: ='SwapDesk — Operations · Merchan'!V18*'SwapDesk — Assumptions · Mercha'!F5 -> 578.701 | W27: ='SwapDesk — Operations · Merchan'!W18*'SwapDesk — Assumptions · Mercha'!F5 -> 597.12698 | X27: ='SwapDesk — Operations · Merchan'!X18*'SwapDesk — Assumptions · Mercha'!F5 -> 615.18444 | Y27: ='SwapDesk — Operations · Merchan'!Y18*'SwapDesk — Assumptions · Mercha'!F5 -> 632.88075 | Z27: ='SwapDesk — Operations · Merchan'!Z18*'SwapDesk — Assumptions · Mercha'!F5 -> 650.22314
A28: Small shop | B28: =0 -> 0 | C28: ='SwapDesk — Operations · Merchan'!C19*'SwapDesk — Assumptions · Mercha'!F6 -> 105.3 | D28: ='SwapDesk — Operations · Merchan'!D19*'SwapDesk — Assumptions · Mercha'!F6 -> 120.141 | E28: ='SwapDesk — Operations · Merchan'!E19*'SwapDesk — Assumptions · Mercha'!F6 -> 134.53677 | F28: ='SwapDesk — Operations · Merchan'!F19*'SwapDesk — Assumptions · Mercha'!F6 -> 148.50067 | G28: ='SwapDesk — Operations · Merchan'!G19*'SwapDesk — Assumptions · Mercha'!F6 -> 162.04565 | H28: ='SwapDesk — Operations · Merchan'!H19*'SwapDesk — Assumptions · Mercha'!F6 -> 175.18428 | I28: ='SwapDesk — Operations · Merchan'!I19*'SwapDesk — Assumptions · Mercha'!F6 -> 187.92875 | J28: ='SwapDesk — Operations · Merchan'!J19*'SwapDesk — Assumptions · Mercha'!F6 -> 200.29089 | K28: ='SwapDesk — Operations · Merchan'!K19*'SwapDesk — Assumptions · Mercha'!F6 -> 212.28216 | L28: ='SwapDesk — Operations · Merchan'!L19*'SwapDesk — Assumptions · Mercha'!F6 -> 223.9137 | M28: ='SwapDesk — Operations · Merchan'!M19*'SwapDesk — Assumptions · Mercha'!F6 -> 235.19628 | N28: ='SwapDesk — Operations · Merchan'!N19*'SwapDesk — Assumptions · Mercha'!F6 -> 246.1404 | O28: ='SwapDesk — Operations · Merchan'!O19*'SwapDesk — Assumptions · Mercha'!F6 -> 256.75618 | P28: ='SwapDesk — Operations · Merchan'!P19*'SwapDesk — Assumptions · Mercha'!F6 -> 267.0535 | Q28: ='SwapDesk — Operations · Merchan'!Q19*'SwapDesk — Assumptions · Mercha'!F6 -> 277.04189 | R28: ='SwapDesk — Operations · Merchan'!R19*'SwapDesk — Assumptions · Mercha'!F6 -> 286.73064 | S28: ='SwapDesk — Operations · Merchan'!S19*'SwapDesk — Assumptions · Mercha'!F6 -> 296.12872 | T28: ='SwapDesk — Operations · Merchan'!T19*'SwapDesk — Assumptions · Mercha'!F6 -> 305.24486 | U28: ='SwapDesk — Operations · Merchan'!U19*'SwapDesk — Assumptions · Mercha'!F6 -> 314.08751 | V28: ='SwapDesk — Operations · Merchan'!V19*'SwapDesk — Assumptions · Mercha'!F6 -> 322.66489 | W28: ='SwapDesk — Operations · Merchan'!W19*'SwapDesk — Assumptions · Mercha'!F6 -> 330.98494 | X28: ='SwapDesk — Operations · Merchan'!X19*'SwapDesk — Assumptions · Mercha'!F6 -> 339.05539 | Y28: ='SwapDesk — Operations · Merchan'!Y19*'SwapDesk — Assumptions · Mercha'!F6 -> 346.88373 | Z28: ='SwapDesk — Operations · Merchan'!Z19*'SwapDesk — Assumptions · Mercha'!F6 -> 354.47722
A29: Total executions | B29: =SUM('SwapDesk — Operations · Merchan'!B30,'SwapDesk — Operations · Merchan'!B31) -> 0 | C29: =SUM('SwapDesk — Operations · Merchan'!C30,'SwapDesk — Operations · Merchan'!C31) -> 1938.9 | D29: =SUM('SwapDesk — Operations · Merchan'!D30,'SwapDesk — Operations · Merchan'!D31) -> 2260.049 | E29: =SUM('SwapDesk — Operations · Merchan'!E30,'SwapDesk — Operations · Merchan'!E31) -> 2573.6372 | F29: =SUM('SwapDesk — Operations · Merchan'!F30,'SwapDesk — Operations · Merchan'!F31) -> 2879.85 | G29: =SUM('SwapDesk — Operations · Merchan'!G30,'SwapDesk — Operations · Merchan'!G31) -> 3178.8679 | H29: =SUM('SwapDesk — Operations · Merchan'!H30,'SwapDesk — Operations · Merchan'!H31) -> 3470.8671 | I29: =SUM('SwapDesk — Operations · Merchan'!I30,'SwapDesk — Operations · Merchan'!I31) -> 3756.0189 | ... Z29: =SUM('SwapDesk — Operations · Merchan'!Z30,'SwapDesk — Operations · Merchan'!Z31) -> 7702.7027
A30: Growing shop | B30: =0 -> 0 | C30: ='SwapDesk — Operations · Merchan'!C18+'SwapDesk — Operations · Merchan'!C27 -> 1131.6 | D30: ='SwapDesk — Operations · Merchan'!D18+'SwapDesk — Operations · Merchan'!D27 -> 1338.968 | E30: ='SwapDesk — Operations · Merchan'!E18+'SwapDesk — Operations · Merchan'!E27 -> 1542.1886 | F30: ='SwapDesk — Operations · Merchan'!F18+'SwapDesk — Operations · Merchan'!F27 -> 1741.3449 | G30: ='SwapDesk — Operations · Merchan'!G18+'SwapDesk — Operations · Merchan'!G27 -> 1936.518 | H30: ='SwapDesk — Operations · Merchan'!H18+'SwapDesk — Operations · Merchan'!H27 -> 2127.7876 | I30: ='SwapDesk — Operations · Merchan'!I18+'SwapDesk — Operations · Merchan'!I27 -> 2315.2319 | J30: ='SwapDesk — Operations · Merchan'!J18+'SwapDesk — Operations · Merchan'!J27 -> 2498.9272 | ... Z30: ='SwapDesk — Operations · Merchan'!Z18+'SwapDesk — Operations · Merchan'!Z27 -> 4985.044
A31: Small shop | B31: =0 -> 0 | C31: ='SwapDesk — Operations · Merchan'!C19+'SwapDesk — Operations · Merchan'!C28 -> 807.3 | D31: ='SwapDesk — Operations · Merchan'!D19+'SwapDesk — Operations · Merchan'!D28 -> 921.081 | E31: ='SwapDesk — Operations · Merchan'!E19+'SwapDesk — Operations · Merchan'!E28 -> 1031.4486 | F31: ='SwapDesk — Operations · Merchan'!F19+'SwapDesk — Operations · Merchan'!F28 -> 1138.5051 | G31: ='SwapDesk — Operations · Merchan'!G19+'SwapDesk — Operations · Merchan'!G28 -> 1242.35 | H31: ='SwapDesk — Operations · Merchan'!H19+'SwapDesk — Operations · Merchan'!H28 -> 1343.0795 | I31: ='SwapDesk — Operations · Merchan'!I19+'SwapDesk — Operations · Merchan'!I28 -> 1440.7871 | J31: ='SwapDesk — Operations · Merchan'!J19+'SwapDesk — Operations · Merchan'!J28 -> 1535.5635 | ... Z31: ='SwapDesk — Operations · Merchan'!Z19+'SwapDesk — Operations · Merchan'!Z28 -> 2717.6587
A32: Subscription revenue | B32: =SUM('SwapDesk — Operations · Merchan'!B33,'SwapDesk — Operations · Merchan'!B34) -> 0 | C32: =SUM('SwapDesk — Operations · Merchan'!C33,'SwapDesk — Operations · Merchan'!C34) -> 407.19 | D32: =SUM('SwapDesk — Operations · Merchan'!D33,'SwapDesk — Operations · Merchan'!D34) -> 469.6797 | E32: =SUM('SwapDesk — Operations · Merchan'!E33,'SwapDesk — Operations · Merchan'!E34) -> 530.5156 | F32: =SUM('SwapDesk — Operations · Merchan'!F33,'SwapDesk — Operations · Merchan'!F34) -> 589.7429 | G32: =SUM('SwapDesk — Operations · Merchan'!G33,'SwapDesk — Operations · Merchan'!G34) -> 647.40552 | H32: =SUM('SwapDesk — Operations · Merchan'!H33,'SwapDesk — Operations · Merchan'!H34) -> 703.54617 | I32: =SUM('SwapDesk — Operations · Merchan'!I33,'SwapDesk — Operations · Merchan'!I34) -> 758.20634 | ... Z32: =SUM('SwapDesk — Operations · Merchan'!Z33,'SwapDesk — Operations · Merchan'!Z34) -> 1495.9813
A33: Growing shop | B33: =0 -> 0 | C33: ='SwapDesk — Operations · Merchan'!C15*'SwapDesk — Assumptions · Commer'!B5 -> 120.54 | D33: ='SwapDesk — Operations · Merchan'!D15*'SwapDesk — Assumptions · Commer'!B5 -> 142.6292 | E33: ='SwapDesk — Operations · Merchan'!E15*'SwapDesk — Assumptions · Commer'!B5 -> 164.27662 | F33: ='SwapDesk — Operations · Merchan'!F15*'SwapDesk — Assumptions · Commer'!B5 -> 185.49108 | G33: ='SwapDesk — Operations · Merchan'!G15*'SwapDesk — Assumptions · Commer'!B5 -> 206.28126 | H33: ='SwapDesk — Operations · Merchan'!H15*'SwapDesk — Assumptions · Commer'!B5 -> 226.65564 | I33: ='SwapDesk — Operations · Merchan'!I15*'SwapDesk — Assumptions · Commer'!B5 -> 246.62252 | J33: ='SwapDesk — Operations · Merchan'!J15*'SwapDesk — Assumptions · Commer'!B5 -> 266.19007 | K33: ='SwapDesk — Operations · Merchan'!K15*'SwapDesk — Assumptions · Commer'!B5 -> 285.36627 | L33: ='SwapDesk — Operations · Merchan'!L15*'SwapDesk — Assumptions · Commer'!B5 -> 304.15895 | M33: ='SwapDesk — Operations · Merchan'!M15*'SwapDesk — Assumptions · Commer'!B5 -> 322.57577 | N33: ='SwapDesk — Operations · Merchan'!N15*'SwapDesk — Assumptions · Commer'!B5 -> 340.62425 | O33: ='SwapDesk — Operations · Merchan'!O15*'SwapDesk — Assumptions · Commer'!B5 -> 358.31177 | P33: ='SwapDesk — Operations · Merchan'!P15*'SwapDesk — Assumptions · Commer'!B5 -> 375.64553 | Q33: ='SwapDesk — Operations · Merchan'!Q15*'SwapDesk — Assumptions · Commer'!B5 -> 392.63262 | R33: ='SwapDesk — Operations · Merchan'!R15*'SwapDesk — Assumptions · Commer'!B5 -> 409.27997 | S33: ='SwapDesk — Operations · Merchan'!S15*'SwapDesk — Assumptions · Commer'!B5 -> 425.59437 | T33: ='SwapDesk — Operations · Merchan'!T15*'SwapDesk — Assumptions · Commer'!B5 -> 441.58248 | U33: ='SwapDesk — Operations · Merchan'!U15*'SwapDesk — Assumptions · Commer'!B5 -> 457.25083 | V33: ='SwapDesk — Operations · Merchan'!V15*'SwapDesk — Assumptions · Commer'!B5 -> 472.60582 | W33: ='SwapDesk — Operations · Merchan'!W15*'SwapDesk — Assumptions · Commer'!B5 -> 487.6537 | X33: ='SwapDesk — Operations · Merchan'!X15*'SwapDesk — Assumptions · Commer'!B5 -> 502.40063 | Y33: ='SwapDesk — Operations · Merchan'!Y15*'SwapDesk — Assumptions · Commer'!B5 -> 516.85261 | Z33: ='SwapDesk — Operations · Merchan'!Z15*'SwapDesk — Assumptions · Commer'!B5 -> 531.01556
A34: Small shop | B34: =0 -> 0 | C34: ='SwapDesk — Operations · Merchan'!C16*'SwapDesk — Assumptions · Commer'!B5 -> 286.65 | D34: ='SwapDesk — Operations · Merchan'!D16*'SwapDesk — Assumptions · Commer'!B5 -> 327.0505 | E34: ='SwapDesk — Operations · Merchan'!E16*'SwapDesk — Assumptions · Commer'!B5 -> 366.23899 | F34: ='SwapDesk — Operations · Merchan'!F16*'SwapDesk — Assumptions · Commer'!B5 -> 404.25182 | G34: ='SwapDesk — Operations · Merchan'!G16*'SwapDesk — Assumptions · Commer'!B5 -> 441.12426 | H34: ='SwapDesk — Operations · Merchan'!H16*'SwapDesk — Assumptions · Commer'!B5 -> 476.89053 | I34: ='SwapDesk — Operations · Merchan'!I16*'SwapDesk — Assumptions · Commer'!B5 -> 511.58382 | J34: ='SwapDesk — Operations · Merchan'!J16*'SwapDesk — Assumptions · Commer'!B5 -> 545.2363 | K34: ='SwapDesk — Operations · Merchan'!K16*'SwapDesk — Assumptions · Commer'!B5 -> 577.87921 | L34: ='SwapDesk — Operations · Merchan'!L16*'SwapDesk — Assumptions · Commer'!B5 -> 609.54284 | M34: ='SwapDesk — Operations · Merchan'!M16*'SwapDesk — Assumptions · Commer'!B5 -> 640.25655 | N34: ='SwapDesk — Operations · Merchan'!N16*'SwapDesk — Assumptions · Commer'!B5 -> 670.04886 | O34: ='SwapDesk — Operations · Merchan'!O16*'SwapDesk — Assumptions · Commer'!B5 -> 698.94739 | P34: ='SwapDesk — Operations · Merchan'!P16*'SwapDesk — Assumptions · Commer'!B5 -> 726.97897 | Q34: ='SwapDesk — Operations · Merchan'!Q16*'SwapDesk — Assumptions · Commer'!B5 -> 754.1696 | R34: ='SwapDesk — Operations · Merchan'!R16*'SwapDesk — Assumptions · Commer'!B5 -> 780.54451 | S34: ='SwapDesk — Operations · Merchan'!S16*'SwapDesk — Assumptions · Commer'!B5 -> 806.12818 | T34: ='SwapDesk — Operations · Merchan'!T16*'SwapDesk — Assumptions · Commer'!B5 -> 830.94433 | U34: ='SwapDesk — Operations · Merchan'!U16*'SwapDesk — Assumptions · Commer'!B5 -> 855.016 | V34: ='SwapDesk — Operations · Merchan'!V16*'SwapDesk — Assumptions · Commer'!B5 -> 878.36552 | W34: ='SwapDesk — Operations · Merchan'!W16*'SwapDesk — Assumptions · Commer'!B5 -> 901.01455 | X34: ='SwapDesk — Operations · Merchan'!X16*'SwapDesk — Assumptions · Commer'!B5 -> 922.98412 | Y34: ='SwapDesk — Operations · Merchan'!Y16*'SwapDesk — Assumptions · Commer'!B5 -> 944.29459 | Z34: ='SwapDesk — Operations · Merchan'!Z16*'SwapDesk — Assumptions · Commer'!B5 -> 964.96576
A35: Overage revenue | B35: =SUM('SwapDesk — Operations · Merchan'!B36,'SwapDesk — Operations · Merchan'!B37) -> 0 | C35: =SUM('SwapDesk — Operations · Merchan'!C36,'SwapDesk — Operations · Merchan'!C37) -> 196.8 | D35: =SUM('SwapDesk — Operations · Merchan'!D36,'SwapDesk — Operations · Merchan'!D37) -> 232.864 | E35: =SUM('SwapDesk — Operations · Merchan'!E36,'SwapDesk — Operations · Merchan'!E37) -> 268.20672 | F35: =SUM('SwapDesk — Operations · Merchan'!F36,'SwapDesk — Operations · Merchan'!F37) -> 302.84259 | G35: =SUM('SwapDesk — Operations · Merchan'!G36,'SwapDesk — Operations · Merchan'!G37) -> 336.78573 | H35: =SUM('SwapDesk — Operations · Merchan'!H36,'SwapDesk — Operations · Merchan'!H37) -> 370.05002 | I35: =SUM('SwapDesk — Operations · Merchan'!I36,'SwapDesk — Operations · Merchan'!I37) -> 402.64902 | ... Z35: =SUM('SwapDesk — Operations · Merchan'!Z36,'SwapDesk — Operations · Merchan'!Z37) -> 866.96418
A36: Growing shop | B36: =0 -> 0 | C36: ='SwapDesk — Operations · Merchan'!C15*MAX('SwapDesk — Assumptions · Mercha'!D5*'SwapDesk — Assumptions · Mercha'!E5-'SwapDesk — Assumptions · Commer'!B6,0)*'SwapDesk — Assumptions · Commer'!B7 -> 196.8 | D36: ='SwapDesk — Operations · Merchan'!D15*MAX('SwapDesk — Assumptions · Mercha'!D5*'SwapDesk — Assumptions · Mercha'!E5-'SwapDesk — Assumptions · Commer'!B6,0)*'SwapDesk — Assumptions · Commer'!B7 -> 232.864 | E36: ='SwapDesk — Operations · Merchan'!E15*MAX('SwapDesk — Assumptions · Mercha'!D5*'SwapDesk — Assumptions · Mercha'!E5-'SwapDesk — Assumptions · Commer'!B6,0)*'SwapDesk — Assumptions · Commer'!B7 -> 268.20672 | F36: ='SwapDesk — Operations · Merchan'!F15*MAX('SwapDesk — Assumptions · Mercha'!D5*'SwapDesk — Assumptions · Mercha'!E5-'SwapDesk — Assumptions · Commer'!B6,0)*'SwapDesk — Assumptions · Commer'!B7 -> 302.84259 | G36: ='SwapDesk — Operations · Merchan'!G15*MAX('SwapDesk — Assumptions · Mercha'!D5*'SwapDesk — Assumptions · Mercha'!E5-'SwapDesk — Assumptions · Commer'!B6,0)*'SwapDesk — Assumptions · Commer'!B7 -> 336.78573 | H36: ='SwapDesk — Operations · Merchan'!H15*MAX('SwapDesk — Assumptions · Mercha'!D5*'SwapDesk — Assumptions · Mercha'!E5-'SwapDesk — Assumptions · Commer'!B6,0)*'SwapDesk — Assumptions · Commer'!B7 -> 370.05002 | I36: ='SwapDesk — Operations · Merchan'!I15*MAX('SwapDesk — Assumptions · Mercha'!D5*'SwapDesk — Assumptions · Mercha'!E5-'SwapDesk — Assumptions · Commer'!B6,0)*'SwapDesk — Assumptions · Commer'!B7 -> 402.64902 | J36: ='SwapDesk — Operations · Merchan'!J15*MAX('SwapDesk — Assumptions · Mercha'!D5*'SwapDesk — Assumptions · Mercha'!E5-'SwapDesk — Assumptions · Commer'!B6,0)*'SwapDesk — Assumptions · Commer'!B7 -> 434.59604 | K36: ='SwapDesk — Operations · Merchan'!K15*MAX('SwapDesk — Assumptions · Mercha'!D5*'SwapDesk — Assumptions · Mercha'!E5-'SwapDesk — Assumptions · Commer'!B6,0)*'SwapDesk — Assumptions · Commer'!B7 -> 465.90412 | L36: ='SwapDesk — Operations · Merchan'!L15*MAX('SwapDesk — Assumptions · Mercha'!D5*'SwapDesk — Assumptions · Mercha'!E5-'SwapDesk — Assumptions · Commer'!B6,0)*'SwapDesk — Assumptions · Commer'!B7 -> 496.58604 | M36: ='SwapDesk — Operations · Merchan'!M15*MAX('SwapDesk — Assumptions · Mercha'!D5*'SwapDesk — Assumptions · Mercha'!E5-'SwapDesk — Assumptions · Commer'!B6,0)*'SwapDesk — Assumptions · Commer'!B7 -> 526.65431 | N36: ='SwapDesk — Operations · Merchan'!N15*MAX('SwapDesk — Assumptions · Mercha'!D5*'SwapDesk — Assumptions · Mercha'!E5-'SwapDesk — Assumptions · Commer'!B6,0)*'SwapDesk — Assumptions · Commer'!B7 -> 556.12123 | O36: ='SwapDesk — Operations · Merchan'!O15*MAX('SwapDesk — Assumptions · Mercha'!D5*'SwapDesk — Assumptions · Mercha'!E5-'SwapDesk — Assumptions · Commer'!B6,0)*'SwapDesk — Assumptions · Commer'!B7 -> 584.9988 | P36: ='SwapDesk — Operations · Merchan'!P15*MAX('SwapDesk — Assumptions · Mercha'!D5*'SwapDesk — Assumptions · Mercha'!E5-'SwapDesk — Assumptions · Commer'!B6,0)*'SwapDesk — Assumptions · Commer'!B7 -> 613.29883 | Q36: ='SwapDesk — Operations · Merchan'!Q15*MAX('SwapDesk — Assumptions · Mercha'!D5*'SwapDesk — Assumptions · Mercha'!E5-'SwapDesk — Assumptions · Commer'!B6,0)*'SwapDesk — Assumptions · Commer'!B7 -> 641.03285 | R36: ='SwapDesk — Operations · Merchan'!R15*MAX('SwapDesk — Assumptions · Mercha'!D5*'SwapDesk — Assumptions · Mercha'!E5-'SwapDesk — Assumptions · Commer'!B6,0)*'SwapDesk — Assumptions · Commer'!B7 -> 668.21219 | S36: ='SwapDesk — Operations · Merchan'!S15*MAX('SwapDesk — Assumptions · Mercha'!D5*'SwapDesk — Assumptions · Mercha'!E5-'SwapDesk — Assumptions · Commer'!B6,0)*'SwapDesk — Assumptions · Commer'!B7 -> 694.84795 | T36: ='SwapDesk — Operations · Merchan'!T15*MAX('SwapDesk — Assumptions · Mercha'!D5*'SwapDesk — Assumptions · Mercha'!E5-'SwapDesk — Assumptions · Commer'!B6,0)*'SwapDesk — Assumptions · Commer'!B7 -> 720.95099 | U36: ='SwapDesk — Operations · Merchan'!U15*MAX('SwapDesk — Assumptions · Mercha'!D5*'SwapDesk — Assumptions · Mercha'!E5-'SwapDesk — Assumptions · Commer'!B6,0)*'SwapDesk — Assumptions · Commer'!B7 -> 746.53197 | V36: ='SwapDesk — Operations · Merchan'!V15*MAX('SwapDesk — Assumptions · Mercha'!D5*'SwapDesk — Assumptions · Mercha'!E5-'SwapDesk — Assumptions · Commer'!B6,0)*'SwapDesk — Assumptions · Commer'!B7 -> 771.60133 | W36: ='SwapDesk — Operations · Merchan'!W15*MAX('SwapDesk — Assumptions · Mercha'!D5*'SwapDesk — Assumptions · Mercha'!E5-'SwapDesk — Assumptions · Commer'!B6,0)*'SwapDesk — Assumptions · Commer'!B7 -> 796.16931 | X36: ='SwapDesk — Operations · Merchan'!X15*MAX('SwapDesk — Assumptions · Mercha'!D5*'SwapDesk — Assumptions · Mercha'!E5-'SwapDesk — Assumptions · Commer'!B6,0)*'SwapDesk — Assumptions · Commer'!B7 -> 820.24592 | Y36: ='SwapDesk — Operations · Merchan'!Y15*MAX('SwapDesk — Assumptions · Mercha'!D5*'SwapDesk — Assumptions · Mercha'!E5-'SwapDesk — Assumptions · Commer'!B6,0)*'SwapDesk — Assumptions · Commer'!B7 -> 843.841 | Z36: ='SwapDesk — Operations · Merchan'!Z15*MAX('SwapDesk — Assumptions · Mercha'!D5*'SwapDesk — Assumptions · Mercha'!E5-'SwapDesk — Assumptions · Commer'!B6,0)*'SwapDesk — Assumptions · Commer'!B7 -> 866.96418
A37: Small shop | B37: =0 -> 0 | C37: ='SwapDesk — Operations · Merchan'!C16*MAX('SwapDesk — Assumptions · Mercha'!D6*'SwapDesk — Assumptions · Mercha'!E6-'SwapDesk — Assumptions · Commer'!B6,0)*'SwapDesk — Assumptions · Commer'!B7 -> 0 | D37: ='SwapDesk — Operations · Merchan'!D16*MAX('SwapDesk — Assumptions · Mercha'!D6*'SwapDesk — Assumptions · Mercha'!E6-'SwapDesk — Assumptions · Commer'!B6,0)*'SwapDesk — Assumptions · Commer'!B7 -> 0 | E37: ='SwapDesk — Operations · Merchan'!E16*MAX('SwapDesk — Assumptions · Mercha'!D6*'SwapDesk — Assumptions · Mercha'!E6-'SwapDesk — Assumptions · Commer'!B6,0)*'SwapDesk — Assumptions · Commer'!B7 -> 0 | F37: ='SwapDesk — Operations · Merchan'!F16*MAX('SwapDesk — Assumptions · Mercha'!D6*'SwapDesk — Assumptions · Mercha'!E6-'SwapDesk — Assumptions · Commer'!B6,0)*'SwapDesk — Assumptions · Commer'!B7 -> 0 | G37: ='SwapDesk — Operations · Merchan'!G16*MAX('SwapDesk — Assumptions · Mercha'!D6*'SwapDesk — Assumptions · Mercha'!E6-'SwapDesk — Assumptions · Commer'!B6,0)*'SwapDesk — Assumptions · Commer'!B7 -> 0 | H37: ='SwapDesk — Operations · Merchan'!H16*MAX('SwapDesk — Assumptions · Mercha'!D6*'SwapDesk — Assumptions · Mercha'!E6-'SwapDesk — Assumptions · Commer'!B6,0)*'SwapDesk — Assumptions · Commer'!B7 -> 0 | I37: ='SwapDesk — Operations · Merchan'!I16*MAX('SwapDesk — Assumptions · Mercha'!D6*'SwapDesk — Assumptions · Mercha'!E6-'SwapDesk — Assumptions · Commer'!B6,0)*'SwapDesk — Assumptions · Commer'!B7 -> 0 | J37: ='SwapDesk — Operations · Merchan'!J16*MAX('SwapDesk — Assumptions · Mercha'!D6*'SwapDesk — Assumptions · Mercha'!E6-'SwapDesk — Assumptions · Commer'!B6,0)*'SwapDesk — Assumptions · Commer'!B7 -> 0 | K37: ='SwapDesk — Operations · Merchan'!K16*MAX('SwapDesk — Assumptions · Mercha'!D6*'SwapDesk — Assumptions · Mercha'!E6-'SwapDesk — Assumptions · Commer'!B6,0)*'SwapDesk — Assumptions · Commer'!B7 -> 0 | L37: ='SwapDesk — Operations · Merchan'!L16*MAX('SwapDesk — Assumptions · Mercha'!D6*'SwapDesk — Assumptions · Mercha'!E6-'SwapDesk — Assumptions · Commer'!B6,0)*'SwapDesk — Assumptions · Commer'!B7 -> 0 | M37: ='SwapDesk — Operations · Merchan'!M16*MAX('SwapDesk — Assumptions · Mercha'!D6*'SwapDesk — Assumptions · Mercha'!E6-'SwapDesk — Assumptions · Commer'!B6,0)*'SwapDesk — Assumptions · Commer'!B7 -> 0 | N37: ='SwapDesk — Operations · Merchan'!N16*MAX('SwapDesk — Assumptions · Mercha'!D6*'SwapDesk — Assumptions · Mercha'!E6-'SwapDesk — Assumptions · Commer'!B6,0)*'SwapDesk — Assumptions · Commer'!B7 -> 0 | O37: ='SwapDesk — Operations · Merchan'!O16*MAX('SwapDesk — Assumptions · Mercha'!D6*'SwapDesk — Assumptions · Mercha'!E6-'SwapDesk — Assumptions · Commer'!B6,0)*'SwapDesk — Assumptions · Commer'!B7 -> 0 | P37: ='SwapDesk — Operations · Merchan'!P16*MAX('SwapDesk — Assumptions · Mercha'!D6*'SwapDesk — Assumptions · Mercha'!E6-'SwapDesk — Assumptions · Commer'!B6,0)*'SwapDesk — Assumptions · Commer'!B7 -> 0 | Q37: ='SwapDesk — Operations · Merchan'!Q16*MAX('SwapDesk — Assumptions · Mercha'!D6*'SwapDesk — Assumptions · Mercha'!E6-'SwapDesk — Assumptions · Commer'!B6,0)*'SwapDesk — Assumptions · Commer'!B7 -> 0 | R37: ='SwapDesk — Operations · Merchan'!R16*MAX('SwapDesk — Assumptions · Mercha'!D6*'SwapDesk — Assumptions · Mercha'!E6-'SwapDesk — Assumptions · Commer'!B6,0)*'SwapDesk — Assumptions · Commer'!B7 -> 0 | S37: ='SwapDesk — Operations · Merchan'!S16*MAX('SwapDesk — Assumptions · Mercha'!D6*'SwapDesk — Assumptions · Mercha'!E6-'SwapDesk — Assumptions · Commer'!B6,0)*'SwapDesk — Assumptions · Commer'!B7 -> 0 | T37: ='SwapDesk — Operations · Merchan'!T16*MAX('SwapDesk — Assumptions · Mercha'!D6*'SwapDesk — Assumptions · Mercha'!E6-'SwapDesk — Assumptions · Commer'!B6,0)*'SwapDesk — Assumptions · Commer'!B7 -> 0 | U37: ='SwapDesk — Operations · Merchan'!U16*MAX('SwapDesk — Assumptions · Mercha'!D6*'SwapDesk — Assumptions · Mercha'!E6-'SwapDesk — Assumptions · Commer'!B6,0)*'SwapDesk — Assumptions · Commer'!B7 -> 0 | V37: ='SwapDesk — Operations · Merchan'!V16*MAX('SwapDesk — Assumptions · Mercha'!D6*'SwapDesk — Assumptions · Mercha'!E6-'SwapDesk — Assumptions · Commer'!B6,0)*'SwapDesk — Assumptions · Commer'!B7 -> 0 | W37: ='SwapDesk — Operations · Merchan'!W16*MAX('SwapDesk — Assumptions · Mercha'!D6*'SwapDesk — Assumptions · Mercha'!E6-'SwapDesk — Assumptions · Commer'!B6,0)*'SwapDesk — Assumptions · Commer'!B7 -> 0 | X37: ='SwapDesk — Operations · Merchan'!X16*MAX('SwapDesk — Assumptions · Mercha'!D6*'SwapDesk — Assumptions · Mercha'!E6-'SwapDesk — Assumptions · Commer'!B6,0)*'SwapDesk — Assumptions · Commer'!B7 -> 0 | Y37: ='SwapDesk — Operations · Merchan'!Y16*MAX('SwapDesk — Assumptions · Mercha'!D6*'SwapDesk — Assumptions · Mercha'!E6-'SwapDesk — Assumptions · Commer'!B6,0)*'SwapDesk — Assumptions · Commer'!B7 -> 0 | Z37: ='SwapDesk — Operations · Merchan'!Z16*MAX('SwapDesk — Assumptions · Mercha'!D6*'SwapDesk — Assumptions · Mercha'!E6-'SwapDesk — Assumptions · Commer'!B6,0)*'SwapDesk — Assumptions · Commer'!B7 -> 0
A38: Revenue | B38: =SUM('SwapDesk — Operations · Merchan'!B39,'SwapDesk — Operations · Merchan'!B40) -> 0 | C38: =SUM('SwapDesk — Operations · Merchan'!C39,'SwapDesk — Operations · Merchan'!C40) -> 603.99 | D38: =SUM('SwapDesk — Operations · Merchan'!D39,'SwapDesk — Operations · Merchan'!D40) -> 702.5437 | E38: =SUM('SwapDesk — Operations · Merchan'!E39,'SwapDesk — Operations · Merchan'!E40) -> 798.72232 | F38: =SUM('SwapDesk — Operations · Merchan'!F39,'SwapDesk — Operations · Merchan'!F40) -> 892.58548 | G38: =SUM('SwapDesk — Operations · Merchan'!G39,'SwapDesk — Operations · Merchan'!G40) -> 984.19126 | H38: =SUM('SwapDesk — Operations · Merchan'!H39,'SwapDesk — Operations · Merchan'!H40) -> 1073.5962 | I38: =SUM('SwapDesk — Operations · Merchan'!I39,'SwapDesk — Operations · Merchan'!I40) -> 1160.8554 | ... Z38: =SUM('SwapDesk — Operations · Merchan'!Z39,'SwapDesk — Operations · Merchan'!Z40) -> 2362.9455
A39: Growing shop | B39: =0 -> 0 | C39: ='SwapDesk — Operations · Merchan'!C33+'SwapDesk — Operations · Merchan'!C36 -> 317.34 | D39: ='SwapDesk — Operations · Merchan'!D33+'SwapDesk — Operations · Merchan'!D36 -> 375.4932 | E39: ='SwapDesk — Operations · Merchan'!E33+'SwapDesk — Operations · Merchan'!E36 -> 432.48334 | F39: ='SwapDesk — Operations · Merchan'!F33+'SwapDesk — Operations · Merchan'!F36 -> 488.33367 | G39: ='SwapDesk — Operations · Merchan'!G33+'SwapDesk — Operations · Merchan'!G36 -> 543.067 | H39: ='SwapDesk — Operations · Merchan'!H33+'SwapDesk — Operations · Merchan'!H36 -> 596.70566 | I39: ='SwapDesk — Operations · Merchan'!I33+'SwapDesk — Operations · Merchan'!I36 -> 649.27154 | J39: ='SwapDesk — Operations · Merchan'!J33+'SwapDesk — Operations · Merchan'!J36 -> 700.78611 | ... Z39: ='SwapDesk — Operations · Merchan'!Z33+'SwapDesk — Operations · Merchan'!Z36 -> 1397.9797
A40: Small shop | B40: =0 -> 0 | C40: ='SwapDesk — Operations · Merchan'!C34+'SwapDesk — Operations · Merchan'!C37 -> 286.65 | D40: ='SwapDesk — Operations · Merchan'!D34+'SwapDesk — Operations · Merchan'!D37 -> 327.0505 | E40: ='SwapDesk — Operations · Merchan'!E34+'SwapDesk — Operations · Merchan'!E37 -> 366.23899 | F40: ='SwapDesk — Operations · Merchan'!F34+'SwapDesk — Operations · Merchan'!F37 -> 404.25182 | G40: ='SwapDesk — Operations · Merchan'!G34+'SwapDesk — Operations · Merchan'!G37 -> 441.12426 | H40: ='SwapDesk — Operations · Merchan'!H34+'SwapDesk — Operations · Merchan'!H37 -> 476.89053 | I40: ='SwapDesk — Operations · Merchan'!I34+'SwapDesk — Operations · Merchan'!I37 -> 511.58382 | J40: ='SwapDesk — Operations · Merchan'!J34+'SwapDesk — Operations · Merchan'!J37 -> 545.2363 | ... Z40: ='SwapDesk — Operations · Merchan'!Z34+'SwapDesk — Operations · Merchan'!Z37 -> 964.96576
A41: Inference cost | B41: =SUM('SwapDesk — Operations · Merchan'!B42,'SwapDesk — Operations · Merchan'!B43) -> 0 | C41: =SUM('SwapDesk — Operations · Merchan'!C42,'SwapDesk — Operations · Merchan'!C43) -> 58.167 | D41: =SUM('SwapDesk — Operations · Merchan'!D42,'SwapDesk — Operations · Merchan'!D43) -> 67.80147 | E41: =SUM('SwapDesk — Operations · Merchan'!E42,'SwapDesk — Operations · Merchan'!E43) -> 77.209116 | F41: =SUM('SwapDesk — Operations · Merchan'!F42,'SwapDesk — Operations · Merchan'!F43) -> 86.395499 | G41: =SUM('SwapDesk — Operations · Merchan'!G42,'SwapDesk — Operations · Merchan'!G43) -> 95.366038 | H41: =SUM('SwapDesk — Operations · Merchan'!H42,'SwapDesk — Operations · Merchan'!H43) -> 104.12601 | I41: =SUM('SwapDesk — Operations · Merchan'!I42,'SwapDesk — Operations · Merchan'!I43) -> 112.68057 | ... Z41: =SUM('SwapDesk — Operations · Merchan'!Z42,'SwapDesk — Operations · Merchan'!Z43) -> 231.08108
A42: Growing shop | B42: =0 -> 0 | C42: ='SwapDesk — Operations · Merchan'!C30*'SwapDesk — Assumptions · Commer'!B8 -> 33.948 | D42: ='SwapDesk — Operations · Merchan'!D30*'SwapDesk — Assumptions · Commer'!B8 -> 40.16904 | E42: ='SwapDesk — Operations · Merchan'!E30*'SwapDesk — Assumptions · Commer'!B8 -> 46.265659 | F42: ='SwapDesk — Operations · Merchan'!F30*'SwapDesk — Assumptions · Commer'!B8 -> 52.240346 | G42: ='SwapDesk — Operations · Merchan'!G30*'SwapDesk — Assumptions · Commer'!B8 -> 58.095539 | H42: ='SwapDesk — Operations · Merchan'!H30*'SwapDesk — Assumptions · Commer'!B8 -> 63.833628 | I42: ='SwapDesk — Operations · Merchan'!I30*'SwapDesk — Assumptions · Commer'!B8 -> 69.456956 | J42: ='SwapDesk — Operations · Merchan'!J30*'SwapDesk — Assumptions · Commer'!B8 -> 74.967817 | K42: ='SwapDesk — Operations · Merchan'!K30*'SwapDesk — Assumptions · Commer'!B8 -> 80.36846 | L42: ='SwapDesk — Operations · Merchan'!L30*'SwapDesk — Assumptions · Commer'!B8 -> 85.661091 | M42: ='SwapDesk — Operations · Merchan'!M30*'SwapDesk — Assumptions · Commer'!B8 -> 90.847869 | N42: ='SwapDesk — Operations · Merchan'!N30*'SwapDesk — Assumptions · Commer'!B8 -> 95.930912 | O42: ='SwapDesk — Operations · Merchan'!O30*'SwapDesk — Assumptions · Commer'!B8 -> 100.91229 | P42: ='SwapDesk — Operations · Merchan'!P30*'SwapDesk — Assumptions · Commer'!B8 -> 105.79405 | Q42: ='SwapDesk — Operations · Merchan'!Q30*'SwapDesk — Assumptions · Commer'!B8 -> 110.57817 | R42: ='SwapDesk — Operations · Merchan'!R30*'SwapDesk — Assumptions · Commer'!B8 -> 115.2666 | S42: ='SwapDesk — Operations · Merchan'!S30*'SwapDesk — Assumptions · Commer'!B8 -> 119.86127 | T42: ='SwapDesk — Operations · Merchan'!T30*'SwapDesk — Assumptions · Commer'!B8 -> 124.36405 | U42: ='SwapDesk — Operations · Merchan'!U30*'SwapDesk — Assumptions · Commer'!B8 -> 128.77677 | V42: ='SwapDesk — Operations · Merchan'!V30*'SwapDesk — Assumptions · Commer'!B8 -> 133.10123 | W42: ='SwapDesk — Operations · Merchan'!W30*'SwapDesk — Assumptions · Commer'!B8 -> 137.33921 | X42: ='SwapDesk — Operations · Merchan'!X30*'SwapDesk — Assumptions · Commer'!B8 -> 141.49242 | Y42: ='SwapDesk — Operations · Merchan'!Y30*'SwapDesk — Assumptions · Commer'!B8 -> 145.56257 | Z42: ='SwapDesk — Operations · Merchan'!Z30*'SwapDesk — Assumptions · Commer'!B8 -> 149.55132
A43: Small shop | B43: =0 -> 0 | C43: ='SwapDesk — Operations · Merchan'!C31*'SwapDesk — Assumptions · Commer'!B8 -> 24.219 | D43: ='SwapDesk — Operations · Merchan'!D31*'SwapDesk — Assumptions · Commer'!B8 -> 27.63243 | E43: ='SwapDesk — Operations · Merchan'!E31*'SwapDesk — Assumptions · Commer'!B8 -> 30.943457 | F43: ='SwapDesk — Operations · Merchan'!F31*'SwapDesk — Assumptions · Commer'!B8 -> 34.155153 | G43: ='SwapDesk — Operations · Merchan'!G31*'SwapDesk — Assumptions · Commer'!B8 -> 37.270499 | H43: ='SwapDesk — Operations · Merchan'!H31*'SwapDesk — Assumptions · Commer'!B8 -> 40.292384 | I43: ='SwapDesk — Operations · Merchan'!I31*'SwapDesk — Assumptions · Commer'!B8 -> 43.223612 | J43: ='SwapDesk — Operations · Merchan'!J31*'SwapDesk — Assumptions · Commer'!B8 -> 46.066904 | K43: ='SwapDesk — Operations · Merchan'!K31*'SwapDesk — Assumptions · Commer'!B8 -> 48.824897 | L43: ='SwapDesk — Operations · Merchan'!L31*'SwapDesk — Assumptions · Commer'!B8 -> 51.50015 | M43: ='SwapDesk — Operations · Merchan'!M31*'SwapDesk — Assumptions · Commer'!B8 -> 54.095145 | N43: ='SwapDesk — Operations · Merchan'!N31*'SwapDesk — Assumptions · Commer'!B8 -> 56.612291 | O43: ='SwapDesk — Operations · Merchan'!O31*'SwapDesk — Assumptions · Commer'!B8 -> 59.053922 | P43: ='SwapDesk — Operations · Merchan'!P31*'SwapDesk — Assumptions · Commer'!B8 -> 61.422305 | Q43: ='SwapDesk — Operations · Merchan'!Q31*'SwapDesk — Assumptions · Commer'!B8 -> 63.719636 | R43: ='SwapDesk — Operations · Merchan'!R31*'SwapDesk — Assumptions · Commer'!B8 -> 65.948046 | S43: ='SwapDesk — Operations · Merchan'!S31*'SwapDesk — Assumptions · Commer'!B8 -> 68.109605 | T43: ='SwapDesk — Operations · Merchan'!T31*'SwapDesk — Assumptions · Commer'!B8 -> 70.206317 | U43: ='SwapDesk — Operations · Merchan'!U31*'SwapDesk — Assumptions · Commer'!B8 -> 72.240127 | V43: ='SwapDesk — Operations · Merchan'!V31*'SwapDesk — Assumptions · Commer'!B8 -> 74.212924 | W43: ='SwapDesk — Operations · Merchan'!W31*'SwapDesk — Assumptions · Commer'!B8 -> 76.126536 | X43: ='SwapDesk — Operations · Merchan'!X31*'SwapDesk — Assumptions · Commer'!B8 -> 77.98274 | Y43: ='SwapDesk — Operations · Merchan'!Y31*'SwapDesk — Assumptions · Commer'!B8 -> 79.783258 | Z43: ='SwapDesk — Operations · Merchan'!Z31*'SwapDesk — Assumptions · Commer'!B8 -> 81.52976
A44: Infrastructure variable cost | B44: =SUM('SwapDesk — Operations · Merchan'!B45,'SwapDesk — Operations · Merchan'!B46) -> 0 | C44: =SUM('SwapDesk — Operations · Merchan'!C45,'SwapDesk — Operations · Merchan'!C46) -> 8.31 | D44: =SUM('SwapDesk — Operations · Merchan'!D45,'SwapDesk — Operations · Merchan'!D46) -> 9.5853 | E44: =SUM('SwapDesk — Operations · Merchan'!E45,'SwapDesk — Operations · Merchan'!E46) -> 10.826849 | F44: =SUM('SwapDesk — Operations · Merchan'!F45,'SwapDesk — Operations · Merchan'!F46) -> 12.035569 | G44: =SUM('SwapDesk — Operations · Merchan'!G45,'SwapDesk — Operations · Merchan'!G46) -> 13.212358 | H44: =SUM('SwapDesk — Operations · Merchan'!H45,'SwapDesk — Operations · Merchan'!H46) -> 14.358085 | I44: =SUM('SwapDesk — Operations · Merchan'!I45,'SwapDesk — Operations · Merchan'!I46) -> 15.473599 | ... Z44: =SUM('SwapDesk — Operations · Merchan'!Z45,'SwapDesk — Operations · Merchan'!Z46) -> 30.530231
A45: Growing shop | B45: =0 -> 0 | C45: ='SwapDesk — Operations · Merchan'!C15*'SwapDesk — Assumptions · Commer'!B13 -> 2.46 | D45: ='SwapDesk — Operations · Merchan'!D15*'SwapDesk — Assumptions · Commer'!B13 -> 2.9108 | E45: ='SwapDesk — Operations · Merchan'!E15*'SwapDesk — Assumptions · Commer'!B13 -> 3.352584 | F45: ='SwapDesk — Operations · Merchan'!F15*'SwapDesk — Assumptions · Commer'!B13 -> 3.7855323 | G45: ='SwapDesk — Operations · Merchan'!G15*'SwapDesk — Assumptions · Commer'!B13 -> 4.2098217 | H45: ='SwapDesk — Operations · Merchan'!H15*'SwapDesk — Assumptions · Commer'!B13 -> 4.6256252 | I45: ='SwapDesk — Operations · Merchan'!I15*'SwapDesk — Assumptions · Commer'!B13 -> 5.0331127 | J45: ='SwapDesk — Operations · Merchan'!J15*'SwapDesk — Assumptions · Commer'!B13 -> 5.4324505 | K45: ='SwapDesk — Operations · Merchan'!K15*'SwapDesk — Assumptions · Commer'!B13 -> 5.8238015 | L45: ='SwapDesk — Operations · Merchan'!L15*'SwapDesk — Assumptions · Commer'!B13 -> 6.2073254 | M45: ='SwapDesk — Operations · Merchan'!M15*'SwapDesk — Assumptions · Commer'!B13 -> 6.5831789 | N45: ='SwapDesk — Operations · Merchan'!N15*'SwapDesk — Assumptions · Commer'!B13 -> 6.9515154 | O45: ='SwapDesk — Operations · Merchan'!O15*'SwapDesk — Assumptions · Commer'!B13 -> 7.312485 | P45: ='SwapDesk — Operations · Merchan'!P15*'SwapDesk — Assumptions · Commer'!B13 -> 7.6662353 | Q45: ='SwapDesk — Operations · Merchan'!Q15*'SwapDesk — Assumptions · Commer'!B13 -> 8.0129106 | R45: ='SwapDesk — Operations · Merchan'!R15*'SwapDesk — Assumptions · Commer'!B13 -> 8.3526524 | S45: ='SwapDesk — Operations · Merchan'!S15*'SwapDesk — Assumptions · Commer'!B13 -> 8.6855994 | T45: ='SwapDesk — Operations · Merchan'!T15*'SwapDesk — Assumptions · Commer'!B13 -> 9.0118874 | U45: ='SwapDesk — Operations · Merchan'!U15*'SwapDesk — Assumptions · Commer'!B13 -> 9.3316496 | V45: ='SwapDesk — Operations · Merchan'!V15*'SwapDesk — Assumptions · Commer'!B13 -> 9.6450166 | W45: ='SwapDesk — Operations · Merchan'!W15*'SwapDesk — Assumptions · Commer'!B13 -> 9.9521163 | X45: ='SwapDesk — Operations · Merchan'!X15*'SwapDesk — Assumptions · Commer'!B13 -> 10.253074 | Y45: ='SwapDesk — Operations · Merchan'!Y15*'SwapDesk — Assumptions · Commer'!B13 -> 10.548013 | Z45: ='SwapDesk — Operations · Merchan'!Z15*'SwapDesk — Assumptions · Commer'!B13 -> 10.837052
A46: Small shop | B46: =0 -> 0 | C46: ='SwapDesk — Operations · Merchan'!C16*'SwapDesk — Assumptions · Commer'!B13 -> 5.85 | D46: ='SwapDesk — Operations · Merchan'!D16*'SwapDesk — Assumptions · Commer'!B13 -> 6.6745 | E46: ='SwapDesk — Operations · Merchan'!E16*'SwapDesk — Assumptions · Commer'!B13 -> 7.474265 | F46: ='SwapDesk — Operations · Merchan'!F16*'SwapDesk — Assumptions · Commer'!B13 -> 8.250037 | G46: ='SwapDesk — Operations · Merchan'!G16*'SwapDesk — Assumptions · Commer'!B13 -> 9.0025359 | H46: ='SwapDesk — Operations · Merchan'!H16*'SwapDesk — Assumptions · Commer'!B13 -> 9.7324599 | I46: ='SwapDesk — Operations · Merchan'!I16*'SwapDesk — Assumptions · Commer'!B13 -> 10.440486 | J46: ='SwapDesk — Operations · Merchan'!J16*'SwapDesk — Assumptions · Commer'!B13 -> 11.127271 | K46: ='SwapDesk — Operations · Merchan'!K16*'SwapDesk — Assumptions · Commer'!B13 -> 11.793453 | L46: ='SwapDesk — Operations · Merchan'!L16*'SwapDesk — Assumptions · Commer'!B13 -> 12.43965 | M46: ='SwapDesk — Operations · Merchan'!M16*'SwapDesk — Assumptions · Commer'!B13 -> 13.06646 | N46: ='SwapDesk — Operations · Merchan'!N16*'SwapDesk — Assumptions · Commer'!B13 -> 13.674466 | O46: ='SwapDesk — Operations · Merchan'!O16*'SwapDesk — Assumptions · Commer'!B13 -> 14.264232 | P46: ='SwapDesk — Operations · Merchan'!P16*'SwapDesk — Assumptions · Commer'!B13 -> 14.836305 | Q46: ='SwapDesk — Operations · Merchan'!Q16*'SwapDesk — Assumptions · Commer'!B13 -> 15.391216 | R46: ='SwapDesk — Operations · Merchan'!R16*'SwapDesk — Assumptions · Commer'!B13 -> 15.92948 | S46: ='SwapDesk — Operations · Merchan'!S16*'SwapDesk — Assumptions · Commer'!B13 -> 16.451595 | T46: ='SwapDesk — Operations · Merchan'!T16*'SwapDesk — Assumptions · Commer'!B13 -> 16.958048 | U46: ='SwapDesk — Operations · Merchan'!U16*'SwapDesk — Assumptions · Commer'!B13 -> 17.449306 | V46: ='SwapDesk — Operations · Merchan'!V16*'SwapDesk — Assumptions · Commer'!B13 -> 17.925827 | W46: ='SwapDesk — Operations · Merchan'!W16*'SwapDesk — Assumptions · Commer'!B13 -> 18.388052 | X46: ='SwapDesk — Operations · Merchan'!X16*'SwapDesk — Assumptions · Commer'!B13 -> 18.836411 | Y46: ='SwapDesk — Operations · Merchan'!Y16*'SwapDesk — Assumptions · Commer'!B13 -> 19.271318 | Z46: ='SwapDesk — Operations · Merchan'!Z16*'SwapDesk — Assumptions · Commer'!B13 -> 19.693179
A47: Merchant support cost | B47: =SUM('SwapDesk — Operations · Merchan'!B48,'SwapDesk — Operations · Merchan'!B49) -> 0 | C47: =SUM('SwapDesk — Operations · Merchan'!C48,'SwapDesk — Operations · Merchan'!C49) -> 67.3125 | D47: =SUM('SwapDesk — Operations · Merchan'!D48,'SwapDesk — Operations · Merchan'!D49) -> 78.100625 | E47: =SUM('SwapDesk — Operations · Merchan'!E48,'SwapDesk — Operations · Merchan'!E49) -> 88.621456 | F47: =SUM('SwapDesk — Operations · Merchan'!F48,'SwapDesk — Operations · Merchan'!F49) -> 98.881886 | G47: =SUM('SwapDesk — Operations · Merchan'!G48,'SwapDesk — Operations · Merchan'!G49) -> 108.88862 | H47: =SUM('SwapDesk — Operations · Merchan'!H48,'SwapDesk — Operations · Merchan'!H49) -> 118.64819 | I47: =SUM('SwapDesk — Operations · Merchan'!I48,'SwapDesk — Operations · Merchan'!I49) -> 128.16695 | ... Z47: =SUM('SwapDesk — Operations · Merchan'!Z48,'SwapDesk — Operations · Merchan'!Z49) -> 258.54552
A48: Growing shop | B48: =0 -> 0 | C48: ='SwapDesk — Operations · Merchan'!C15*'SwapDesk — Assumptions · Mercha'!G5/60*'SwapDesk — Assumptions · Commer'!B9 -> 30.75 | D48: ='SwapDesk — Operations · Merchan'!D15*'SwapDesk — Assumptions · Mercha'!G5/60*'SwapDesk — Assumptions · Commer'!B9 -> 36.385 | E48: ='SwapDesk — Operations · Merchan'!E15*'SwapDesk — Assumptions · Mercha'!G5/60*'SwapDesk — Assumptions · Commer'!B9 -> 41.9073 | F48: ='SwapDesk — Operations · Merchan'!F15*'SwapDesk — Assumptions · Mercha'!G5/60*'SwapDesk — Assumptions · Commer'!B9 -> 47.319154 | G48: ='SwapDesk — Operations · Merchan'!G15*'SwapDesk — Assumptions · Mercha'!G5/60*'SwapDesk — Assumptions · Commer'!B9 -> 52.622771 | H48: ='SwapDesk — Operations · Merchan'!H15*'SwapDesk — Assumptions · Mercha'!G5/60*'SwapDesk — Assumptions · Commer'!B9 -> 57.820316 | I48: ='SwapDesk — Operations · Merchan'!I15*'SwapDesk — Assumptions · Mercha'!G5/60*'SwapDesk — Assumptions · Commer'!B9 -> 62.913909 | J48: ='SwapDesk — Operations · Merchan'!J15*'SwapDesk — Assumptions · Mercha'!G5/60*'SwapDesk — Assumptions · Commer'!B9 -> 67.905631 | K48: ='SwapDesk — Operations · Merchan'!K15*'SwapDesk — Assumptions · Mercha'!G5/60*'SwapDesk — Assumptions · Commer'!B9 -> 72.797518 | L48: ='SwapDesk — Operations · Merchan'!L15*'SwapDesk — Assumptions · Mercha'!G5/60*'SwapDesk — Assumptions · Commer'!B9 -> 77.591568 | M48: ='SwapDesk — Operations · Merchan'!M15*'SwapDesk — Assumptions · Mercha'!G5/60*'SwapDesk — Assumptions · Commer'!B9 -> 82.289737 | N48: ='SwapDesk — Operations · Merchan'!N15*'SwapDesk — Assumptions · Mercha'!G5/60*'SwapDesk — Assumptions · Commer'!B9 -> 86.893942 | O48: ='SwapDesk — Operations · Merchan'!O15*'SwapDesk — Assumptions · Mercha'!G5/60*'SwapDesk — Assumptions · Commer'!B9 -> 91.406063 | P48: ='SwapDesk — Operations · Merchan'!P15*'SwapDesk — Assumptions · Mercha'!G5/60*'SwapDesk — Assumptions · Commer'!B9 -> 95.827942 | Q48: ='SwapDesk — Operations · Merchan'!Q15*'SwapDesk — Assumptions · Mercha'!G5/60*'SwapDesk — Assumptions · Commer'!B9 -> 100.16138 | R48: ='SwapDesk — Operations · Merchan'!R15*'SwapDesk — Assumptions · Mercha'!G5/60*'SwapDesk — Assumptions · Commer'!B9 -> 104.40816 | S48: ='SwapDesk — Operations · Merchan'!S15*'SwapDesk — Assumptions · Mercha'!G5/60*'SwapDesk — Assumptions · Commer'!B9 -> 108.56999 | T48: ='SwapDesk — Operations · Merchan'!T15*'SwapDesk — Assumptions · Mercha'!G5/60*'SwapDesk — Assumptions · Commer'!B9 -> 112.64859 | U48: ='SwapDesk — Operations · Merchan'!U15*'SwapDesk — Assumptions · Mercha'!G5/60*'SwapDesk — Assumptions · Commer'!B9 -> 116.64562 | V48: ='SwapDesk — Operations · Merchan'!V15*'SwapDesk — Assumptions · Mercha'!G5/60*'SwapDesk — Assumptions · Commer'!B9 -> 120.56271 | W48: ='SwapDesk — Operations · Merchan'!W15*'SwapDesk — Assumptions · Mercha'!G5/60*'SwapDesk — Assumptions · Commer'!B9 -> 124.40145 | X48: ='SwapDesk — Operations · Merchan'!X15*'SwapDesk — Assumptions · Mercha'!G5/60*'SwapDesk — Assumptions · Commer'!B9 -> 128.16342 | Y48: ='SwapDesk — Operations · Merchan'!Y15*'SwapDesk — Assumptions · Mercha'!G5/60*'SwapDesk — Assumptions · Commer'!B9 -> 131.85016 | Z48: ='SwapDesk — Operations · Merchan'!Z15*'SwapDesk — Assumptions · Mercha'!G5/60*'SwapDesk — Assumptions · Commer'!B9 -> 135.46315
A49: Small shop | B49: =0 -> 0 | C49: ='SwapDesk — Operations · Merchan'!C16*'SwapDesk — Assumptions · Mercha'!G6/60*'SwapDesk — Assumptions · Commer'!B9 -> 36.5625 | D49: ='SwapDesk — Operations · Merchan'!D16*'SwapDesk — Assumptions · Mercha'!G6/60*'SwapDesk — Assumptions · Commer'!B9 -> 41.715625 | E49: ='SwapDesk — Operations · Merchan'!E16*'SwapDesk — Assumptions · Mercha'!G6/60*'SwapDesk — Assumptions · Commer'!B9 -> 46.714156 | F49: ='SwapDesk — Operations · Merchan'!F16*'SwapDesk — Assumptions · Mercha'!G6/60*'SwapDesk — Assumptions · Commer'!B9 -> 51.562732 | G49: ='SwapDesk — Operations · Merchan'!G16*'SwapDesk — Assumptions · Mercha'!G6/60*'SwapDesk — Assumptions · Commer'!B9 -> 56.26585 | H49: ='SwapDesk — Operations · Merchan'!H16*'SwapDesk — Assumptions · Mercha'!G6/60*'SwapDesk — Assumptions · Commer'!B9 -> 60.827874 | I49: ='SwapDesk — Operations · Merchan'!I16*'SwapDesk — Assumptions · Mercha'!G6/60*'SwapDesk — Assumptions · Commer'!B9 -> 65.253038 | J49: ='SwapDesk — Operations · Merchan'!J16*'SwapDesk — Assumptions · Mercha'!G6/60*'SwapDesk — Assumptions · Commer'!B9 -> 69.545447 | K49: ='SwapDesk — Operations · Merchan'!K16*'SwapDesk — Assumptions · Mercha'!G6/60*'SwapDesk — Assumptions · Commer'!B9 -> 73.709083 | L49: ='SwapDesk — Operations · Merchan'!L16*'SwapDesk — Assumptions · Mercha'!G6/60*'SwapDesk — Assumptions · Commer'!B9 -> 77.747811 | M49: ='SwapDesk — Operations · Merchan'!M16*'SwapDesk — Assumptions · Mercha'!G6/60*'SwapDesk — Assumptions · Commer'!B9 -> 81.665377 | N49: ='SwapDesk — Operations · Merchan'!N16*'SwapDesk — Assumptions · Mercha'!G6/60*'SwapDesk — Assumptions · Commer'!B9 -> 85.465415 | O49: ='SwapDesk — Operations · Merchan'!O16*'SwapDesk — Assumptions · Mercha'!G6/60*'SwapDesk — Assumptions · Commer'!B9 -> 89.151453 | P49: ='SwapDesk — Operations · Merchan'!P16*'SwapDesk — Assumptions · Mercha'!G6/60*'SwapDesk — Assumptions · Commer'!B9 -> 92.726909 | Q49: ='SwapDesk — Operations · Merchan'!Q16*'SwapDesk — Assumptions · Mercha'!G6/60*'SwapDesk — Assumptions · Commer'!B9 -> 96.195102 | R49: ='SwapDesk — Operations · Merchan'!R16*'SwapDesk — Assumptions · Mercha'!G6/60*'SwapDesk — Assumptions · Commer'!B9 -> 99.559249 | S49: ='SwapDesk — Operations · Merchan'!S16*'SwapDesk — Assumptions · Mercha'!G6/60*'SwapDesk — Assumptions · Commer'!B9 -> 102.82247 | T49: ='SwapDesk — Operations · Merchan'!T16*'SwapDesk — Assumptions · Mercha'!G6/60*'SwapDesk — Assumptions · Commer'!B9 -> 105.9878 | U49: ='SwapDesk — Operations · Merchan'!U16*'SwapDesk — Assumptions · Mercha'!G6/60*'SwapDesk — Assumptions · Commer'!B9 -> 109.05816 | V49: ='SwapDesk — Operations · Merchan'!V16*'SwapDesk — Assumptions · Mercha'!G6/60*'SwapDesk — Assumptions · Commer'!B9 -> 112.03642 | W49: ='SwapDesk — Operations · Merchan'!W16*'SwapDesk — Assumptions · Mercha'!G6/60*'SwapDesk — Assumptions · Commer'!B9 -> 114.92533 | X49: ='SwapDesk — Operations · Merchan'!X16*'SwapDesk — Assumptions · Mercha'!G6/60*'SwapDesk — Assumptions · Commer'!B9 -> 117.72757 | Y49: ='SwapDesk — Operations · Merchan'!Y16*'SwapDesk — Assumptions · Mercha'!G6/60*'SwapDesk — Assumptions · Commer'!B9 -> 120.44574 | Z49: ='SwapDesk — Operations · Merchan'!Z16*'SwapDesk — Assumptions · Mercha'!G6/60*'SwapDesk — Assumptions · Commer'!B9 -> 123.08237
A50: Onboarding cost | B50: =SUM('SwapDesk — Operations · Merchan'!B51,'SwapDesk — Operations · Merchan'!B52) -> 0 | C50: =SUM('SwapDesk — Operations · Merchan'!C51,'SwapDesk — Operations · Merchan'!C52) -> 56.25 | D50: =SUM('SwapDesk — Operations · Merchan'!D51,'SwapDesk — Operations · Merchan'!D52) -> 56.25 | E50: =SUM('SwapDesk — Operations · Merchan'!E51,'SwapDesk — Operations · Merchan'!E52) -> 56.25 | F50: =SUM('SwapDesk — Operations · Merchan'!F51,'SwapDesk — Operations · Merchan'!F52) -> 56.25 | G50: =SUM('SwapDesk — Operations · Merchan'!G51,'SwapDesk — Operations · Merchan'!G52) -> 56.25 | H50: =SUM('SwapDesk — Operations · Merchan'!H51,'SwapDesk — Operations · Merchan'!H52) -> 56.25 | I50: =SUM('SwapDesk — Operations · Merchan'!I51,'SwapDesk — Operations · Merchan'!I52) -> 56.25 | ... Z50: =SUM('SwapDesk — Operations · Merchan'!Z51,'SwapDesk — Operations · Merchan'!Z52) -> 56.25
A51: Growing shop | B51: =0 -> 0 | C51: ='SwapDesk — Operations · Merchan'!C9*'SwapDesk — Assumptions · Commer'!B10/60*'SwapDesk — Assumptions · Commer'!B9 -> 18.75 | D51: ='SwapDesk — Operations · Merchan'!D9*'SwapDesk — Assumptions · Commer'!B10/60*'SwapDesk — Assumptions · Commer'!B9 -> 18.75 | E51: ='SwapDesk — Operations · Merchan'!E9*'SwapDesk — Assumptions · Commer'!B10/60*'SwapDesk — Assumptions · Commer'!B9 -> 18.75 | F51: ='SwapDesk — Operations · Merchan'!F9*'SwapDesk — Assumptions · Commer'!B10/60*'SwapDesk — Assumptions · Commer'!B9 -> 18.75 | G51: ='SwapDesk — Operations · Merchan'!G9*'SwapDesk — Assumptions · Commer'!B10/60*'SwapDesk — Assumptions · Commer'!B9 -> 18.75 | H51: ='SwapDesk — Operations · Merchan'!H9*'SwapDesk — Assumptions · Commer'!B10/60*'SwapDesk — Assumptions · Commer'!B9 -> 18.75 | I51: ='SwapDesk — Operations · Merchan'!I9*'SwapDesk — Assumptions · Commer'!B10/60*'SwapDesk — Assumptions · Commer'!B9 -> 18.75 | J51: ='SwapDesk — Operations · Merchan'!J9*'SwapDesk — Assumptions · Commer'!B10/60*'SwapDesk — Assumptions · Commer'!B9 -> 18.75 | K51: ='SwapDesk — Operations · Merchan'!K9*'SwapDesk — Assumptions · Commer'!B10/60*'SwapDesk — Assumptions · Commer'!B9 -> 18.75 | L51: ='SwapDesk — Operations · Merchan'!L9*'SwapDesk — Assumptions · Commer'!B10/60*'SwapDesk — Assumptions · Commer'!B9 -> 18.75 | M51: ='SwapDesk — Operations · Merchan'!M9*'SwapDesk — Assumptions · Commer'!B10/60*'SwapDesk — Assumptions · Commer'!B9 -> 18.75 | N51: ='SwapDesk — Operations · Merchan'!N9*'SwapDesk — Assumptions · Commer'!B10/60*'SwapDesk — Assumptions · Commer'!B9 -> 18.75 | O51: ='SwapDesk — Operations · Merchan'!O9*'SwapDesk — Assumptions · Commer'!B10/60*'SwapDesk — Assumptions · Commer'!B9 -> 18.75 | P51: ='SwapDesk — Operations · Merchan'!P9*'SwapDesk — Assumptions · Commer'!B10/60*'SwapDesk — Assumptions · Commer'!B9 -> 18.75 | Q51: ='SwapDesk — Operations · Merchan'!Q9*'SwapDesk — Assumptions · Commer'!B10/60*'SwapDesk — Assumptions · Commer'!B9 -> 18.75 | R51: ='SwapDesk — Operations · Merchan'!R9*'SwapDesk — Assumptions · Commer'!B10/60*'SwapDesk — Assumptions · Commer'!B9 -> 18.75 | S51: ='SwapDesk — Operations · Merchan'!S9*'SwapDesk — Assumptions · Commer'!B10/60*'SwapDesk — Assumptions · Commer'!B9 -> 18.75 | T51: ='SwapDesk — Operations · Merchan'!T9*'SwapDesk — Assumptions · Commer'!B10/60*'SwapDesk — Assumptions · Commer'!B9 -> 18.75 | U51: ='SwapDesk — Operations · Merchan'!U9*'SwapDesk — Assumptions · Commer'!B10/60*'SwapDesk — Assumptions · Commer'!B9 -> 18.75 | V51: ='SwapDesk — Operations · Merchan'!V9*'SwapDesk — Assumptions · Commer'!B10/60*'SwapDesk — Assumptions · Commer'!B9 -> 18.75 | W51: ='SwapDesk — Operations · Merchan'!W9*'SwapDesk — Assumptions · Commer'!B10/60*'SwapDesk — Assumptions · Commer'!B9 -> 18.75 | X51: ='SwapDesk — Operations · Merchan'!X9*'SwapDesk — Assumptions · Commer'!B10/60*'SwapDesk — Assumptions · Commer'!B9 -> 18.75 | Y51: ='SwapDesk — Operations · Merchan'!Y9*'SwapDesk — Assumptions · Commer'!B10/60*'SwapDesk — Assumptions · Commer'!B9 -> 18.75 | Z51: ='SwapDesk — Operations · Merchan'!Z9*'SwapDesk — Assumptions · Commer'!B10/60*'SwapDesk — Assumptions · Commer'!B9 -> 18.75
A52: Small shop | B52: =0 -> 0 | C52: ='SwapDesk — Operations · Merchan'!C10*'SwapDesk — Assumptions · Commer'!B10/60*'SwapDesk — Assumptions · Commer'!B9 -> 37.5 | D52: ='SwapDesk — Operations · Merchan'!D10*'SwapDesk — Assumptions · Commer'!B10/60*'SwapDesk — Assumptions · Commer'!B9 -> 37.5 | E52: ='SwapDesk — Operations · Merchan'!E10*'SwapDesk — Assumptions · Commer'!B10/60*'SwapDesk — Assumptions · Commer'!B9 -> 37.5 | F52: ='SwapDesk — Operations · Merchan'!F10*'SwapDesk — Assumptions · Commer'!B10/60*'SwapDesk — Assumptions · Commer'!B9 -> 37.5 | G52: ='SwapDesk — Operations · Merchan'!G10*'SwapDesk — Assumptions · Commer'!B10/60*'SwapDesk — Assumptions · Commer'!B9 -> 37.5 | H52: ='SwapDesk — Operations · Merchan'!H10*'SwapDesk — Assumptions · Commer'!B10/60*'SwapDesk — Assumptions · Commer'!B9 -> 37.5 | I52: ='SwapDesk — Operations · Merchan'!I10*'SwapDesk — Assumptions · Commer'!B10/60*'SwapDesk — Assumptions · Commer'!B9 -> 37.5 | J52: ='SwapDesk — Operations · Merchan'!J10*'SwapDesk — Assumptions · Commer'!B10/60*'SwapDesk — Assumptions · Commer'!B9 -> 37.5 | K52: ='SwapDesk — Operations · Merchan'!K10*'SwapDesk — Assumptions · Commer'!B10/60*'SwapDesk — Assumptions · Commer'!B9 -> 37.5 | L52: ='SwapDesk — Operations · Merchan'!L10*'SwapDesk — Assumptions · Commer'!B10/60*'SwapDesk — Assumptions · Commer'!B9 -> 37.5 | M52: ='SwapDesk — Operations · Merchan'!M10*'SwapDesk — Assumptions · Commer'!B10/60*'SwapDesk — Assumptions · Commer'!B9 -> 37.5 | N52: ='SwapDesk — Operations · Merchan'!N10*'SwapDesk — Assumptions · Commer'!B10/60*'SwapDesk — Assumptions · Commer'!B9 -> 37.5 | O52: ='SwapDesk — Operations · Merchan'!O10*'SwapDesk — Assumptions · Commer'!B10/60*'SwapDesk — Assumptions · Commer'!B9 -> 37.5 | P52: ='SwapDesk — Operations · Merchan'!P10*'SwapDesk — Assumptions · Commer'!B10/60*'SwapDesk — Assumptions · Commer'!B9 -> 37.5 | Q52: ='SwapDesk — Operations · Merchan'!Q10*'SwapDesk — Assumptions · Commer'!B10/60*'SwapDesk — Assumptions · Commer'!B9 -> 37.5 | R52: ='SwapDesk — Operations · Merchan'!R10*'SwapDesk — Assumptions · Commer'!B10/60*'SwapDesk — Assumptions · Commer'!B9 -> 37.5 | S52: ='SwapDesk — Operations · Merchan'!S10*'SwapDesk — Assumptions · Commer'!B10/60*'SwapDesk — Assumptions · Commer'!B9 -> 37.5 | T52: ='SwapDesk — Operations · Merchan'!T10*'SwapDesk — Assumptions · Commer'!B10/60*'SwapDesk — Assumptions · Commer'!B9 -> 37.5 | U52: ='SwapDesk — Operations · Merchan'!U10*'SwapDesk — Assumptions · Commer'!B10/60*'SwapDesk — Assumptions · Commer'!B9 -> 37.5 | V52: ='SwapDesk — Operations · Merchan'!V10*'SwapDesk — Assumptions · Commer'!B10/60*'SwapDesk — Assumptions · Commer'!B9 -> 37.5 | W52: ='SwapDesk — Operations · Merchan'!W10*'SwapDesk — Assumptions · Commer'!B10/60*'SwapDesk — Assumptions · Commer'!B9 -> 37.5 | X52: ='SwapDesk — Operations · Merchan'!X10*'SwapDesk — Assumptions · Commer'!B10/60*'SwapDesk — Assumptions · Commer'!B9 -> 37.5 | Y52: ='SwapDesk — Operations · Merchan'!Y10*'SwapDesk — Assumptions · Commer'!B10/60*'SwapDesk — Assumptions · Commer'!B9 -> 37.5 | Z52: ='SwapDesk — Operations · Merchan'!Z10*'SwapDesk — Assumptions · Commer'!B10/60*'SwapDesk — Assumptions · Commer'!B9 -> 37.5
A53: Acquisition spending | B53: =SUM('SwapDesk — Operations · Merchan'!B54,'SwapDesk — Operations · Merchan'!B55) -> 0 | C53: =SUM('SwapDesk — Operations · Merchan'!C54,'SwapDesk — Operations · Merchan'!C55) -> 150 | D53: =SUM('SwapDesk — Operations · Merchan'!D54,'SwapDesk — Operations · Merchan'!D55) -> 150 | E53: =SUM('SwapDesk — Operations · Merchan'!E54,'SwapDesk — Operations · Merchan'!E55) -> 150 | F53: =SUM('SwapDesk — Operations · Merchan'!F54,'SwapDesk — Operations · Merchan'!F55) -> 150 | G53: =SUM('SwapDesk — Operations · Merchan'!G54,'SwapDesk — Operations · Merchan'!G55) -> 150 | H53: =SUM('SwapDesk — Operations · Merchan'!H54,'SwapDesk — Operations · Merchan'!H55) -> 150 | I53: =SUM('SwapDesk — Operations · Merchan'!I54,'SwapDesk — Operations · Merchan'!I55) -> 150 | ... Z53: =SUM('SwapDesk — Operations · Merchan'!Z54,'SwapDesk — Operations · Merchan'!Z55) -> 150
A54: Growing shop | B54: =0 -> 0 | C54: ='SwapDesk — Operations · Merchan'!C9*'SwapDesk — Assumptions · Commer'!B11 -> 50 | D54: ='SwapDesk — Operations · Merchan'!D9*'SwapDesk — Assumptions · Commer'!B11 -> 50 | E54: ='SwapDesk — Operations · Merchan'!E9*'SwapDesk — Assumptions · Commer'!B11 -> 50 | F54: ='SwapDesk — Operations · Merchan'!F9*'SwapDesk — Assumptions · Commer'!B11 -> 50 | G54: ='SwapDesk — Operations · Merchan'!G9*'SwapDesk — Assumptions · Commer'!B11 -> 50 | H54: ='SwapDesk — Operations · Merchan'!H9*'SwapDesk — Assumptions · Commer'!B11 -> 50 | I54: ='SwapDesk — Operations · Merchan'!I9*'SwapDesk — Assumptions · Commer'!B11 -> 50 | J54: ='SwapDesk — Operations · Merchan'!J9*'SwapDesk — Assumptions · Commer'!B11 -> 50 | K54: ='SwapDesk — Operations · Merchan'!K9*'SwapDesk — Assumptions · Commer'!B11 -> 50 | L54: ='SwapDesk — Operations · Merchan'!L9*'SwapDesk — Assumptions · Commer'!B11 -> 50 | M54: ='SwapDesk — Operations · Merchan'!M9*'SwapDesk — Assumptions · Commer'!B11 -> 50 | N54: ='SwapDesk — Operations · Merchan'!N9*'SwapDesk — Assumptions · Commer'!B11 -> 50 | O54: ='SwapDesk — Operations · Merchan'!O9*'SwapDesk — Assumptions · Commer'!B11 -> 50 | P54: ='SwapDesk — Operations · Merchan'!P9*'SwapDesk — Assumptions · Commer'!B11 -> 50 | Q54: ='SwapDesk — Operations · Merchan'!Q9*'SwapDesk — Assumptions · Commer'!B11 -> 50 | R54: ='SwapDesk — Operations · Merchan'!R9*'SwapDesk — Assumptions · Commer'!B11 -> 50 | S54: ='SwapDesk — Operations · Merchan'!S9*'SwapDesk — Assumptions · Commer'!B11 -> 50 | T54: ='SwapDesk — Operations · Merchan'!T9*'SwapDesk — Assumptions · Commer'!B11 -> 50 | U54: ='SwapDesk — Operations · Merchan'!U9*'SwapDesk — Assumptions · Commer'!B11 -> 50 | V54: ='SwapDesk — Operations · Merchan'!V9*'SwapDesk — Assumptions · Commer'!B11 -> 50 | W54: ='SwapDesk — Operations · Merchan'!W9*'SwapDesk — Assumptions · Commer'!B11 -> 50 | X54: ='SwapDesk — Operations · Merchan'!X9*'SwapDesk — Assumptions · Commer'!B11 -> 50 | Y54: ='SwapDesk — Operations · Merchan'!Y9*'SwapDesk — Assumptions · Commer'!B11 -> 50 | Z54: ='SwapDesk — Operations · Merchan'!Z9*'SwapDesk — Assumptions · Commer'!B11 -> 50
A55: Small shop | B55: =0 -> 0 | C55: ='SwapDesk — Operations · Merchan'!C10*'SwapDesk — Assumptions · Commer'!B11 -> 100 | D55: ='SwapDesk — Operations · Merchan'!D10*'SwapDesk — Assumptions · Commer'!B11 -> 100 | E55: ='SwapDesk — Operations · Merchan'!E10*'SwapDesk — Assumptions · Commer'!B11 -> 100 | F55: ='SwapDesk — Operations · Merchan'!F10*'SwapDesk — Assumptions · Commer'!B11 -> 100 | G55: ='SwapDesk — Operations · Merchan'!G10*'SwapDesk — Assumptions · Commer'!B11 -> 100 | H55: ='SwapDesk — Operations · Merchan'!H10*'SwapDesk — Assumptions · Commer'!B11 -> 100 | I55: ='SwapDesk — Operations · Merchan'!I10*'SwapDesk — Assumptions · Commer'!B11 -> 100 | J55: ='SwapDesk — Operations · Merchan'!J10*'SwapDesk — Assumptions · Commer'!B11 -> 100 | K55: ='SwapDesk — Operations · Merchan'!K10*'SwapDesk — Assumptions · Commer'!B11 -> 100 | L55: ='SwapDesk — Operations · Merchan'!L10*'SwapDesk — Assumptions · Commer'!B11 -> 100 | M55: ='SwapDesk — Operations · Merchan'!M10*'SwapDesk — Assumptions · Commer'!B11 -> 100 | N55: ='SwapDesk — Operations · Merchan'!N10*'SwapDesk — Assumptions · Commer'!B11 -> 100 | O55: ='SwapDesk — Operations · Merchan'!O10*'SwapDesk — Assumptions · Commer'!B11 -> 100 | P55: ='SwapDesk — Operations · Merchan'!P10*'SwapDesk — Assumptions · Commer'!B11 -> 100 | Q55: ='SwapDesk — Operations · Merchan'!Q10*'SwapDesk — Assumptions · Commer'!B11 -> 100 | R55: ='SwapDesk — Operations · Merchan'!R10*'SwapDesk — Assumptions · Commer'!B11 -> 100 | S55: ='SwapDesk — Operations · Merchan'!S10*'SwapDesk — Assumptions · Commer'!B11 -> 100 | T55: ='SwapDesk — Operations · Merchan'!T10*'SwapDesk — Assumptions · Commer'!B11 -> 100 | U55: ='SwapDesk — Operations · Merchan'!U10*'SwapDesk — Assumptions · Commer'!B11 -> 100 | V55: ='SwapDesk — Operations · Merchan'!V10*'SwapDesk — Assumptions · Commer'!B11 -> 100 | W55: ='SwapDesk — Operations · Merchan'!W10*'SwapDesk — Assumptions · Commer'!B11 -> 100 | X55: ='SwapDesk — Operations · Merchan'!X10*'SwapDesk — Assumptions · Commer'!B11 -> 100 | Y55: ='SwapDesk — Operations · Merchan'!Y10*'SwapDesk — Assumptions · Commer'!B11 -> 100 | Z55: ='SwapDesk — Operations · Merchan'!Z10*'SwapDesk — Assumptions · Commer'!B11 -> 100

Sheet SwapDesk — Operations · Unit ec
A1: SwapDesk — Operations · Unit economics by merchant segment
A2: Financial model (4 pages) · Main Scenario
A4: Variable / dimension | B4: 2026-10 | C4: 2026-11 | D4: 2026-12 | E4: 2027-01 | F4: 2027-02 | G4: 2027-03 | H4: 2027-04 | I4: 2027-05 | J4: 2027-06 | K4: 2027-07 | L4: 2027-08 | M4: 2027-09 | N4: 2027-10 | O4: 2027-11 | P4: 2027-12 | Q4: 2028-01 | R4: 2028-02 | S4: 2028-03 | T4: 2028-04 | U4: 2028-05 | V4: 2028-06 | W4: 2028-07 | X4: 2028-08 | Y4: 2028-09
A5: Revenue per store | B5: =IFERROR('SwapDesk — Operations · Merchan'!C38/'SwapDesk — Operations · Merchan'!C14,"") -> 72.68231 | C5: =IFERROR('SwapDesk — Operations · Merchan'!D38/'SwapDesk — Operations · Merchan'!D14,"") -> 73.293867 | D5: =IFERROR('SwapDesk — Operations · Merchan'!E38/'SwapDesk — Operations · Merchan'!E14,"") -> 73.772371 | E5: =IFERROR('SwapDesk — Operations · Merchan'!F38/'SwapDesk — Operations · Merchan'!F14,"") -> 74.162298 | F5: =IFERROR('SwapDesk — Operations · Merchan'!G38/'SwapDesk — Operations · Merchan'!G14,"") -> 74.490207 | G5: =IFERROR('SwapDesk — Operations · Merchan'!H38/'SwapDesk — Operations · Merchan'!H14,"") -> 74.772937 | H5: =IFERROR('SwapDesk — Operations · Merchan'!I38/'SwapDesk — Operations · Merchan'!I14,"") -> 75.021679 | I5: =IFERROR('SwapDesk — Operations · Merchan'!J38/'SwapDesk — Operations · Merchan'!J14,"") -> 75.244163 | ... Y5: =IFERROR('SwapDesk — Operations · Merchan'!Z38/'SwapDesk — Operations · Merchan'!Z14,"") -> 77.396909
A6: Growing shop | B6: =IFERROR('SwapDesk — Operations · Merchan'!C39/'SwapDesk — Operations · Merchan'!C15,"") -> 129 | C6: =IFERROR('SwapDesk — Operations · Merchan'!D39/'SwapDesk — Operations · Merchan'!D15,"") -> 129 | D6: =IFERROR('SwapDesk — Operations · Merchan'!E39/'SwapDesk — Operations · Merchan'!E15,"") -> 129 | E6: =IFERROR('SwapDesk — Operations · Merchan'!F39/'SwapDesk — Operations · Merchan'!F15,"") -> 129 | F6: =IFERROR('SwapDesk — Operations · Merchan'!G39/'SwapDesk — Operations · Merchan'!G15,"") -> 129 | G6: =IFERROR('SwapDesk — Operations · Merchan'!H39/'SwapDesk — Operations · Merchan'!H15,"") -> 129 | H6: =IFERROR('SwapDesk — Operations · Merchan'!I39/'SwapDesk — Operations · Merchan'!I15,"") -> 129 | I6: =IFERROR('SwapDesk — Operations · Merchan'!J39/'SwapDesk — Operations · Merchan'!J15,"") -> 129 | ... Y6: =IFERROR('SwapDesk — Operations · Merchan'!Z39/'SwapDesk — Operations · Merchan'!Z15,"") -> 129
A7: Small shop | B7: =IFERROR('SwapDesk — Operations · Merchan'!C40/'SwapDesk — Operations · Merchan'!C16,"") -> 49 | C7: =IFERROR('SwapDesk — Operations · Merchan'!D40/'SwapDesk — Operations · Merchan'!D16,"") -> 49 | D7: =IFERROR('SwapDesk — Operations · Merchan'!E40/'SwapDesk — Operations · Merchan'!E16,"") -> 49 | E7: =IFERROR('SwapDesk — Operations · Merchan'!F40/'SwapDesk — Operations · Merchan'!F16,"") -> 49 | F7: =IFERROR('SwapDesk — Operations · Merchan'!G40/'SwapDesk — Operations · Merchan'!G16,"") -> 49 | G7: =IFERROR('SwapDesk — Operations · Merchan'!H40/'SwapDesk — Operations · Merchan'!H16,"") -> 49 | H7: =IFERROR('SwapDesk — Operations · Merchan'!I40/'SwapDesk — Operations · Merchan'!I16,"") -> 49 | I7: =IFERROR('SwapDesk — Operations · Merchan'!J40/'SwapDesk — Operations · Merchan'!J16,"") -> 49 | ... Y7: =IFERROR('SwapDesk — Operations · Merchan'!Z40/'SwapDesk — Operations · Merchan'!Z16,"") -> 49
A8: Recurring contribution per store | B8: =IFERROR(('SwapDesk — Operations · Merchan'!C38-'SwapDesk — Operations · Merchan'!C41-'SwapDesk — Operations · Merchan'!C44-'SwapDesk — Operations · Merchan'!C47)/'SwapDesk — Operations · Merchan'!C14,"") -> 56.582491 | C8: =IFERROR(('SwapDesk — Operations · Merchan'!D38-'SwapDesk — Operations · Merchan'!D41-'SwapDesk — Operations · Merchan'!D44-'SwapDesk — Operations · Merchan'!D47)/'SwapDesk — Operations · Merchan'!D14,"") -> 57.072424 | D8: =IFERROR(('SwapDesk — Operations · Merchan'!E38-'SwapDesk — Operations · Merchan'!E41-'SwapDesk — Operations · Merchan'!E44-'SwapDesk — Operations · Merchan'!E47)/'SwapDesk — Operations · Merchan'!E14,"") -> 57.455766 | E8: =IFERROR(('SwapDesk — Operations · Merchan'!F38-'SwapDesk — Operations · Merchan'!F41-'SwapDesk — Operations · Merchan'!F44-'SwapDesk — Operations · Merchan'!F47)/'SwapDesk — Operations · Merchan'!F14,"") -> 57.768146 | F8: =IFERROR(('SwapDesk — Operations · Merchan'!G38-'SwapDesk — Operations · Merchan'!G41-'SwapDesk — Operations · Merchan'!G44-'SwapDesk — Operations · Merchan'!G47)/'SwapDesk — Operations · Merchan'!G14,"") -> 58.030842 | G8: =IFERROR(('SwapDesk — Operations · Merchan'!H38-'SwapDesk — Operations · Merchan'!H41-'SwapDesk — Operations · Merchan'!H44-'SwapDesk — Operations · Merchan'!H47)/'SwapDesk — Operations · Merchan'!H14,"") -> 58.257344 | H8: =IFERROR(('SwapDesk — Operations · Merchan'!I38-'SwapDesk — Operations · Merchan'!I41-'SwapDesk — Operations · Merchan'!I44-'SwapDesk — Operations · Merchan'!I47)/'SwapDesk — Operations · Merchan'!I14,"") -> 58.456617 | I8: =IFERROR(('SwapDesk — Operations · Merchan'!J38-'SwapDesk — Operations · Merchan'!J41-'SwapDesk — Operations · Merchan'!J44-'SwapDesk — Operations · Merchan'!J47)/'SwapDesk — Operations · Merchan'!J14,"") -> 58.634855 | ... Y8: =IFERROR(('SwapDesk — Operations · Merchan'!Z38-'SwapDesk — Operations · Merchan'!Z41-'SwapDesk — Operations · Merchan'!Z44-'SwapDesk — Operations · Merchan'!Z47)/'SwapDesk — Operations · Merchan'!Z14,"") -> 60.359473
A9: Growing shop | B9: =IFERROR(('SwapDesk — Operations · Merchan'!C39-'SwapDesk — Operations · Merchan'!C42-'SwapDesk — Operations · Merchan'!C45-'SwapDesk — Operations · Merchan'!C48)/'SwapDesk — Operations · Merchan'!C15,"") -> 101.7 | C9: =IFERROR(('SwapDesk — Operations · Merchan'!D39-'SwapDesk — Operations · Merchan'!D42-'SwapDesk — Operations · Merchan'!D45-'SwapDesk — Operations · Merchan'!D48)/'SwapDesk — Operations · Merchan'!D15,"") -> 101.7 | D9: =IFERROR(('SwapDesk — Operations · Merchan'!E39-'SwapDesk — Operations · Merchan'!E42-'SwapDesk — Operations · Merchan'!E45-'SwapDesk — Operations · Merchan'!E48)/'SwapDesk — Operations · Merchan'!E15,"") -> 101.7 | E9: =IFERROR(('SwapDesk — Operations · Merchan'!F39-'SwapDesk — Operations · Merchan'!F42-'SwapDesk — Operations · Merchan'!F45-'SwapDesk — Operations · Merchan'!F48)/'SwapDesk — Operations · Merchan'!F15,"") -> 101.7 | F9: =IFERROR(('SwapDesk — Operations · Merchan'!G39-'SwapDesk — Operations · Merchan'!G42-'SwapDesk — Operations · Merchan'!G45-'SwapDesk — Operations · Merchan'!G48)/'SwapDesk — Operations · Merchan'!G15,"") -> 101.7 | G9: =IFERROR(('SwapDesk — Operations · Merchan'!H39-'SwapDesk — Operations · Merchan'!H42-'SwapDesk — Operations · Merchan'!H45-'SwapDesk — Operations · Merchan'!H48)/'SwapDesk — Operations · Merchan'!H15,"") -> 101.7 | H9: =IFERROR(('SwapDesk — Operations · Merchan'!I39-'SwapDesk — Operations · Merchan'!I42-'SwapDesk — Operations · Merchan'!I45-'SwapDesk — Operations · Merchan'!I48)/'SwapDesk — Operations · Merchan'!I15,"") -> 101.7 | I9: =IFERROR(('SwapDesk — Operations · Merchan'!J39-'SwapDesk — Operations · Merchan'!J42-'SwapDesk — Operations · Merchan'!J45-'SwapDesk — Operations · Merchan'!J48)/'SwapDesk — Operations · Merchan'!J15,"") -> 101.7 | ... Y9: =IFERROR(('SwapDesk — Operations · Merchan'!Z39-'SwapDesk — Operations · Merchan'!Z42-'SwapDesk — Operations · Merchan'!Z45-'SwapDesk — Operations · Merchan'!Z48)/'SwapDesk — Operations · Merchan'!Z15,"") -> 101.7
A10: Small shop | B10: =IFERROR(('SwapDesk — Operations · Merchan'!C40-'SwapDesk — Operations · Merchan'!C43-'SwapDesk — Operations · Merchan'!C46-'SwapDesk — Operations · Merchan'!C49)/'SwapDesk — Operations · Merchan'!C16,"") -> 37.61 | C10: =IFERROR(('SwapDesk — Operations · Merchan'!D40-'SwapDesk — Operations · Merchan'!D43-'SwapDesk — Operations · Merchan'!D46-'SwapDesk — Operations · Merchan'!D49)/'SwapDesk — Operations · Merchan'!D16,"") -> 37.61 | D10: =IFERROR(('SwapDesk — Operations · Merchan'!E40-'SwapDesk — Operations · Merchan'!E43-'SwapDesk — Operations · Merchan'!E46-'SwapDesk — Operations · Merchan'!E49)/'SwapDesk — Operations · Merchan'!E16,"") -> 37.61 | E10: =IFERROR(('SwapDesk — Operations · Merchan'!F40-'SwapDesk — Operations · Merchan'!F43-'SwapDesk — Operations · Merchan'!F46-'SwapDesk — Operations · Merchan'!F49)/'SwapDesk — Operations · Merchan'!F16,"") -> 37.61 | F10: =IFERROR(('SwapDesk — Operations · Merchan'!G40-'SwapDesk — Operations · Merchan'!G43-'SwapDesk — Operations · Merchan'!G46-'SwapDesk — Operations · Merchan'!G49)/'SwapDesk — Operations · Merchan'!G16,"") -> 37.61 | G10: =IFERROR(('SwapDesk — Operations · Merchan'!H40-'SwapDesk — Operations · Merchan'!H43-'SwapDesk — Operations · Merchan'!H46-'SwapDesk — Operations · Merchan'!H49)/'SwapDesk — Operations · Merchan'!H16,"") -> 37.61 | H10: =IFERROR(('SwapDesk — Operations · Merchan'!I40-'SwapDesk — Operations · Merchan'!I43-'SwapDesk — Operations · Merchan'!I46-'SwapDesk — Operations · Merchan'!I49)/'SwapDesk — Operations · Merchan'!I16,"") -> 37.61 | I10: =IFERROR(('SwapDesk — Operations · Merchan'!J40-'SwapDesk — Operations · Merchan'!J43-'SwapDesk — Operations · Merchan'!J46-'SwapDesk — Operations · Merchan'!J49)/'SwapDesk — Operations · Merchan'!J16,"") -> 37.61 | ... Y10: =IFERROR(('SwapDesk — Operations · Merchan'!Z40-'SwapDesk — Operations · Merchan'!Z43-'SwapDesk — Operations · Merchan'!Z46-'SwapDesk — Operations · Merchan'!Z49)/'SwapDesk — Operations · Merchan'!Z16,"") -> 37.61
A11: Inference spend per arrangement | B11: =IFERROR('SwapDesk — Operations · Merchan'!C41/'SwapDesk — Operations · Merchan'!C20,"") -> 0.053076923 | C11: =IFERROR('SwapDesk — Operations · Merchan'!D41/'SwapDesk — Operations · Merchan'!D20,"") -> 0.053076923 | D11: =IFERROR('SwapDesk — Operations · Merchan'!E41/'SwapDesk — Operations · Merchan'!E20,"") -> 0.053076923 | E11: =IFERROR('SwapDesk — Operations · Merchan'!F41/'SwapDesk — Operations · Merchan'!F20,"") -> 0.053076923 | F11: =IFERROR('SwapDesk — Operations · Merchan'!G41/'SwapDesk — Operations · Merchan'!G20,"") -> 0.053076923 | G11: =IFERROR('SwapDesk — Operations · Merchan'!H41/'SwapDesk — Operations · Merchan'!H20,"") -> 0.053076923 | H11: =IFERROR('SwapDesk — Operations · Merchan'!I41/'SwapDesk — Operations · Merchan'!I20,"") -> 0.053076923 | I11: =IFERROR('SwapDesk — Operations · Merchan'!J41/'SwapDesk — Operations · Merchan'!J20,"") -> 0.053076923 | ... Y11: =IFERROR('SwapDesk — Operations · Merchan'!Z41/'SwapDesk — Operations · Merchan'!Z20,"") -> 0.053076923
A12: Growing shop | B12: =IFERROR('SwapDesk — Operations · Merchan'!C42/'SwapDesk — Operations · Merchan'!C21,"") -> 0.053076923 | C12: =IFERROR('SwapDesk — Operations · Merchan'!D42/'SwapDesk — Operations · Merchan'!D21,"") -> 0.053076923 | D12: =IFERROR('SwapDesk — Operations · Merchan'!E42/'SwapDesk — Operations · Merchan'!E21,"") -> 0.053076923 | E12: =IFERROR('SwapDesk — Operations · Merchan'!F42/'SwapDesk — Operations · Merchan'!F21,"") -> 0.053076923 | F12: =IFERROR('SwapDesk — Operations · Merchan'!G42/'SwapDesk — Operations · Merchan'!G21,"") -> 0.053076923 | G12: =IFERROR('SwapDesk — Operations · Merchan'!H42/'SwapDesk — Operations · Merchan'!H21,"") -> 0.053076923 | H12: =IFERROR('SwapDesk — Operations · Merchan'!I42/'SwapDesk — Operations · Merchan'!I21,"") -> 0.053076923 | I12: =IFERROR('SwapDesk — Operations · Merchan'!J42/'SwapDesk — Operations · Merchan'!J21,"") -> 0.053076923 | ... Y12: =IFERROR('SwapDesk — Operations · Merchan'!Z42/'SwapDesk — Operations · Merchan'!Z21,"") -> 0.053076923
A13: Small shop | B13: =IFERROR('SwapDesk — Operations · Merchan'!C43/'SwapDesk — Operations · Merchan'!C22,"") -> 0.053076923 | C13: =IFERROR('SwapDesk — Operations · Merchan'!D43/'SwapDesk — Operations · Merchan'!D22,"") -> 0.053076923 | D13: =IFERROR('SwapDesk — Operations · Merchan'!E43/'SwapDesk — Operations · Merchan'!E22,"") -> 0.053076923 | E13: =IFERROR('SwapDesk — Operations · Merchan'!F43/'SwapDesk — Operations · Merchan'!F22,"") -> 0.053076923 | F13: =IFERROR('SwapDesk — Operations · Merchan'!G43/'SwapDesk — Operations · Merchan'!G22,"") -> 0.053076923 | G13: =IFERROR('SwapDesk — Operations · Merchan'!H43/'SwapDesk — Operations · Merchan'!H22,"") -> 0.053076923 | H13: =IFERROR('SwapDesk — Operations · Merchan'!I43/'SwapDesk — Operations · Merchan'!I22,"") -> 0.053076923 | I13: =IFERROR('SwapDesk — Operations · Merchan'!J43/'SwapDesk — Operations · Merchan'!J22,"") -> 0.053076923 | ... Y13: =IFERROR('SwapDesk — Operations · Merchan'!Z43/'SwapDesk — Operations · Merchan'!Z22,"") -> 0.053076923
A14: CAC payback months | B14: =IFERROR('SwapDesk — Assumptions · Commer'!B11/'SwapDesk — Operations · Unit ec'!B8,"") -> 1.7673312 | C14: =IFERROR('SwapDesk — Assumptions · Commer'!B11/'SwapDesk — Operations · Unit ec'!C8,"") -> 1.7521597 | D14: =IFERROR('SwapDesk — Assumptions · Commer'!B11/'SwapDesk — Operations · Unit ec'!D8,"") -> 1.7404694 | E14: =IFERROR('SwapDesk — Assumptions · Commer'!B11/'SwapDesk — Operations · Unit ec'!E8,"") -> 1.7310578 | F14: =IFERROR('SwapDesk — Assumptions · Commer'!B11/'SwapDesk — Operations · Unit ec'!F8,"") -> 1.7232216 | G14: =IFERROR('SwapDesk — Assumptions · Commer'!B11/'SwapDesk — Operations · Unit ec'!G8,"") -> 1.7165218 | H14: =IFERROR('SwapDesk — Assumptions · Commer'!B11/'SwapDesk — Operations · Unit ec'!H8,"") -> 1.7106703 | I14: =IFERROR('SwapDesk — Assumptions · Commer'!B11/'SwapDesk — Operations · Unit ec'!I8,"") -> 1.7054702 | J14: =IFERROR('SwapDesk — Assumptions · Commer'!B11/'SwapDesk — Operations · Unit ec'!J8,"") -> 1.7007824 | K14: =IFERROR('SwapDesk — Assumptions · Commer'!B11/'SwapDesk — Operations · Unit ec'!K8,"") -> 1.6965056 | L14: =IFERROR('SwapDesk — Assumptions · Commer'!B11/'SwapDesk — Operations · Unit ec'!L8,"") -> 1.6925645 | M14: =IFERROR('SwapDesk — Assumptions · Commer'!B11/'SwapDesk — Operations · Unit ec'!M8,"") -> 1.6889019 | N14: =IFERROR('SwapDesk — Assumptions · Commer'!B11/'SwapDesk — Operations · Unit ec'!N8,"") -> 1.6854736 | O14: =IFERROR('SwapDesk — Assumptions · Commer'!B11/'SwapDesk — Operations · Unit ec'!O8,"") -> 1.6822448 | P14: =IFERROR('SwapDesk — Assumptions · Commer'!B11/'SwapDesk — Operations · Unit ec'!P8,"") -> 1.6791878 | Q14: =IFERROR('SwapDesk — Assumptions · Commer'!B11/'SwapDesk — Operations · Unit ec'!Q8,"") -> 1.6762801 | R14: =IFERROR('SwapDesk — Assumptions · Commer'!B11/'SwapDesk — Operations · Unit ec'!R8,"") -> 1.6735036 | S14: =IFERROR('SwapDesk — Assumptions · Commer'!B11/'SwapDesk — Operations · Unit ec'!S8,"") -> 1.6708432 | T14: =IFERROR('SwapDesk — Assumptions · Commer'!B11/'SwapDesk — Operations · Unit ec'!T8,"") -> 1.6682865 | U14: =IFERROR('SwapDesk — Assumptions · Commer'!B11/'SwapDesk — Operations · Unit ec'!U8,"") -> 1.6658229 | V14: =IFERROR('SwapDesk — Assumptions · Commer'!B11/'SwapDesk — Operations · Unit ec'!V8,"") -> 1.6634435 | W14: =IFERROR('SwapDesk — Assumptions · Commer'!B11/'SwapDesk — Operations · Unit ec'!W8,"") -> 1.6611409 | X14: =IFERROR('SwapDesk — Assumptions · Commer'!B11/'SwapDesk — Operations · Unit ec'!X8,"") -> 1.6589085 | Y14: =IFERROR('SwapDesk — Assumptions · Commer'!B11/'SwapDesk — Operations · Unit ec'!Y8,"") -> 1.6567408
A15: Growing shop | B15: =IFERROR('SwapDesk — Assumptions · Commer'!B11/'SwapDesk — Operations · Unit ec'!B9,"") -> 0.98328417 | C15: =IFERROR('SwapDesk — Assumptions · Commer'!B11/'SwapDesk — Operations · Unit ec'!C9,"") -> 0.98328417 | D15: =IFERROR('SwapDesk — Assumptions · Commer'!B11/'SwapDesk — Operations · Unit ec'!D9,"") -> 0.98328417 | E15: =IFERROR('SwapDesk — Assumptions · Commer'!B11/'SwapDesk — Operations · Unit ec'!E9,"") -> 0.98328417 | F15: =IFERROR('SwapDesk — Assumptions · Commer'!B11/'SwapDesk — Operations · Unit ec'!F9,"") -> 0.98328417 | G15: =IFERROR('SwapDesk — Assumptions · Commer'!B11/'SwapDesk — Operations · Unit ec'!G9,"") -> 0.98328417 | H15: =IFERROR('SwapDesk — Assumptions · Commer'!B11/'SwapDesk — Operations · Unit ec'!H9,"") -> 0.98328417 | I15: =IFERROR('SwapDesk — Assumptions · Commer'!B11/'SwapDesk — Operations · Unit ec'!I9,"") -> 0.98328417 | J15: =IFERROR('SwapDesk — Assumptions · Commer'!B11/'SwapDesk — Operations · Unit ec'!J9,"") -> 0.98328417 | K15: =IFERROR('SwapDesk — Assumptions · Commer'!B11/'SwapDesk — Operations · Unit ec'!K9,"") -> 0.98328417 | L15: =IFERROR('SwapDesk — Assumptions · Commer'!B11/'SwapDesk — Operations · Unit ec'!L9,"") -> 0.98328417 | M15: =IFERROR('SwapDesk — Assumptions · Commer'!B11/'SwapDesk — Operations · Unit ec'!M9,"") -> 0.98328417 | N15: =IFERROR('SwapDesk — Assumptions · Commer'!B11/'SwapDesk — Operations · Unit ec'!N9,"") -> 0.98328417 | O15: =IFERROR('SwapDesk — Assumptions · Commer'!B11/'SwapDesk — Operations · Unit ec'!O9,"") -> 0.98328417 | P15: =IFERROR('SwapDesk — Assumptions · Commer'!B11/'SwapDesk — Operations · Unit ec'!P9,"") -> 0.98328417 | Q15: =IFERROR('SwapDesk — Assumptions · Commer'!B11/'SwapDesk — Operations · Unit ec'!Q9,"") -> 0.98328417 | R15: =IFERROR('SwapDesk — Assumptions · Commer'!B11/'SwapDesk — Operations · Unit ec'!R9,"") -> 0.98328417 | S15: =IFERROR('SwapDesk — Assumptions · Commer'!B11/'SwapDesk — Operations · Unit ec'!S9,"") -> 0.98328417 | T15: =IFERROR('SwapDesk — Assumptions · Commer'!B11/'SwapDesk — Operations · Unit ec'!T9,"") -> 0.98328417 | U15: =IFERROR('SwapDesk — Assumptions · Commer'!B11/'SwapDesk — Operations · Unit ec'!U9,"") -> 0.98328417 | V15: =IFERROR('SwapDesk — Assumptions · Commer'!B11/'SwapDesk — Operations · Unit ec'!V9,"") -> 0.98328417 | W15: =IFERROR('SwapDesk — Assumptions · Commer'!B11/'SwapDesk — Operations · Unit ec'!W9,"") -> 0.98328417 | X15: =IFERROR('SwapDesk — Assumptions · Commer'!B11/'SwapDesk — Operations · Unit ec'!X9,"") -> 0.98328417 | Y15: =IFERROR('SwapDesk — Assumptions · Commer'!B11/'SwapDesk — Operations · Unit ec'!Y9,"") -> 0.98328417
A16: Small shop | B16: =IFERROR('SwapDesk — Assumptions · Commer'!B11/'SwapDesk — Operations · Unit ec'!B10,"") -> 2.6588673 | C16: =IFERROR('SwapDesk — Assumptions · Commer'!B11/'SwapDesk — Operations · Unit ec'!C10,"") -> 2.6588673 | D16: =IFERROR('SwapDesk — Assumptions · Commer'!B11/'SwapDesk — Operations · Unit ec'!D10,"") -> 2.6588673 | E16: =IFERROR('SwapDesk — Assumptions · Commer'!B11/'SwapDesk — Operations · Unit ec'!E10,"") -> 2.6588673 | F16: =IFERROR('SwapDesk — Assumptions · Commer'!B11/'SwapDesk — Operations · Unit ec'!F10,"") -> 2.6588673 | G16: =IFERROR('SwapDesk — Assumptions · Commer'!B11/'SwapDesk — Operations · Unit ec'!G10,"") -> 2.6588673 | H16: =IFERROR('SwapDesk — Assumptions · Commer'!B11/'SwapDesk — Operations · Unit ec'!H10,"") -> 2.6588673 | I16: =IFERROR('SwapDesk — Assumptions · Commer'!B11/'SwapDesk — Operations · Unit ec'!I10,"") -> 2.6588673 | J16: =IFERROR('SwapDesk — Assumptions · Commer'!B11/'SwapDesk — Operations · Unit ec'!J10,"") -> 2.6588673 | K16: =IFERROR('SwapDesk — Assumptions · Commer'!B11/'SwapDesk — Operations · Unit ec'!K10,"") -> 2.6588673 | L16: =IFERROR('SwapDesk — Assumptions · Commer'!B11/'SwapDesk — Operations · Unit ec'!L10,"") -> 2.6588673 | M16: =IFERROR('SwapDesk — Assumptions · Commer'!B11/'SwapDesk — Operations · Unit ec'!M10,"") -> 2.6588673 | N16: =IFERROR('SwapDesk — Assumptions · Commer'!B11/'SwapDesk — Operations · Unit ec'!N10,"") -> 2.6588673 | O16: =IFERROR('SwapDesk — Assumptions · Commer'!B11/'SwapDesk — Operations · Unit ec'!O10,"") -> 2.6588673 | P16: =IFERROR('SwapDesk — Assumptions · Commer'!B11/'SwapDesk — Operations · Unit ec'!P10,"") -> 2.6588673 | Q16: =IFERROR('SwapDesk — Assumptions · Commer'!B11/'SwapDesk — Operations · Unit ec'!Q10,"") -> 2.6588673 | R16: =IFERROR('SwapDesk — Assumptions · Commer'!B11/'SwapDesk — Operations · Unit ec'!R10,"") -> 2.6588673 | S16: =IFERROR('SwapDesk — Assumptions · Commer'!B11/'SwapDesk — Operations · Unit ec'!S10,"") -> 2.6588673 | T16: =IFERROR('SwapDesk — Assumptions · Commer'!B11/'SwapDesk — Operations · Unit ec'!T10,"") -> 2.6588673 | U16: =IFERROR('SwapDesk — Assumptions · Commer'!B11/'SwapDesk — Operations · Unit ec'!U10,"") -> 2.6588673 | V16: =IFERROR('SwapDesk — Assumptions · Commer'!B11/'SwapDesk — Operations · Unit ec'!V10,"") -> 2.6588673 | W16: =IFERROR('SwapDesk — Assumptions · Commer'!B11/'SwapDesk — Operations · Unit ec'!W10,"") -> 2.6588673 | X16: =IFERROR('SwapDesk — Assumptions · Commer'!B11/'SwapDesk — Operations · Unit ec'!X10,"") -> 2.6588673 | Y16: =IFERROR('SwapDesk — Assumptions · Commer'!B11/'SwapDesk — Operations · Unit ec'!Y10,"") -> 2.6588673

Sheet SwapDesk — Financials · Founder
A1: SwapDesk — Financials · Founder payroll schedule
A2: Financial model (4 pages) · Main Scenario
A4: Variable / dimension | B4: 2026-09 | C4: 2026-10 | D4: 2026-11 | E4: 2026-12 | F4: 2027-01 | G4: 2027-02 | H4: 2027-03 | I4: 2027-04 | J4: 2027-05 | K4: 2027-06 | L4: 2027-07 | M4: 2027-08 | N4: 2027-09 | O4: 2027-10 | P4: 2027-11 | Q4: 2027-12 | R4: 2028-01 | S4: 2028-02 | T4: 2028-03 | U4: 2028-04 | V4: 2028-05 | W4: 2028-06 | X4: 2028-07 | Y4: 2028-08 | Z4: 2028-09
A5: Founder payroll | B5: =SUM('SwapDesk — Financials · Founder'!B6) -> 0 | C5: =SUM('SwapDesk — Financials · Founder'!C6) -> 0 | D5: =SUM('SwapDesk — Financials · Founder'!D6) -> 0 | E5: =SUM('SwapDesk — Financials · Founder'!E6) -> 0 | F5: =SUM('SwapDesk — Financials · Founder'!F6) -> 2000 | G5: =SUM('SwapDesk — Financials · Founder'!G6) -> 2000 | H5: =SUM('SwapDesk — Financials · Founder'!H6) -> 2000 | I5: =SUM('SwapDesk — Financials · Founder'!I6) -> 2000 | ... Z5: =SUM('SwapDesk — Financials · Founder'!Z6) -> 2000
A6: Placeholder founder 1 | B6: =0 -> 0 | C6: =IF(IF(IF(ISERROR(DATE(2026,10,1)>=DATE(YEAR('SwapDesk — Assumptions · Placeh'!B5),MONTH('SwapDesk — Assumptions · Placeh'!B5),1)),DATE(2026,10,1)>=DATE(YEAR('SwapDesk — Assumptions · Placeh'!B5),MONTH('SwapDesk — Assumptions · Placeh'!B5),1),IF(DATE(YEAR('SwapDesk — Assumptions · Placeh'!B5),MONTH('SwapDesk — Assumptions · Placeh'!B5),1)="","",DATE(2026,10,1)>=DATE(YEAR('SwapDesk — Assumptions · Placeh'!B5),MONTH('SwapDesk — Assumptions · Placeh'!B5),1)))="",FALSE,IF(ISERROR(DATE(2026,10,1)>=DATE(YEAR('SwapDesk — Assumptions · Placeh'!B5),MONTH('SwapDesk — Assumptions · Placeh'!B5),1)),DATE(2026,10,1)>=DATE(YEAR('SwapDesk — Assumptions · Placeh'!B5),MONTH('SwapDesk — Assumptions · Placeh'!B5),1),IF(DATE(YEAR('SwapDesk — Assumptions · Placeh'!B5),MONTH('SwapDesk — Assumptions · Placeh'!B5),1)="","",DATE(2026,10,1)>=DATE(YEAR('SwapDesk — Assumptions · Placeh'!B5),MONTH('SwapDesk — Assumptions · Placeh'!B5),1)))),'SwapDesk — Assumptions · Placeh'!C5/12,0) -> 0 | D6: =IF(IF(IF(ISERROR(DATE(2026,11,1)>=DATE(YEAR('SwapDesk — Assumptions · Placeh'!B5),MONTH('SwapDesk — Assumptions · Placeh'!B5),1)),DATE(2026,11,1)>=DATE(YEAR('SwapDesk — Assumptions · Placeh'!B5),MONTH('SwapDesk — Assumptions · Placeh'!B5),1),IF(DATE(YEAR('SwapDesk — Assumptions · Placeh'!B5),MONTH('SwapDesk — Assumptions · Placeh'!B5),1)="","",DATE(2026,11,1)>=DATE(YEAR('SwapDesk — Assumptions · Placeh'!B5),MONTH('SwapDesk — Assumptions · Placeh'!B5),1)))="",FALSE,IF(ISERROR(DATE(2026,11,1)>=DATE(YEAR('SwapDesk — Assumptions · Placeh'!B5),MONTH('SwapDesk — Assumptions · Placeh'!B5),1)),DATE(2026,11,1)>=DATE(YEAR('SwapDesk — Assumptions · Placeh'!B5),MONTH('SwapDesk — Assumptions · Placeh'!B5),1),IF(DATE(YEAR('SwapDesk — Assumptions · Placeh'!B5),MONTH('SwapDesk — Assumptions · Placeh'!B5),1)="","",DATE(2026,11,1)>=DATE(YEAR('SwapDesk — Assumptions · Placeh'!B5),MONTH('SwapDesk — Assumptions · Placeh'!B5),1)))),'SwapDesk — Assumptions · Placeh'!C5/12,0) -> 0 | E6: =IF(IF(IF(ISERROR(DATE(2026,12,1)>=DATE(YEAR('SwapDesk — Assumptions · Placeh'!B5),MONTH('SwapDesk — Assumptions · Placeh'!B5),1)),DATE(2026,12,1)>=DATE(YEAR('SwapDesk — Assumptions · Placeh'!B5),MONTH('SwapDesk — Assumptions · Placeh'!B5),1),IF(DATE(YEAR('SwapDesk — Assumptions · Placeh'!B5),MONTH('SwapDesk — Assumptions · Placeh'!B5),1)="","",DATE(2026,12,1)>=DATE(YEAR('SwapDesk — Assumptions · Placeh'!B5),MONTH('SwapDesk — Assumptions · Placeh'!B5),1)))="",FALSE,IF(ISERROR(DATE(2026,12,1)>=DATE(YEAR('SwapDesk — Assumptions · Placeh'!B5),MONTH('SwapDesk — Assumptions · Placeh'!B5),1)),DATE(2026,12,1)>=DATE(YEAR('SwapDesk — Assumptions · Placeh'!B5),MONTH('SwapDesk — Assumptions · Placeh'!B5),1),IF(DATE(YEAR('SwapDesk — Assumptions · Placeh'!B5),MONTH('SwapDesk — Assumptions · Placeh'!B5),1)="","",DATE(2026,12,1)>=DATE(YEAR('SwapDesk — Assumptions · Placeh'!B5),MONTH('SwapDesk — Assumptions · Placeh'!B5),1)))),'SwapDesk — Assumptions · Placeh'!C5/12,0) -> 0 | F6: =IF(IF(IF(ISERROR(DATE(2027,1,1)>=DATE(YEAR('SwapDesk — Assumptions · Placeh'!B5),MONTH('SwapDesk — Assumptions · Placeh'!B5),1)),DATE(2027,1,1)>=DATE(YEAR('SwapDesk — Assumptions · Placeh'!B5),MONTH('SwapDesk — Assumptions · Placeh'!B5),1),IF(DATE(YEAR('SwapDesk — Assumptions · Placeh'!B5),MONTH('SwapDesk — Assumptions · Placeh'!B5),1)="","",DATE(2027,1,1)>=DATE(YEAR('SwapDesk — Assumptions · Placeh'!B5),MONTH('SwapDesk — Assumptions · Placeh'!B5),1)))="",FALSE,IF(ISERROR(DATE(2027,1,1)>=DATE(YEAR('SwapDesk — Assumptions · Placeh'!B5),MONTH('SwapDesk — Assumptions · Placeh'!B5),1)),DATE(2027,1,1)>=DATE(YEAR('SwapDesk — Assumptions · Placeh'!B5),MONTH('SwapDesk — Assumptions · Placeh'!B5),1),IF(DATE(YEAR('SwapDesk — Assumptions · Placeh'!B5),MONTH('SwapDesk — Assumptions · Placeh'!B5),1)="","",DATE(2027,1,1)>=DATE(YEAR('SwapDesk — Assumptions · Placeh'!B5),MONTH('SwapDesk — Assumptions · Placeh'!B5),1)))),'SwapDesk — Assumptions · Placeh'!C5/12,0) -> 2000 | G6: =IF(IF(IF(ISERROR(DATE(2027,2,1)>=DATE(YEAR('SwapDesk — Assumptions · Placeh'!B5),MONTH('SwapDesk — Assumptions · Placeh'!B5),1)),DATE(2027,2,1)>=DATE(YEAR('SwapDesk — Assumptions · Placeh'!B5),MONTH('SwapDesk — Assumptions · Placeh'!B5),1),IF(DATE(YEAR('SwapDesk — Assumptions · Placeh'!B5),MONTH('SwapDesk — Assumptions · Placeh'!B5),1)="","",DATE(2027,2,1)>=DATE(YEAR('SwapDesk — Assumptions · Placeh'!B5),MONTH('SwapDesk — Assumptions · Placeh'!B5),1)))="",FALSE,IF(ISERROR(DATE(2027,2,1)>=DATE(YEAR('SwapDesk — Assumptions · Placeh'!B5),MONTH('SwapDesk — Assumptions · Placeh'!B5),1)),DATE(2027,2,1)>=DATE(YEAR('SwapDesk — Assumptions · Placeh'!B5),MONTH('SwapDesk — Assumptions · Placeh'!B5),1),IF(DATE(YEAR('SwapDesk — Assumptions · Placeh'!B5),MONTH('SwapDesk — Assumptions · Placeh'!B5),1)="","",DATE(2027,2,1)>=DATE(YEAR('SwapDesk — Assumptions · Placeh'!B5),MONTH('SwapDesk — Assumptions · Placeh'!B5),1)))),'SwapDesk — Assumptions · Placeh'!C5/12,0) -> 2000 | H6: =IF(IF(IF(ISERROR(DATE(2027,3,1)>=DATE(YEAR('SwapDesk — Assumptions · Placeh'!B5),MONTH('SwapDesk — Assumptions · Placeh'!B5),1)),DATE(2027,3,1)>=DATE(YEAR('SwapDesk — Assumptions · Placeh'!B5),MONTH('SwapDesk — Assumptions · Placeh'!B5),1),IF(DATE(YEAR('SwapDesk — Assumptions · Placeh'!B5),MONTH('SwapDesk — Assumptions · Placeh'!B5),1)="","",DATE(2027,3,1)>=DATE(YEAR('SwapDesk — Assumptions · Placeh'!B5),MONTH('SwapDesk — Assumptions · Placeh'!B5),1)))="",FALSE,IF(ISERROR(DATE(2027,3,1)>=DATE(YEAR('SwapDesk — Assumptions · Placeh'!B5),MONTH('SwapDesk — Assumptions · Placeh'!B5),1)),DATE(2027,3,1)>=DATE(YEAR('SwapDesk — Assumptions · Placeh'!B5),MONTH('SwapDesk — Assumptions · Placeh'!B5),1),IF(DATE(YEAR('SwapDesk — Assumptions · Placeh'!B5),MONTH('SwapDesk — Assumptions · Placeh'!B5),1)="","",DATE(2027,3,1)>=DATE(YEAR('SwapDesk — Assumptions · Placeh'!B5),MONTH('SwapDesk — Assumptions · Placeh'!B5),1)))),'SwapDesk — Assumptions · Placeh'!C5/12,0) -> 2000 | I6: =IF(IF(IF(ISERROR(DATE(2027,4,1)>=DATE(YEAR('SwapDesk — Assumptions · Placeh'!B5),MONTH('SwapDesk — Assumptions · Placeh'!B5),1)),DATE(2027,4,1)>=DATE(YEAR('SwapDesk — Assumptions · Placeh'!B5),MONTH('SwapDesk — Assumptions · Placeh'!B5),1),IF(DATE(YEAR('SwapDesk — Assumptions · Placeh'!B5),MONTH('SwapDesk — Assumptions · Placeh'!B5),1)="","",DATE(2027,4,1)>=DATE(YEAR('SwapDesk — Assumptions · Placeh'!B5),MONTH('SwapDesk — Assumptions · Placeh'!B5),1)))="",FALSE,IF(ISERROR(DATE(2027,4,1)>=DATE(YEAR('SwapDesk — Assumptions · Placeh'!B5),MONTH('SwapDesk — Assumptions · Placeh'!B5),1)),DATE(2027,4,1)>=DATE(YEAR('SwapDesk — Assumptions · Placeh'!B5),MONTH('SwapDesk — Assumptions · Placeh'!B5),1),IF(DATE(YEAR('SwapDesk — Assumptions · Placeh'!B5),MONTH('SwapDesk — Assumptions · Placeh'!B5),1)="","",DATE(2027,4,1)>=DATE(YEAR('SwapDesk — Assumptions · Placeh'!B5),MONTH('SwapDesk — Assumptions · Placeh'!B5),1)))),'SwapDesk — Assumptions · Placeh'!C5/12,0) -> 2000 | J6: =IF(IF(IF(ISERROR(DATE(2027,5,1)>=DATE(YEAR('SwapDesk — Assumptions · Placeh'!B5),MONTH('SwapDesk — Assumptions · Placeh'!B5),1)),DATE(2027,5,1)>=DATE(YEAR('SwapDesk — Assumptions · Placeh'!B5),MONTH('SwapDesk — Assumptions · Placeh'!B5),1),IF(DATE(YEAR('SwapDesk — Assumptions · Placeh'!B5),MONTH('SwapDesk — Assumptions · Placeh'!B5),1)="","",DATE(2027,5,1)>=DATE(YEAR('SwapDesk — Assumptions · Placeh'!B5),MONTH('SwapDesk — Assumptions · Placeh'!B5),1)))="",FALSE,IF(ISERROR(DATE(2027,5,1)>=DATE(YEAR('SwapDesk — Assumptions · Placeh'!B5),MONTH('SwapDesk — Assumptions · Placeh'!B5),1)),DATE(2027,5,1)>=DATE(YEAR('SwapDesk — Assumptions · Placeh'!B5),MONTH('SwapDesk — Assumptions · Placeh'!B5),1),IF(DATE(YEAR('SwapDesk — Assumptions · Placeh'!B5),MONTH('SwapDesk — Assumptions · Placeh'!B5),1)="","",DATE(2027,5,1)>=DATE(YEAR('SwapDesk — Assumptions · Placeh'!B5),MONTH('SwapDesk — Assumptions · Placeh'!B5),1)))),'SwapDesk — Assumptions · Placeh'!C5/12,0) -> 2000 | K6: =IF(IF(IF(ISERROR(DATE(2027,6,1)>=DATE(YEAR('SwapDesk — Assumptions · Placeh'!B5),MONTH('SwapDesk — Assumptions · Placeh'!B5),1)),DATE(2027,6,1)>=DATE(YEAR('SwapDesk — Assumptions · Placeh'!B5),MONTH('SwapDesk — Assumptions · Placeh'!B5),1),IF(DATE(YEAR('SwapDesk — Assumptions · Placeh'!B5),MONTH('SwapDesk — Assumptions · Placeh'!B5),1)="","",DATE(2027,6,1)>=DATE(YEAR('SwapDesk — Assumptions · Placeh'!B5),MONTH('SwapDesk — Assumptions · Placeh'!B5),1)))="",FALSE,IF(ISERROR(DATE(2027,6,1)>=DATE(YEAR('SwapDesk — Assumptions · Placeh'!B5),MONTH('SwapDesk — Assumptions · Placeh'!B5),1)),DATE(2027,6,1)>=DATE(YEAR('SwapDesk — Assumptions · Placeh'!B5),MONTH('SwapDesk — Assumptions · Placeh'!B5),1),IF(DATE(YEAR('SwapDesk — Assumptions · Placeh'!B5),MONTH('SwapDesk — Assumptions · Placeh'!B5),1)="","",DATE(2027,6,1)>=DATE(YEAR('SwapDesk — Assumptions · Placeh'!B5),MONTH('SwapDesk — Assumptions · Placeh'!B5),1)))),'SwapDesk — Assumptions · Placeh'!C5/12,0) -> 2000 | L6: =IF(IF(IF(ISERROR(DATE(2027,7,1)>=DATE(YEAR('SwapDesk — Assumptions · Placeh'!B5),MONTH('SwapDesk — Assumptions · Placeh'!B5),1)),DATE(2027,7,1)>=DATE(YEAR('SwapDesk — Assumptions · Placeh'!B5),MONTH('SwapDesk — Assumptions · Placeh'!B5),1),IF(DATE(YEAR('SwapDesk — Assumptions · Placeh'!B5),MONTH('SwapDesk — Assumptions · Placeh'!B5),1)="","",DATE(2027,7,1)>=DATE(YEAR('SwapDesk — Assumptions · Placeh'!B5),MONTH('SwapDesk — Assumptions · Placeh'!B5),1)))="",FALSE,IF(ISERROR(DATE(2027,7,1)>=DATE(YEAR('SwapDesk — Assumptions · Placeh'!B5),MONTH('SwapDesk — Assumptions · Placeh'!B5),1)),DATE(2027,7,1)>=DATE(YEAR('SwapDesk — Assumptions · Placeh'!B5),MONTH('SwapDesk — Assumptions · Placeh'!B5),1),IF(DATE(YEAR('SwapDesk — Assumptions · Placeh'!B5),MONTH('SwapDesk — Assumptions · Placeh'!B5),1)="","",DATE(2027,7,1)>=DATE(YEAR('SwapDesk — Assumptions · Placeh'!B5),MONTH('SwapDesk — Assumptions · Placeh'!B5),1)))),'SwapDesk — Assumptions · Placeh'!C5/12,0) -> 2000 | M6: =IF(IF(IF(ISERROR(DATE(2027,8,1)>=DATE(YEAR('SwapDesk — Assumptions · Placeh'!B5),MONTH('SwapDesk — Assumptions · Placeh'!B5),1)),DATE(2027,8,1)>=DATE(YEAR('SwapDesk — Assumptions · Placeh'!B5),MONTH('SwapDesk — Assumptions · Placeh'!B5),1),IF(DATE(YEAR('SwapDesk — Assumptions · Placeh'!B5),MONTH('SwapDesk — Assumptions · Placeh'!B5),1)="","",DATE(2027,8,1)>=DATE(YEAR('SwapDesk — Assumptions · Placeh'!B5),MONTH('SwapDesk — Assumptions · Placeh'!B5),1)))="",FALSE,IF(ISERROR(DATE(2027,8,1)>=DATE(YEAR('SwapDesk — Assumptions · Placeh'!B5),MONTH('SwapDesk — Assumptions · Placeh'!B5),1)),DATE(2027,8,1)>=DATE(YEAR('SwapDesk — Assumptions · Placeh'!B5),MONTH('SwapDesk — Assumptions · Placeh'!B5),1),IF(DATE(YEAR('SwapDesk — Assumptions · Placeh'!B5),MONTH('SwapDesk — Assumptions · Placeh'!B5),1)="","",DATE(2027,8,1)>=DATE(YEAR('SwapDesk — Assumptions · Placeh'!B5),MONTH('SwapDesk — Assumptions · Placeh'!B5),1)))),'SwapDesk — Assumptions · Placeh'!C5/12,0) -> 2000 | N6: =IF(IF(IF(ISERROR(DATE(2027,9,1)>=DATE(YEAR('SwapDesk — Assumptions · Placeh'!B5),MONTH('SwapDesk — Assumptions · Placeh'!B5),1)),DATE(2027,9,1)>=DATE(YEAR('SwapDesk — Assumptions · Placeh'!B5),MONTH('SwapDesk — Assumptions · Placeh'!B5),1),IF(DATE(YEAR('SwapDesk — Assumptions · Placeh'!B5),MONTH('SwapDesk — Assumptions · Placeh'!B5),1)="","",DATE(2027,9,1)>=DATE(YEAR('SwapDesk — Assumptions · Placeh'!B5),MONTH('SwapDesk — Assumptions · Placeh'!B5),1)))="",FALSE,IF(ISERROR(DATE(2027,9,1)>=DATE(YEAR('SwapDesk — Assumptions · Placeh'!B5),MONTH('SwapDesk — Assumptions · Placeh'!B5),1)),DATE(2027,9,1)>=DATE(YEAR('SwapDesk — Assumptions · Placeh'!B5),MONTH('SwapDesk — Assumptions · Placeh'!B5),1),IF(DATE(YEAR('SwapDesk — Assumptions · Placeh'!B5),MONTH('SwapDesk — Assumptions · Placeh'!B5),1)="","",DATE(2027,9,1)>=DATE(YEAR('SwapDesk — Assumptions · Placeh'!B5),MONTH('SwapDesk — Assumptions · Placeh'!B5),1)))),'SwapDesk — Assumptions · Placeh'!C5/12,0) -> 2000 | O6: =IF(IF(IF(ISERROR(DATE(2027,10,1)>=DATE(YEAR('SwapDesk — Assumptions · Placeh'!B5),MONTH('SwapDesk — Assumptions · Placeh'!B5),1)),DATE(2027,10,1)>=DATE(YEAR('SwapDesk — Assumptions · Placeh'!B5),MONTH('SwapDesk — Assumptions · Placeh'!B5),1),IF(DATE(YEAR('SwapDesk — Assumptions · Placeh'!B5),MONTH('SwapDesk — Assumptions · Placeh'!B5),1)="","",DATE(2027,10,1)>=DATE(YEAR('SwapDesk — Assumptions · Placeh'!B5),MONTH('SwapDesk — Assumptions · Placeh'!B5),1)))="",FALSE,IF(ISERROR(DATE(2027,10,1)>=DATE(YEAR('SwapDesk — Assumptions · Placeh'!B5),MONTH('SwapDesk — Assumptions · Placeh'!B5),1)),DATE(2027,10,1)>=DATE(YEAR('SwapDesk — Assumptions · Placeh'!B5),MONTH('SwapDesk — Assumptions · Placeh'!B5),1),IF(DATE(YEAR('SwapDesk — Assumptions · Placeh'!B5),MONTH('SwapDesk — Assumptions · Placeh'!B5),1)="","",DATE(2027,10,1)>=DATE(YEAR('SwapDesk — Assumptions · Placeh'!B5),MONTH('SwapDesk — Assumptions · Placeh'!B5),1)))),'SwapDesk — Assumptions · Placeh'!C5/12,0) -> 2000 | P6: =IF(IF(IF(ISERROR(DATE(2027,11,1)>=DATE(YEAR('SwapDesk — Assumptions · Placeh'!B5),MONTH('SwapDesk — Assumptions · Placeh'!B5),1)),DATE(2027,11,1)>=DATE(YEAR('SwapDesk — Assumptions · Placeh'!B5),MONTH('SwapDesk — Assumptions · Placeh'!B5),1),IF(DATE(YEAR('SwapDesk — Assumptions · Placeh'!B5),MONTH('SwapDesk — Assumptions · Placeh'!B5),1)="","",DATE(2027,11,1)>=DATE(YEAR('SwapDesk — Assumptions · Placeh'!B5),MONTH('SwapDesk — Assumptions · Placeh'!B5),1)))="",FALSE,IF(ISERROR(DATE(2027,11,1)>=DATE(YEAR('SwapDesk — Assumptions · Placeh'!B5),MONTH('SwapDesk — Assumptions · Placeh'!B5),1)),DATE(2027,11,1)>=DATE(YEAR('SwapDesk — Assumptions · Placeh'!B5),MONTH('SwapDesk — Assumptions · Placeh'!B5),1),IF(DATE(YEAR('SwapDesk — Assumptions · Placeh'!B5),MONTH('SwapDesk — Assumptions · Placeh'!B5),1)="","",DATE(2027,11,1)>=DATE(YEAR('SwapDesk — Assumptions · Placeh'!B5),MONTH('SwapDesk — Assumptions · Placeh'!B5),1)))),'SwapDesk — Assumptions · Placeh'!C5/12,0) -> 2000 | Q6: =IF(IF(IF(ISERROR(DATE(2027,12,1)>=DATE(YEAR('SwapDesk — Assumptions · Placeh'!B5),MONTH('SwapDesk — Assumptions · Placeh'!B5),1)),DATE(2027,12,1)>=DATE(YEAR('SwapDesk — Assumptions · Placeh'!B5),MONTH('SwapDesk — Assumptions · Placeh'!B5),1),IF(DATE(YEAR('SwapDesk — Assumptions · Placeh'!B5),MONTH('SwapDesk — Assumptions · Placeh'!B5),1)="","",DATE(2027,12,1)>=DATE(YEAR('SwapDesk — Assumptions · Placeh'!B5),MONTH('SwapDesk — Assumptions · Placeh'!B5),1)))="",FALSE,IF(ISERROR(DATE(2027,12,1)>=DATE(YEAR('SwapDesk — Assumptions · Placeh'!B5),MONTH('SwapDesk — Assumptions · Placeh'!B5),1)),DATE(2027,12,1)>=DATE(YEAR('SwapDesk — Assumptions · Placeh'!B5),MONTH('SwapDesk — Assumptions · Placeh'!B5),1),IF(DATE(YEAR('SwapDesk — Assumptions · Placeh'!B5),MONTH('SwapDesk — Assumptions · Placeh'!B5),1)="","",DATE(2027,12,1)>=DATE(YEAR('SwapDesk — Assumptions · Placeh'!B5),MONTH('SwapDesk — Assumptions · Placeh'!B5),1)))),'SwapDesk — Assumptions · Placeh'!C5/12,0) -> 2000 | R6: =IF(IF(IF(ISERROR(DATE(2028,1,1)>=DATE(YEAR('SwapDesk — Assumptions · Placeh'!B5),MONTH('SwapDesk — Assumptions · Placeh'!B5),1)),DATE(2028,1,1)>=DATE(YEAR('SwapDesk — Assumptions · Placeh'!B5),MONTH('SwapDesk — Assumptions · Placeh'!B5),1),IF(DATE(YEAR('SwapDesk — Assumptions · Placeh'!B5),MONTH('SwapDesk — Assumptions · Placeh'!B5),1)="","",DATE(2028,1,1)>=DATE(YEAR('SwapDesk — Assumptions · Placeh'!B5),MONTH('SwapDesk — Assumptions · Placeh'!B5),1)))="",FALSE,IF(ISERROR(DATE(2028,1,1)>=DATE(YEAR('SwapDesk — Assumptions · Placeh'!B5),MONTH('SwapDesk — Assumptions · Placeh'!B5),1)),DATE(2028,1,1)>=DATE(YEAR('SwapDesk — Assumptions · Placeh'!B5),MONTH('SwapDesk — Assumptions · Placeh'!B5),1),IF(DATE(YEAR('SwapDesk — Assumptions · Placeh'!B5),MONTH('SwapDesk — Assumptions · Placeh'!B5),1)="","",DATE(2028,1,1)>=DATE(YEAR('SwapDesk — Assumptions · Placeh'!B5),MONTH('SwapDesk — Assumptions · Placeh'!B5),1)))),'SwapDesk — Assumptions · Placeh'!C5/12,0) -> 2000 | S6: =IF(IF(IF(ISERROR(DATE(2028,2,1)>=DATE(YEAR('SwapDesk — Assumptions · Placeh'!B5),MONTH('SwapDesk — Assumptions · Placeh'!B5),1)),DATE(2028,2,1)>=DATE(YEAR('SwapDesk — Assumptions · Placeh'!B5),MONTH('SwapDesk — Assumptions · Placeh'!B5),1),IF(DATE(YEAR('SwapDesk — Assumptions · Placeh'!B5),MONTH('SwapDesk — Assumptions · Placeh'!B5),1)="","",DATE(2028,2,1)>=DATE(YEAR('SwapDesk — Assumptions · Placeh'!B5),MONTH('SwapDesk — Assumptions · Placeh'!B5),1)))="",FALSE,IF(ISERROR(DATE(2028,2,1)>=DATE(YEAR('SwapDesk — Assumptions · Placeh'!B5),MONTH('SwapDesk — Assumptions · Placeh'!B5),1)),DATE(2028,2,1)>=DATE(YEAR('SwapDesk — Assumptions · Placeh'!B5),MONTH('SwapDesk — Assumptions · Placeh'!B5),1),IF(DATE(YEAR('SwapDesk — Assumptions · Placeh'!B5),MONTH('SwapDesk — Assumptions · Placeh'!B5),1)="","",DATE(2028,2,1)>=DATE(YEAR('SwapDesk — Assumptions · Placeh'!B5),MONTH('SwapDesk — Assumptions · Placeh'!B5),1)))),'SwapDesk — Assumptions · Placeh'!C5/12,0) -> 2000 | T6: =IF(IF(IF(ISERROR(DATE(2028,3,1)>=DATE(YEAR('SwapDesk — Assumptions · Placeh'!B5),MONTH('SwapDesk — Assumptions · Placeh'!B5),1)),DATE(2028,3,1)>=DATE(YEAR('SwapDesk — Assumptions · Placeh'!B5),MONTH('SwapDesk — Assumptions · Placeh'!B5),1),IF(DATE(YEAR('SwapDesk — Assumptions · Placeh'!B5),MONTH('SwapDesk — Assumptions · Placeh'!B5),1)="","",DATE(2028,3,1)>=DATE(YEAR('SwapDesk — Assumptions · Placeh'!B5),MONTH('SwapDesk — Assumptions · Placeh'!B5),1)))="",FALSE,IF(ISERROR(DATE(2028,3,1)>=DATE(YEAR('SwapDesk — Assumptions · Placeh'!B5),MONTH('SwapDesk — Assumptions · Placeh'!B5),1)),DATE(2028,3,1)>=DATE(YEAR('SwapDesk — Assumptions · Placeh'!B5),MONTH('SwapDesk — Assumptions · Placeh'!B5),1),IF(DATE(YEAR('SwapDesk — Assumptions · Placeh'!B5),MONTH('SwapDesk — Assumptions · Placeh'!B5),1)="","",DATE(2028,3,1)>=DATE(YEAR('SwapDesk — Assumptions · Placeh'!B5),MONTH('SwapDesk — Assumptions · Placeh'!B5),1)))),'SwapDesk — Assumptions · Placeh'!C5/12,0) -> 2000 | U6: =IF(IF(IF(ISERROR(DATE(2028,4,1)>=DATE(YEAR('SwapDesk — Assumptions · Placeh'!B5),MONTH('SwapDesk — Assumptions · Placeh'!B5),1)),DATE(2028,4,1)>=DATE(YEAR('SwapDesk — Assumptions · Placeh'!B5),MONTH('SwapDesk — Assumptions · Placeh'!B5),1),IF(DATE(YEAR('SwapDesk — Assumptions · Placeh'!B5),MONTH('SwapDesk — Assumptions · Placeh'!B5),1)="","",DATE(2028,4,1)>=DATE(YEAR('SwapDesk — Assumptions · Placeh'!B5),MONTH('SwapDesk — Assumptions · Placeh'!B5),1)))="",FALSE,IF(ISERROR(DATE(2028,4,1)>=DATE(YEAR('SwapDesk — Assumptions · Placeh'!B5),MONTH('SwapDesk — Assumptions · Placeh'!B5),1)),DATE(2028,4,1)>=DATE(YEAR('SwapDesk — Assumptions · Placeh'!B5),MONTH('SwapDesk — Assumptions · Placeh'!B5),1),IF(DATE(YEAR('SwapDesk — Assumptions · Placeh'!B5),MONTH('SwapDesk — Assumptions · Placeh'!B5),1)="","",DATE(2028,4,1)>=DATE(YEAR('SwapDesk — Assumptions · Placeh'!B5),MONTH('SwapDesk — Assumptions · Placeh'!B5),1)))),'SwapDesk — Assumptions · Placeh'!C5/12,0) -> 2000 | V6: =IF(IF(IF(ISERROR(DATE(2028,5,1)>=DATE(YEAR('SwapDesk — Assumptions · Placeh'!B5),MONTH('SwapDesk — Assumptions · Placeh'!B5),1)),DATE(2028,5,1)>=DATE(YEAR('SwapDesk — Assumptions · Placeh'!B5),MONTH('SwapDesk — Assumptions · Placeh'!B5),1),IF(DATE(YEAR('SwapDesk — Assumptions · Placeh'!B5),MONTH('SwapDesk — Assumptions · Placeh'!B5),1)="","",DATE(2028,5,1)>=DATE(YEAR('SwapDesk — Assumptions · Placeh'!B5),MONTH('SwapDesk — Assumptions · Placeh'!B5),1)))="",FALSE,IF(ISERROR(DATE(2028,5,1)>=DATE(YEAR('SwapDesk — Assumptions · Placeh'!B5),MONTH('SwapDesk — Assumptions · Placeh'!B5),1)),DATE(2028,5,1)>=DATE(YEAR('SwapDesk — Assumptions · Placeh'!B5),MONTH('SwapDesk — Assumptions · Placeh'!B5),1),IF(DATE(YEAR('SwapDesk — Assumptions · Placeh'!B5),MONTH('SwapDesk — Assumptions · Placeh'!B5),1)="","",DATE(2028,5,1)>=DATE(YEAR('SwapDesk — Assumptions · Placeh'!B5),MONTH('SwapDesk — Assumptions · Placeh'!B5),1)))),'SwapDesk — Assumptions · Placeh'!C5/12,0) -> 2000 | W6: =IF(IF(IF(ISERROR(DATE(2028,6,1)>=DATE(YEAR('SwapDesk — Assumptions · Placeh'!B5),MONTH('SwapDesk — Assumptions · Placeh'!B5),1)),DATE(2028,6,1)>=DATE(YEAR('SwapDesk — Assumptions · Placeh'!B5),MONTH('SwapDesk — Assumptions · Placeh'!B5),1),IF(DATE(YEAR('SwapDesk — Assumptions · Placeh'!B5),MONTH('SwapDesk — Assumptions · Placeh'!B5),1)="","",DATE(2028,6,1)>=DATE(YEAR('SwapDesk — Assumptions · Placeh'!B5),MONTH('SwapDesk — Assumptions · Placeh'!B5),1)))="",FALSE,IF(ISERROR(DATE(2028,6,1)>=DATE(YEAR('SwapDesk — Assumptions · Placeh'!B5),MONTH('SwapDesk — Assumptions · Placeh'!B5),1)),DATE(2028,6,1)>=DATE(YEAR('SwapDesk — Assumptions · Placeh'!B5),MONTH('SwapDesk — Assumptions · Placeh'!B5),1),IF(DATE(YEAR('SwapDesk — Assumptions · Placeh'!B5),MONTH('SwapDesk — Assumptions · Placeh'!B5),1)="","",DATE(2028,6,1)>=DATE(YEAR('SwapDesk — Assumptions · Placeh'!B5),MONTH('SwapDesk — Assumptions · Placeh'!B5),1)))),'SwapDesk — Assumptions · Placeh'!C5/12,0) -> 2000 | X6: =IF(IF(IF(ISERROR(DATE(2028,7,1)>=DATE(YEAR('SwapDesk — Assumptions · Placeh'!B5),MONTH('SwapDesk — Assumptions · Placeh'!B5),1)),DATE(2028,7,1)>=DATE(YEAR('SwapDesk — Assumptions · Placeh'!B5),MONTH('SwapDesk — Assumptions · Placeh'!B5),1),IF(DATE(YEAR('SwapDesk — Assumptions · Placeh'!B5),MONTH('SwapDesk — Assumptions · Placeh'!B5),1)="","",DATE(2028,7,1)>=DATE(YEAR('SwapDesk — Assumptions · Placeh'!B5),MONTH('SwapDesk — Assumptions · Placeh'!B5),1)))="",FALSE,IF(ISERROR(DATE(2028,7,1)>=DATE(YEAR('SwapDesk — Assumptions · Placeh'!B5),MONTH('SwapDesk — Assumptions · Placeh'!B5),1)),DATE(2028,7,1)>=DATE(YEAR('SwapDesk — Assumptions · Placeh'!B5),MONTH('SwapDesk — Assumptions · Placeh'!B5),1),IF(DATE(YEAR('SwapDesk — Assumptions · Placeh'!B5),MONTH('SwapDesk — Assumptions · Placeh'!B5),1)="","",DATE(2028,7,1)>=DATE(YEAR('SwapDesk — Assumptions · Placeh'!B5),MONTH('SwapDesk — Assumptions · Placeh'!B5),1)))),'SwapDesk — Assumptions · Placeh'!C5/12,0) -> 2000 | Y6: =IF(IF(IF(ISERROR(DATE(2028,8,1)>=DATE(YEAR('SwapDesk — Assumptions · Placeh'!B5),MONTH('SwapDesk — Assumptions · Placeh'!B5),1)),DATE(2028,8,1)>=DATE(YEAR('SwapDesk — Assumptions · Placeh'!B5),MONTH('SwapDesk — Assumptions · Placeh'!B5),1),IF(DATE(YEAR('SwapDesk — Assumptions · Placeh'!B5),MONTH('SwapDesk — Assumptions · Placeh'!B5),1)="","",DATE(2028,8,1)>=DATE(YEAR('SwapDesk — Assumptions · Placeh'!B5),MONTH('SwapDesk — Assumptions · Placeh'!B5),1)))="",FALSE,IF(ISERROR(DATE(2028,8,1)>=DATE(YEAR('SwapDesk — Assumptions · Placeh'!B5),MONTH('SwapDesk — Assumptions · Placeh'!B5),1)),DATE(2028,8,1)>=DATE(YEAR('SwapDesk — Assumptions · Placeh'!B5),MONTH('SwapDesk — Assumptions · Placeh'!B5),1),IF(DATE(YEAR('SwapDesk — Assumptions · Placeh'!B5),MONTH('SwapDesk — Assumptions · Placeh'!B5),1)="","",DATE(2028,8,1)>=DATE(YEAR('SwapDesk — Assumptions · Placeh'!B5),MONTH('SwapDesk — Assumptions · Placeh'!B5),1)))),'SwapDesk — Assumptions · Placeh'!C5/12,0) -> 2000 | Z6: =IF(IF(IF(ISERROR(DATE(2028,9,1)>=DATE(YEAR('SwapDesk — Assumptions · Placeh'!B5),MONTH('SwapDesk — Assumptions · Placeh'!B5),1)),DATE(2028,9,1)>=DATE(YEAR('SwapDesk — Assumptions · Placeh'!B5),MONTH('SwapDesk — Assumptions · Placeh'!B5),1),IF(DATE(YEAR('SwapDesk — Assumptions · Placeh'!B5),MONTH('SwapDesk — Assumptions · Placeh'!B5),1)="","",DATE(2028,9,1)>=DATE(YEAR('SwapDesk — Assumptions · Placeh'!B5),MONTH('SwapDesk — Assumptions · Placeh'!B5),1)))="",FALSE,IF(ISERROR(DATE(2028,9,1)>=DATE(YEAR('SwapDesk — Assumptions · Placeh'!B5),MONTH('SwapDesk — Assumptions · Placeh'!B5),1)),DATE(2028,9,1)>=DATE(YEAR('SwapDesk — Assumptions · Placeh'!B5),MONTH('SwapDesk — Assumptions · Placeh'!B5),1),IF(DATE(YEAR('SwapDesk — Assumptions · Placeh'!B5),MONTH('SwapDesk — Assumptions · Placeh'!B5),1)="","",DATE(2028,9,1)>=DATE(YEAR('SwapDesk — Assumptions · Placeh'!B5),MONTH('SwapDesk — Assumptions · Placeh'!B5),1)))),'SwapDesk — Assumptions · Placeh'!C5/12,0) -> 2000

Sheet SwapDesk — Financials · Profit
A1: SwapDesk — Financials · Profit and cash forecast
A2: Financial model (4 pages) · Main Scenario
A4: Variable / dimension | B4: 2026-10 | C4: 2026-11 | D4: 2026-12 | E4: 2027-01 | F4: 2027-02 | G4: 2027-03 | H4: 2027-04 | I4: 2027-05 | J4: 2027-06 | K4: 2027-07 | L4: 2027-08 | M4: 2027-09 | N4: 2027-10 | O4: 2027-11 | P4: 2027-12 | Q4: 2028-01 | R4: 2028-02 | S4: 2028-03 | T4: 2028-04 | U4: 2028-05 | V4: 2028-06 | W4: 2028-07 | X4: 2028-08 | Y4: 2028-09
A5: Revenue | B5: =SUM('SwapDesk — Operations · Merchan'!C39,'SwapDesk — Operations · Merchan'!C40) -> 603.99 | C5: =SUM('SwapDesk — Operations · Merchan'!D39,'SwapDesk — Operations · Merchan'!D40) -> 702.5437 | D5: =SUM('SwapDesk — Operations · Merchan'!E39,'SwapDesk — Operations · Merchan'!E40) -> 798.72232 | E5: =SUM('SwapDesk — Operations · Merchan'!F39,'SwapDesk — Operations · Merchan'!F40) -> 892.58548 | F5: =SUM('SwapDesk — Operations · Merchan'!G39,'SwapDesk — Operations · Merchan'!G40) -> 984.19126 | G5: =SUM('SwapDesk — Operations · Merchan'!H39,'SwapDesk — Operations · Merchan'!H40) -> 1073.5962 | H5: =SUM('SwapDesk — Operations · Merchan'!I39,'SwapDesk — Operations · Merchan'!I40) -> 1160.8554 | I5: =SUM('SwapDesk — Operations · Merchan'!J39,'SwapDesk — Operations · Merchan'!J40) -> 1246.0224 | ... Y5: =SUM('SwapDesk — Operations · Merchan'!Z39,'SwapDesk — Operations · Merchan'!Z40) -> 2362.9455
A6: Inference cost | B6: =SUM('SwapDesk — Operations · Merchan'!C42,'SwapDesk — Operations · Merchan'!C43) -> 58.167 | C6: =SUM('SwapDesk — Operations · Merchan'!D42,'SwapDesk — Operations · Merchan'!D43) -> 67.80147 | D6: =SUM('SwapDesk — Operations · Merchan'!E42,'SwapDesk — Operations · Merchan'!E43) -> 77.209116 | E6: =SUM('SwapDesk — Operations · Merchan'!F42,'SwapDesk — Operations · Merchan'!F43) -> 86.395499 | F6: =SUM('SwapDesk — Operations · Merchan'!G42,'SwapDesk — Operations · Merchan'!G43) -> 95.366038 | G6: =SUM('SwapDesk — Operations · Merchan'!H42,'SwapDesk — Operations · Merchan'!H43) -> 104.12601 | H6: =SUM('SwapDesk — Operations · Merchan'!I42,'SwapDesk — Operations · Merchan'!I43) -> 112.68057 | I6: =SUM('SwapDesk — Operations · Merchan'!J42,'SwapDesk — Operations · Merchan'!J43) -> 121.03472 | ... Y6: =SUM('SwapDesk — Operations · Merchan'!Z42,'SwapDesk — Operations · Merchan'!Z43) -> 231.08108
A7: Infrastructure variable cost | B7: =SUM('SwapDesk — Operations · Merchan'!C45,'SwapDesk — Operations · Merchan'!C46) -> 8.31 | C7: =SUM('SwapDesk — Operations · Merchan'!D45,'SwapDesk — Operations · Merchan'!D46) -> 9.5853 | D7: =SUM('SwapDesk — Operations · Merchan'!E45,'SwapDesk — Operations · Merchan'!E46) -> 10.826849 | E7: =SUM('SwapDesk — Operations · Merchan'!F45,'SwapDesk — Operations · Merchan'!F46) -> 12.035569 | F7: =SUM('SwapDesk — Operations · Merchan'!G45,'SwapDesk — Operations · Merchan'!G46) -> 13.212358 | G7: =SUM('SwapDesk — Operations · Merchan'!H45,'SwapDesk — Operations · Merchan'!H46) -> 14.358085 | H7: =SUM('SwapDesk — Operations · Merchan'!I45,'SwapDesk — Operations · Merchan'!I46) -> 15.473599 | I7: =SUM('SwapDesk — Operations · Merchan'!J45,'SwapDesk — Operations · Merchan'!J46) -> 16.559722 | ... Y7: =SUM('SwapDesk — Operations · Merchan'!Z45,'SwapDesk — Operations · Merchan'!Z46) -> 30.530231
A8: Merchant support cost | B8: =SUM('SwapDesk — Operations · Merchan'!C48,'SwapDesk — Operations · Merchan'!C49) -> 67.3125 | C8: =SUM('SwapDesk — Operations · Merchan'!D48,'SwapDesk — Operations · Merchan'!D49) -> 78.100625 | D8: =SUM('SwapDesk — Operations · Merchan'!E48,'SwapDesk — Operations · Merchan'!E49) -> 88.621456 | E8: =SUM('SwapDesk — Operations · Merchan'!F48,'SwapDesk — Operations · Merchan'!F49) -> 98.881886 | F8: =SUM('SwapDesk — Operations · Merchan'!G48,'SwapDesk — Operations · Merchan'!G49) -> 108.88862 | G8: =SUM('SwapDesk — Operations · Merchan'!H48,'SwapDesk — Operations · Merchan'!H49) -> 118.64819 | H8: =SUM('SwapDesk — Operations · Merchan'!I48,'SwapDesk — Operations · Merchan'!I49) -> 128.16695 | I8: =SUM('SwapDesk — Operations · Merchan'!J48,'SwapDesk — Operations · Merchan'!J49) -> 137.45108 | ... Y8: =SUM('SwapDesk — Operations · Merchan'!Z48,'SwapDesk — Operations · Merchan'!Z49) -> 258.54552
A9: Fixed hosting | B9: =IF('SwapDesk — Assumptions · Commer'!B12="","",'SwapDesk — Assumptions · Commer'!B12) -> 75 | C9: =IF('SwapDesk — Assumptions · Commer'!B12="","",'SwapDesk — Assumptions · Commer'!B12) -> 75 | D9: =IF('SwapDesk — Assumptions · Commer'!B12="","",'SwapDesk — Assumptions · Commer'!B12) -> 75 | E9: =IF('SwapDesk — Assumptions · Commer'!B12="","",'SwapDesk — Assumptions · Commer'!B12) -> 75 | F9: =IF('SwapDesk — Assumptions · Commer'!B12="","",'SwapDesk — Assumptions · Commer'!B12) -> 75 | G9: =IF('SwapDesk — Assumptions · Commer'!B12="","",'SwapDesk — Assumptions · Commer'!B12) -> 75 | H9: =IF('SwapDesk — Assumptions · Commer'!B12="","",'SwapDesk — Assumptions · Commer'!B12) -> 75 | I9: =IF('SwapDesk — Assumptions · Commer'!B12="","",'SwapDesk — Assumptions · Commer'!B12) -> 75 | J9: =IF('SwapDesk — Assumptions · Commer'!B12="","",'SwapDesk — Assumptions · Commer'!B12) -> 75 | K9: =IF('SwapDesk — Assumptions · Commer'!B12="","",'SwapDesk — Assumptions · Commer'!B12) -> 75 | L9: =IF('SwapDesk — Assumptions · Commer'!B12="","",'SwapDesk — Assumptions · Commer'!B12) -> 75 | M9: =IF('SwapDesk — Assumptions · Commer'!B12="","",'SwapDesk — Assumptions · Commer'!B12) -> 75 | N9: =IF('SwapDesk — Assumptions · Commer'!B12="","",'SwapDesk — Assumptions · Commer'!B12) -> 75 | O9: =IF('SwapDesk — Assumptions · Commer'!B12="","",'SwapDesk — Assumptions · Commer'!B12) -> 75 | P9: =IF('SwapDesk — Assumptions · Commer'!B12="","",'SwapDesk — Assumptions · Commer'!B12) -> 75 | Q9: =IF('SwapDesk — Assumptions · Commer'!B12="","",'SwapDesk — Assumptions · Commer'!B12) -> 75 | R9: =IF('SwapDesk — Assumptions · Commer'!B12="","",'SwapDesk — Assumptions · Commer'!B12) -> 75 | S9: =IF('SwapDesk — Assumptions · Commer'!B12="","",'SwapDesk — Assumptions · Commer'!B12) -> 75 | T9: =IF('SwapDesk — Assumptions · Commer'!B12="","",'SwapDesk — Assumptions · Commer'!B12) -> 75 | U9: =IF('SwapDesk — Assumptions · Commer'!B12="","",'SwapDesk — Assumptions · Commer'!B12) -> 75 | V9: =IF('SwapDesk — Assumptions · Commer'!B12="","",'SwapDesk — Assumptions · Commer'!B12) -> 75 | W9: =IF('SwapDesk — Assumptions · Commer'!B12="","",'SwapDesk — Assumptions · Commer'!B12) -> 75 | X9: =IF('SwapDesk — Assumptions · Commer'!B12="","",'SwapDesk — Assumptions · Commer'!B12) -> 75 | Y9: =IF('SwapDesk — Assumptions · Commer'!B12="","",'SwapDesk — Assumptions · Commer'!B12) -> 75
A10: Cost of service | B10: ='SwapDesk — Financials · Profit'!B6+'SwapDesk — Financials · Profit'!B7+'SwapDesk — Financials · Profit'!B8+'SwapDesk — Financials · Profit'!B9 -> 208.7895 | C10: ='SwapDesk — Financials · Profit'!C6+'SwapDesk — Financials · Profit'!C7+'SwapDesk — Financials · Profit'!C8+'SwapDesk — Financials · Profit'!C9 -> 230.48739 | D10: ='SwapDesk — Financials · Profit'!D6+'SwapDesk — Financials · Profit'!D7+'SwapDesk — Financials · Profit'!D8+'SwapDesk — Financials · Profit'!D9 -> 251.65742 | E10: ='SwapDesk — Financials · Profit'!E6+'SwapDesk — Financials · Profit'!E7+'SwapDesk — Financials · Profit'!E8+'SwapDesk — Financials · Profit'!E9 -> 272.31295 | F10: ='SwapDesk — Financials · Profit'!F6+'SwapDesk — Financials · Profit'!F7+'SwapDesk — Financials · Profit'!F8+'SwapDesk — Financials · Profit'!F9 -> 292.46702 | G10: ='SwapDesk — Financials · Profit'!G6+'SwapDesk — Financials · Profit'!G7+'SwapDesk — Financials · Profit'!G8+'SwapDesk — Financials · Profit'!G9 -> 312.13229 | H10: ='SwapDesk — Financials · Profit'!H6+'SwapDesk — Financials · Profit'!H7+'SwapDesk — Financials · Profit'!H8+'SwapDesk — Financials · Profit'!H9 -> 331.32111 | I10: ='SwapDesk — Financials · Profit'!I6+'SwapDesk — Financials · Profit'!I7+'SwapDesk — Financials · Profit'!I8+'SwapDesk — Financials · Profit'!I9 -> 350.04552 | ... Y10: ='SwapDesk — Financials · Profit'!Y6+'SwapDesk — Financials · Profit'!Y7+'SwapDesk — Financials · Profit'!Y8+'SwapDesk — Financials · Profit'!Y9 -> 595.15683
A11: Gross profit | B11: ='SwapDesk — Financials · Profit'!B5-'SwapDesk — Financials · Profit'!B10 -> 395.2005 | C11: ='SwapDesk — Financials · Profit'!C5-'SwapDesk — Financials · Profit'!C10 -> 472.0563 | D11: ='SwapDesk — Financials · Profit'!D5-'SwapDesk — Financials · Profit'!D10 -> 547.0649 | E11: ='SwapDesk — Financials · Profit'!E5-'SwapDesk — Financials · Profit'!E10 -> 620.27253 | F11: ='SwapDesk — Financials · Profit'!F5-'SwapDesk — Financials · Profit'!F10 -> 691.72424 | G11: ='SwapDesk — Financials · Profit'!G5-'SwapDesk — Financials · Profit'!G10 -> 761.4639 | H11: ='SwapDesk — Financials · Profit'!H5-'SwapDesk — Financials · Profit'!H10 -> 829.53425 | I11: ='SwapDesk — Financials · Profit'!I5-'SwapDesk — Financials · Profit'!I10 -> 895.97689 | ... Y11: ='SwapDesk — Financials · Profit'!Y5-'SwapDesk — Financials · Profit'!Y10 -> 1767.7887
A12: Gross margin | B12: =IFERROR('SwapDesk — Financials · Profit'!B11/'SwapDesk — Financials · Profit'!B5,"") -> 0.6543163 | C12: =IFERROR('SwapDesk — Financials · Profit'!C11/'SwapDesk — Financials · Profit'!C5,"") -> 0.67192447 | D12: =IFERROR('SwapDesk — Financials · Profit'!D11/'SwapDesk — Financials · Profit'!D5,"") -> 0.68492502 | E12: =IFERROR('SwapDesk — Financials · Profit'!E11/'SwapDesk — Financials · Profit'!E5,"") -> 0.69491667 | F12: =IFERROR('SwapDesk — Financials · Profit'!F11/'SwapDesk — Financials · Profit'!F5,"") -> 0.70283518 | G12: =IFERROR('SwapDesk — Financials · Profit'!G11/'SwapDesk — Financials · Profit'!G5,"") -> 0.70926472 | H12: =IFERROR('SwapDesk — Financials · Profit'!H11/'SwapDesk — Financials · Profit'!H5,"") -> 0.71458881 | I12: =IFERROR('SwapDesk — Financials · Profit'!I11/'SwapDesk — Financials · Profit'!I5,"") -> 0.71906964 | ... Y12: =IFERROR('SwapDesk — Financials · Profit'!Y11/'SwapDesk — Financials · Profit'!Y5,"") -> 0.74812926
A13: Onboarding cost | B13: =SUM('SwapDesk — Operations · Merchan'!C51,'SwapDesk — Operations · Merchan'!C52) -> 56.25 | C13: =SUM('SwapDesk — Operations · Merchan'!D51,'SwapDesk — Operations · Merchan'!D52) -> 56.25 | D13: =SUM('SwapDesk — Operations · Merchan'!E51,'SwapDesk — Operations · Merchan'!E52) -> 56.25 | E13: =SUM('SwapDesk — Operations · Merchan'!F51,'SwapDesk — Operations · Merchan'!F52) -> 56.25 | F13: =SUM('SwapDesk — Operations · Merchan'!G51,'SwapDesk — Operations · Merchan'!G52) -> 56.25 | G13: =SUM('SwapDesk — Operations · Merchan'!H51,'SwapDesk — Operations · Merchan'!H52) -> 56.25 | H13: =SUM('SwapDesk — Operations · Merchan'!I51,'SwapDesk — Operations · Merchan'!I52) -> 56.25 | I13: =SUM('SwapDesk — Operations · Merchan'!J51,'SwapDesk — Operations · Merchan'!J52) -> 56.25 | ... Y13: =SUM('SwapDesk — Operations · Merchan'!Z51,'SwapDesk — Operations · Merchan'!Z52) -> 56.25
A14: Acquisition spending | B14: =SUM('SwapDesk — Operations · Merchan'!C54,'SwapDesk — Operations · Merchan'!C55) -> 150 | C14: =SUM('SwapDesk — Operations · Merchan'!D54,'SwapDesk — Operations · Merchan'!D55) -> 150 | D14: =SUM('SwapDesk — Operations · Merchan'!E54,'SwapDesk — Operations · Merchan'!E55) -> 150 | E14: =SUM('SwapDesk — Operations · Merchan'!F54,'SwapDesk — Operations · Merchan'!F55) -> 150 | F14: =SUM('SwapDesk — Operations · Merchan'!G54,'SwapDesk — Operations · Merchan'!G55) -> 150 | G14: =SUM('SwapDesk — Operations · Merchan'!H54,'SwapDesk — Operations · Merchan'!H55) -> 150 | H14: =SUM('SwapDesk — Operations · Merchan'!I54,'SwapDesk — Operations · Merchan'!I55) -> 150 | I14: =SUM('SwapDesk — Operations · Merchan'!J54,'SwapDesk — Operations · Merchan'!J55) -> 150 | ... Y14: =SUM('SwapDesk — Operations · Merchan'!Z54,'SwapDesk — Operations · Merchan'!Z55) -> 150
A15: Founder payroll | B15: =SUM('SwapDesk — Financials · Founder'!C6) -> 0 | C15: =SUM('SwapDesk — Financials · Founder'!D6) -> 0 | D15: =SUM('SwapDesk — Financials · Founder'!E6) -> 0 | E15: =SUM('SwapDesk — Financials · Founder'!F6) -> 2000 | F15: =SUM('SwapDesk — Financials · Founder'!G6) -> 2000 | G15: =SUM('SwapDesk — Financials · Founder'!H6) -> 2000 | H15: =SUM('SwapDesk — Financials · Founder'!I6) -> 2000 | I15: =SUM('SwapDesk — Financials · Founder'!J6) -> 2000 | ... Y15: =SUM('SwapDesk — Financials · Founder'!Z6) -> 2000
A16: Other overhead | B16: =IF('SwapDesk — Assumptions · Commer'!B14="","",'SwapDesk — Assumptions · Commer'!B14) -> 150 | C16: =IF('SwapDesk — Assumptions · Commer'!B14="","",'SwapDesk — Assumptions · Commer'!B14) -> 150 | D16: =IF('SwapDesk — Assumptions · Commer'!B14="","",'SwapDesk — Assumptions · Commer'!B14) -> 150 | E16: =IF('SwapDesk — Assumptions · Commer'!B14="","",'SwapDesk — Assumptions · Commer'!B14) -> 150 | F16: =IF('SwapDesk — Assumptions · Commer'!B14="","",'SwapDesk — Assumptions · Commer'!B14) -> 150 | G16: =IF('SwapDesk — Assumptions · Commer'!B14="","",'SwapDesk — Assumptions · Commer'!B14) -> 150 | H16: =IF('SwapDesk — Assumptions · Commer'!B14="","",'SwapDesk — Assumptions · Commer'!B14) -> 150 | I16: =IF('SwapDesk — Assumptions · Commer'!B14="","",'SwapDesk — Assumptions · Commer'!B14) -> 150 | J16: =IF('SwapDesk — Assumptions · Commer'!B14="","",'SwapDesk — Assumptions · Commer'!B14) -> 150 | K16: =IF('SwapDesk — Assumptions · Commer'!B14="","",'SwapDesk — Assumptions · Commer'!B14) -> 150 | L16: =IF('SwapDesk — Assumptions · Commer'!B14="","",'SwapDesk — Assumptions · Commer'!B14) -> 150 | M16: =IF('SwapDesk — Assumptions · Commer'!B14="","",'SwapDesk — Assumptions · Commer'!B14) -> 150 | N16: =IF('SwapDesk — Assumptions · Commer'!B14="","",'SwapDesk — Assumptions · Commer'!B14) -> 150 | O16: =IF('SwapDesk — Assumptions · Commer'!B14="","",'SwapDesk — Assumptions · Commer'!B14) -> 150 | P16: =IF('SwapDesk — Assumptions · Commer'!B14="","",'SwapDesk — Assumptions · Commer'!B14) -> 150 | Q16: =IF('SwapDesk — Assumptions · Commer'!B14="","",'SwapDesk — Assumptions · Commer'!B14) -> 150 | R16: =IF('SwapDesk — Assumptions · Commer'!B14="","",'SwapDesk — Assumptions · Commer'!B14) -> 150 | S16: =IF('SwapDesk — Assumptions · Commer'!B14="","",'SwapDesk — Assumptions · Commer'!B14) -> 150 | T16: =IF('SwapDesk — Assumptions · Commer'!B14="","",'SwapDesk — Assumptions · Commer'!B14) -> 150 | U16: =IF('SwapDesk — Assumptions · Commer'!B14="","",'SwapDesk — Assumptions · Commer'!B14) -> 150 | V16: =IF('SwapDesk — Assumptions · Commer'!B14="","",'SwapDesk — Assumptions · Commer'!B14) -> 150 | W16: =IF('SwapDesk — Assumptions · Commer'!B14="","",'SwapDesk — Assumptions · Commer'!B14) -> 150 | X16: =IF('SwapDesk — Assumptions · Commer'!B14="","",'SwapDesk — Assumptions · Commer'!B14) -> 150 | Y16: =IF('SwapDesk — Assumptions · Commer'!B14="","",'SwapDesk — Assumptions · Commer'!B14) -> 150
A17: Operating expenses | B17: ='SwapDesk — Financials · Profit'!B13+'SwapDesk — Financials · Profit'!B14+'SwapDesk — Financials · Profit'!B15+'SwapDesk — Financials · Profit'!B16 -> 356.25 | C17: ='SwapDesk — Financials · Profit'!C13+'SwapDesk — Financials · Profit'!C14+'SwapDesk — Financials · Profit'!C15+'SwapDesk — Financials · Profit'!C16 -> 356.25 | D17: ='SwapDesk — Financials · Profit'!D13+'SwapDesk — Financials · Profit'!D14+'SwapDesk — Financials · Profit'!D15+'SwapDesk — Financials · Profit'!D16 -> 356.25 | E17: ='SwapDesk — Financials · Profit'!E13+'SwapDesk — Financials · Profit'!E14+'SwapDesk — Financials · Profit'!E15+'SwapDesk — Financials · Profit'!E16 -> 2356.25 | F17: ='SwapDesk — Financials · Profit'!F13+'SwapDesk — Financials · Profit'!F14+'SwapDesk — Financials · Profit'!F15+'SwapDesk — Financials · Profit'!F16 -> 2356.25 | G17: ='SwapDesk — Financials · Profit'!G13+'SwapDesk — Financials · Profit'!G14+'SwapDesk — Financials · Profit'!G15+'SwapDesk — Financials · Profit'!G16 -> 2356.25 | H17: ='SwapDesk — Financials · Profit'!H13+'SwapDesk — Financials · Profit'!H14+'SwapDesk — Financials · Profit'!H15+'SwapDesk — Financials · Profit'!H16 -> 2356.25 | I17: ='SwapDesk — Financials · Profit'!I13+'SwapDesk — Financials · Profit'!I14+'SwapDesk — Financials · Profit'!I15+'SwapDesk — Financials · Profit'!I16 -> 2356.25 | ... Y17: ='SwapDesk — Financials · Profit'!Y13+'SwapDesk — Financials · Profit'!Y14+'SwapDesk — Financials · Profit'!Y15+'SwapDesk — Financials · Profit'!Y16 -> 2356.25
A18: Operating profit | B18: ='SwapDesk — Financials · Profit'!B11-'SwapDesk — Financials · Profit'!B17 -> 38.9505 | C18: ='SwapDesk — Financials · Profit'!C11-'SwapDesk — Financials · Profit'!C17 -> 115.8063 | D18: ='SwapDesk — Financials · Profit'!D11-'SwapDesk — Financials · Profit'!D17 -> 190.8149 | E18: ='SwapDesk — Financials · Profit'!E11-'SwapDesk — Financials · Profit'!E17 -> -1735.9775 | F18: ='SwapDesk — Financials · Profit'!F11-'SwapDesk — Financials · Profit'!F17 -> -1664.5258 | G18: ='SwapDesk — Financials · Profit'!G11-'SwapDesk — Financials · Profit'!G17 -> -1594.7861 | H18: ='SwapDesk — Financials · Profit'!H11-'SwapDesk — Financials · Profit'!H17 -> -1526.7158 | I18: ='SwapDesk — Financials · Profit'!I11-'SwapDesk — Financials · Profit'!I17 -> -1460.2731 | ... Y18: ='SwapDesk — Financials · Profit'!Y11-'SwapDesk — Financials · Profit'!Y17 -> -588.46133
A19: Cash collections | B19: =IF('SwapDesk — Financials · Profit'!B5="","",'SwapDesk — Financials · Profit'!B5) -> 603.99 | C19: =IF('SwapDesk — Financials · Profit'!C5="","",'SwapDesk — Financials · Profit'!C5) -> 702.5437 | D19: =IF('SwapDesk — Financials · Profit'!D5="","",'SwapDesk — Financials · Profit'!D5) -> 798.72232 | E19: =IF('SwapDesk — Financials · Profit'!E5="","",'SwapDesk — Financials · Profit'!E5) -> 892.58548 | F19: =IF('SwapDesk — Financials · Profit'!F5="","",'SwapDesk — Financials · Profit'!F5) -> 984.19126 | G19: =IF('SwapDesk — Financials · Profit'!G5="","",'SwapDesk — Financials · Profit'!G5) -> 1073.5962 | H19: =IF('SwapDesk — Financials · Profit'!H5="","",'SwapDesk — Financials · Profit'!H5) -> 1160.8554 | I19: =IF('SwapDesk — Financials · Profit'!I5="","",'SwapDesk — Financials · Profit'!I5) -> 1246.0224 | ... Y19: =IF('SwapDesk — Financials · Profit'!Y5="","",'SwapDesk — Financials · Profit'!Y5) -> 2362.9455
A20: Cash payments | B20: ='SwapDesk — Financials · Profit'!B10+'SwapDesk — Financials · Profit'!B17 -> 565.0395 | C20: ='SwapDesk — Financials · Profit'!C10+'SwapDesk — Financials · Profit'!C17 -> 586.73739 | D20: ='SwapDesk — Financials · Profit'!D10+'SwapDesk — Financials · Profit'!D17 -> 607.90742 | E20: ='SwapDesk — Financials · Profit'!E10+'SwapDesk — Financials · Profit'!E17 -> 2628.563 | F20: ='SwapDesk — Financials · Profit'!F10+'SwapDesk — Financials · Profit'!F17 -> 2648.717 | G20: ='SwapDesk — Financials · Profit'!G10+'SwapDesk — Financials · Profit'!G17 -> 2668.3823 | H20: ='SwapDesk — Financials · Profit'!H10+'SwapDesk — Financials · Profit'!H17 -> 2687.5711 | I20: ='SwapDesk — Financials · Profit'!I10+'SwapDesk — Financials · Profit'!I17 -> 2706.2955 | ... Y20: ='SwapDesk — Financials · Profit'!Y10+'SwapDesk — Financials · Profit'!Y17 -> 2951.4068
A21: Net cash flow | B21: ='SwapDesk — Financials · Profit'!B19-'SwapDesk — Financials · Profit'!B20 -> 38.9505 | C21: ='SwapDesk — Financials · Profit'!C19-'SwapDesk — Financials · Profit'!C20 -> 115.8063 | D21: ='SwapDesk — Financials · Profit'!D19-'SwapDesk — Financials · Profit'!D20 -> 190.8149 | E21: ='SwapDesk — Financials · Profit'!E19-'SwapDesk — Financials · Profit'!E20 -> -1735.9775 | F21: ='SwapDesk — Financials · Profit'!F19-'SwapDesk — Financials · Profit'!F20 -> -1664.5258 | G21: ='SwapDesk — Financials · Profit'!G19-'SwapDesk — Financials · Profit'!G20 -> -1594.7861 | H21: ='SwapDesk — Financials · Profit'!H19-'SwapDesk — Financials · Profit'!H20 -> -1526.7158 | I21: ='SwapDesk — Financials · Profit'!I19-'SwapDesk — Financials · Profit'!I20 -> -1460.2731 | ... Y21: ='SwapDesk — Financials · Profit'!Y19-'SwapDesk — Financials · Profit'!Y20 -> -588.46133
A22: Ending cash | B22: ='Model inputs'!K14+'SwapDesk — Financials · Profit'!B21 -> 15038.951 | C22: ='SwapDesk — Financials · Profit'!B22+'SwapDesk — Financials · Profit'!C21 -> 15154.757 | D22: ='SwapDesk — Financials · Profit'!C22+'SwapDesk — Financials · Profit'!D21 -> 15345.572 | E22: ='SwapDesk — Financials · Profit'!D22+'SwapDesk — Financials · Profit'!E21 -> 13609.594 | F22: ='SwapDesk — Financials · Profit'!E22+'SwapDesk — Financials · Profit'!F21 -> 11945.068 | G22: ='SwapDesk — Financials · Profit'!F22+'SwapDesk — Financials · Profit'!G21 -> 10350.282 | H22: ='SwapDesk — Financials · Profit'!G22+'SwapDesk — Financials · Profit'!H21 -> 8823.5666 | I22: ='SwapDesk — Financials · Profit'!H22+'SwapDesk — Financials · Profit'!I21 -> 7363.2935 | J22: ='SwapDesk — Financials · Profit'!I22+'SwapDesk — Financials · Profit'!J21 -> 5967.8759 | ... Y22: ='SwapDesk — Financials · Profit'!X22+'SwapDesk — Financials · Profit'!Y21 -> -8147.4205
A23: Funding shortfall | B23: =MAX(-'SwapDesk — Financials · Profit'!B22,0) -> 0 | C23: =MAX(-'SwapDesk — Financials · Profit'!C22,0) -> 0 | D23: =MAX(-'SwapDesk — Financials · Profit'!D22,0) -> 0 | E23: =MAX(-'SwapDesk — Financials · Profit'!E22,0) -> 0 | F23: =MAX(-'SwapDesk — Financials · Profit'!F22,0) -> 0 | G23: =MAX(-'SwapDesk — Financials · Profit'!G22,0) -> 0 | H23: =MAX(-'SwapDesk — Financials · Profit'!H22,0) -> 0 | I23: =MAX(-'SwapDesk — Financials · Profit'!I22,0) -> 0 | ... Y23: =MAX(-'SwapDesk — Financials · Profit'!Y22,0) -> 8147.4205
A24: Cash runway at current burn | B24: =IF(IF(IF(ISERROR('SwapDesk — Financials · Profit'!B21<0),'SwapDesk — Financials · Profit'!B21<0,IF('SwapDesk — Financials · Profit'!B21="","",'SwapDesk — Financials · Profit'!B21<0))="",FALSE,IF(ISERROR('SwapDesk — Financials · Profit'!B21<0),'SwapDesk — Financials · Profit'!B21<0,IF('SwapDesk — Financials · Profit'!B21="","",'SwapDesk — Financials · Profit'!B21<0))),MAX('SwapDesk — Financials · Profit'!B22,0)/-'SwapDesk — Financials · Profit'!B21,"") | C24: =IF(IF(IF(ISERROR('SwapDesk — Financials · Profit'!C21<0),'SwapDesk — Financials · Profit'!C21<0,IF('SwapDesk — Financials · Profit'!C21="","",'SwapDesk — Financials · Profit'!C21<0))="",FALSE,IF(ISERROR('SwapDesk — Financials · Profit'!C21<0),'SwapDesk — Financials · Profit'!C21<0,IF('SwapDesk — Financials · Profit'!C21="","",'SwapDesk — Financials · Profit'!C21<0))),MAX('SwapDesk — Financials · Profit'!C22,0)/-'SwapDesk — Financials · Profit'!C21,"") | D24: =IF(IF(IF(ISERROR('SwapDesk — Financials · Profit'!D21<0),'SwapDesk — Financials · Profit'!D21<0,IF('SwapDesk — Financials · Profit'!D21="","",'SwapDesk — Financials · Profit'!D21<0))="",FALSE,IF(ISERROR('SwapDesk — Financials · Profit'!D21<0),'SwapDesk — Financials · Profit'!D21<0,IF('SwapDesk — Financials · Profit'!D21="","",'SwapDesk — Financials · Profit'!D21<0))),MAX('SwapDesk — Financials · Profit'!D22,0)/-'SwapDesk — Financials · Profit'!D21,"") | E24: =IF(IF(IF(ISERROR('SwapDesk — Financials · Profit'!E21<0),'SwapDesk — Financials · Profit'!E21<0,IF('SwapDesk — Financials · Profit'!E21="","",'SwapDesk — Financials · Profit'!E21<0))="",FALSE,IF(ISERROR('SwapDesk — Financials · Profit'!E21<0),'SwapDesk — Financials · Profit'!E21<0,IF('SwapDesk — Financials · Profit'!E21="","",'SwapDesk — Financials · Profit'!E21<0))),MAX('SwapDesk — Financials · Profit'!E22,0)/-'SwapDesk — Financials · Profit'!E21,"") -> 7.8397298 | F24: =IF(IF(IF(ISERROR('SwapDesk — Financials · Profit'!F21<0),'SwapDesk — Financials · Profit'!F21<0,IF('SwapDesk — Financials · Profit'!F21="","",'SwapDesk — Financials · Profit'!F21<0))="",FALSE,IF(ISERROR('SwapDesk — Financials · Profit'!F21<0),'SwapDesk — Financials · Profit'!F21<0,IF('SwapDesk — Financials · Profit'!F21="","",'SwapDesk — Financials · Profit'!F21<0))),MAX('SwapDesk — Financials · Profit'!F22,0)/-'SwapDesk — Financials · Profit'!F21,"") -> 7.1762593 | G24: =IF(IF(IF(ISERROR('SwapDesk — Financials · Profit'!G21<0),'SwapDesk — Financials · Profit'!G21<0,IF('SwapDesk — Financials · Profit'!G21="","",'SwapDesk — Financials · Profit'!G21<0))="",FALSE,IF(ISERROR('SwapDesk — Financials · Profit'!G21<0),'SwapDesk — Financials · Profit'!G21<0,IF('SwapDesk — Financials · Profit'!G21="","",'SwapDesk — Financials · Profit'!G21<0))),MAX('SwapDesk — Financials · Profit'!G22,0)/-'SwapDesk — Financials · Profit'!G21,"") -> 6.4900756 | H24: =IF(IF(IF(ISERROR('SwapDesk — Financials · Profit'!H21<0),'SwapDesk — Financials · Profit'!H21<0,IF('SwapDesk — Financials · Profit'!H21="","",'SwapDesk — Financials · Profit'!H21<0))="",FALSE,IF(ISERROR('SwapDesk — Financials · Profit'!H21<0),'SwapDesk — Financials · Profit'!H21<0,IF('SwapDesk — Financials · Profit'!H21="","",'SwapDesk — Financials · Profit'!H21<0))),MAX('SwapDesk — Financials · Profit'!H22,0)/-'SwapDesk — Financials · Profit'!H21,"") -> 5.779443 | I24: =IF(IF(IF(ISERROR('SwapDesk — Financials · Profit'!I21<0),'SwapDesk — Financials · Profit'!I21<0,IF('SwapDesk — Financials · Profit'!I21="","",'SwapDesk — Financials · Profit'!I21<0))="",FALSE,IF(ISERROR('SwapDesk — Financials · Profit'!I21<0),'SwapDesk — Financials · Profit'!I21<0,IF('SwapDesk — Financials · Profit'!I21="","",'SwapDesk — Financials · Profit'!I21<0))),MAX('SwapDesk — Financials · Profit'!I22,0)/-'SwapDesk — Financials · Profit'!I21,"") -> 5.0424085 | ... Y24: =IF(IF(IF(ISERROR('SwapDesk — Financials · Profit'!Y21<0),'SwapDesk — Financials · Profit'!Y21<0,IF('SwapDesk — Financials · Profit'!Y21="","",'SwapDesk — Financials · Profit'!Y21<0))="",FALSE,IF(ISERROR('SwapDesk — Financials · Profit'!Y21<0),'SwapDesk — Financials · Profit'!Y21<0,IF('SwapDesk — Financials · Profit'!Y21="","",'SwapDesk — Financials · Profit'!Y21<0))),MAX('SwapDesk — Financials · Profit'!Y22,0)/-'SwapDesk — Financials · Profit'!Y21,"") -> 0
A25: Inference cost per verified arrangement | B25: =IFERROR('SwapDesk — Financials · Profit'!B6/'SwapDesk — Operations · Merchan'!C20,"") -> 0.053076923 | C25: =IFERROR('SwapDesk — Financials · Profit'!C6/'SwapDesk — Operations · Merchan'!D20,"") -> 0.053076923 | D25: =IFERROR('SwapDesk — Financials · Profit'!D6/'SwapDesk — Operations · Merchan'!E20,"") -> 0.053076923 | E25: =IFERROR('SwapDesk — Financials · Profit'!E6/'SwapDesk — Operations · Merchan'!F20,"") -> 0.053076923 | F25: =IFERROR('SwapDesk — Financials · Profit'!F6/'SwapDesk — Operations · Merchan'!G20,"") -> 0.053076923 | G25: =IFERROR('SwapDesk — Financials · Profit'!G6/'SwapDesk — Operations · Merchan'!H20,"") -> 0.053076923 | H25: =IFERROR('SwapDesk — Financials · Profit'!H6/'SwapDesk — Operations · Merchan'!I20,"") -> 0.053076923 | I25: =IFERROR('SwapDesk — Financials · Profit'!I6/'SwapDesk — Operations · Merchan'!J20,"") -> 0.053076923 | ... Y25: =IFERROR('SwapDesk — Financials · Profit'!Y6/'SwapDesk — Operations · Merchan'!Z20,"") -> 0.053076923
A26: Gross profit per store | B26: =IFERROR('SwapDesk — Financials · Profit'!B11/'SwapDesk — Operations · Merchan'!C14,"") -> 47.55722 | C26: =IFERROR('SwapDesk — Financials · Profit'!C11/'SwapDesk — Operations · Merchan'!D14,"") -> 49.247943 | D26: =IFERROR('SwapDesk — Financials · Profit'!D11/'SwapDesk — Operations · Merchan'!E14,"") -> 50.528542 | E26: =IFERROR('SwapDesk — Financials · Profit'!E11/'SwapDesk — Operations · Merchan'!F14,"") -> 51.536617 | F26: =IFERROR('SwapDesk — Financials · Profit'!F11/'SwapDesk — Operations · Merchan'!G14,"") -> 52.354338 | G26: =IFERROR('SwapDesk — Financials · Profit'!G11/'SwapDesk — Operations · Merchan'!H14,"") -> 53.033806 | H26: =IFERROR('SwapDesk — Financials · Profit'!H11/'SwapDesk — Operations · Merchan'!I14,"") -> 53.609652 | I26: =IFERROR('SwapDesk — Financials · Profit'!I11/'SwapDesk — Operations · Merchan'!J14,"") -> 54.105793 | ... Y26: =IFERROR('SwapDesk — Financials · Profit'!Y11/'SwapDesk — Operations · Merchan'!Z14,"") -> 57.902892

Sheet SwapDesk — Business Plan · Quar
A1: SwapDesk — Business Plan · Quarterly scenario comparison
A2: Financial model (4 pages) · Main Scenario
A4: Variable / dimension | B4: 2026-10 | C4: 2026-10 > Growth | D4: 2026-10 > Bad Reliability | E4: 2027-01 | F4: 2027-01 > Growth | G4: 2027-01 > Bad Reliability | H4: 2027-04 | I4: 2027-04 > Growth | J4: 2027-04 > Bad Reliability | K4: 2027-07 | L4: 2027-07 > Growth | M4: 2027-07 > Bad Reliability | N4: 2027-10 | O4: 2027-10 > Growth | P4: 2027-10 > Bad Reliability | Q4: 2028-01 | R4: 2028-01 > Growth | S4: 2028-01 > Bad Reliability | T4: 2028-04 | U4: 2028-04 > Growth | V4: 2028-04 > Bad Reliability | W4: 2028-07 | X4: 2028-07 > Growth | Y4: 2028-07 > Bad Reliability
A5: Revenue | B5: =SUM('SwapDesk — Operations · Merchan'!C38,'SwapDesk — Operations · Merchan'!D38,'SwapDesk — Operations · Merchan'!E38) -> 2105.256 | C5: =SUM('Model inputs'!L54,'Model inputs'!M54,'Model inputs'!N54) -> 3771.3763 | D5: =SUM('Model inputs'!L53,'Model inputs'!M53,'Model inputs'!N53) -> 1673.2605 | E5: =SUM('SwapDesk — Operations · Merchan'!F38,'SwapDesk — Operations · Merchan'!G38,'SwapDesk — Operations · Merchan'!H38) -> 2950.3729 | F5: =SUM('Model inputs'!O54,'Model inputs'!P54,'Model inputs'!Q54) -> 6859.568 | G5: =SUM('Model inputs'!O53,'Model inputs'!P53,'Model inputs'!Q53) -> 2205.5019 | H5: =SUM('SwapDesk — Operations · Merchan'!I38,'SwapDesk — Operations · Merchan'!J38,'SwapDesk — Operations · Merchan'!K38) -> 3736.0274 | I5: =SUM('Model inputs'!R54,'Model inputs'!S54,'Model inputs'!T54) -> 9793.4315 | J5: =SUM('Model inputs'!R53,'Model inputs'!S53,'Model inputs'!T53) -> 2654.9456 | K5: =SUM('SwapDesk — Operations · Merchan'!L38,'SwapDesk — Operations · Merchan'!M38,'SwapDesk — Operations · Merchan'!N38) -> 4466.5688 | L5: =SUM('Model inputs'!U54,'Model inputs'!V54,'Model inputs'!W54) -> 12580.833 | M5: =SUM('Model inputs'!U53,'Model inputs'!V53,'Model inputs'!W53) -> 3034.5674 | N5: =SUM('SwapDesk — Operations · Merchan'!O38,'SwapDesk — Operations · Merchan'!P38,'SwapDesk — Operations · Merchan'!Q38) -> 5146.0164 | O5: =SUM('Model inputs'!X54,'Model inputs'!Y54,'Model inputs'!Z54) -> 15229.23 | P5: =SUM('Model inputs'!X53,'Model inputs'!Y53,'Model inputs'!Z53) -> 3355.2945 | Q5: =SUM('SwapDesk — Operations · Merchan'!R38,'SwapDesk — Operations · Merchan'!S38,'SwapDesk — Operations · Merchan'!T38) -> 5778.085 | R5: =SUM('Model inputs'!AA54,'Model inputs'!AB54,'Model inputs'!AC54) -> 17745.693 | S5: =SUM('Model inputs'!AA53,'Model inputs'!AB53,'Model inputs'!AC53) -> 3626.3319 | T5: =SUM('SwapDesk — Operations · Merchan'!U38,'SwapDesk — Operations · Merchan'!V38,'SwapDesk — Operations · Merchan'!W38) -> 6366.209 | U5: =SUM('Model inputs'!AD54,'Model inputs'!AE54,'Model inputs'!AF54) -> 20136.924 | V5: =SUM('Model inputs'!AD53,'Model inputs'!AE53,'Model inputs'!AF53) -> 3855.435 | W5: =SUM('SwapDesk — Operations · Merchan'!X38,'SwapDesk — Operations · Merchan'!Y38,'SwapDesk — Operations · Merchan'!Z38) -> 6913.5644 | X5: =SUM('Model inputs'!AG54,'Model inputs'!AH54,'Model inputs'!AI54) -> 22409.28 | Y5: =SUM('Model inputs'!AG53,'Model inputs'!AH53,'Model inputs'!AI53) -> 4049.14
A6: Gross profit | B6: =SUM('SwapDesk — Financials · Profit'!B11,'SwapDesk — Financials · Profit'!C11,'SwapDesk — Financials · Profit'!D11) -> 1414.3217 | C6: =SUM('Model inputs'!L31,'Model inputs'!M31,'Model inputs'!N31) -> 2792.4121 | D6: =SUM('Model inputs'!L30,'Model inputs'!M30,'Model inputs'!N30) -> 705.54642 | E6: =SUM('SwapDesk — Financials · Profit'!E11,'SwapDesk — Financials · Profit'!F11,'SwapDesk — Financials · Profit'!G11) -> 2073.4607 | F6: =SUM('Model inputs'!O31,'Model inputs'!P31,'Model inputs'!Q31) -> 5267.5202 | G6: =SUM('Model inputs'!O30,'Model inputs'!P30,'Model inputs'!Q30) -> 996.99206 | H6: =SUM('SwapDesk — Financials · Profit'!H11,'SwapDesk — Financials · Profit'!I11,'SwapDesk — Financials · Profit'!J11) -> 2686.3435 | I6: =SUM('Model inputs'!R31,'Model inputs'!S31,'Model inputs'!T31) -> 7619.4654 | J6: =SUM('Model inputs'!R30,'Model inputs'!S30,'Model inputs'!T30) -> 1242.6904 | K6: =SUM('SwapDesk — Financials · Profit'!K11,'SwapDesk — Financials · Profit'!L11,'SwapDesk — Financials · Profit'!M11) -> 3256.3449 | L6: =SUM('Model inputs'!U31,'Model inputs'!V31,'Model inputs'!W31) -> 9854.4981 | M6: =SUM('Model inputs'!U30,'Model inputs'!V30,'Model inputs'!W30) -> 1449.8743 | N6: =SUM('SwapDesk — Financials · Profit'!N11,'SwapDesk — Financials · Profit'!O11,'SwapDesk — Financials · Profit'!P11) -> 3786.5838 | O6: =SUM('Model inputs'!X31,'Model inputs'!Y31,'Model inputs'!Z31) -> 11978.545 | P6: =SUM('Model inputs'!X30,'Model inputs'!Y30,'Model inputs'!Z30) -> 1624.625 | Q6: =SUM('SwapDesk — Financials · Profit'!Q11,'SwapDesk — Financials · Profit'!R11,'SwapDesk — Financials · Profit'!S11) -> 4279.9436 | R6: =SUM('Model inputs'!AA31,'Model inputs'!AB31,'Model inputs'!AC31) -> 13997.226 | S6: =SUM('Model inputs'!AA30,'Model inputs'!AB30,'Model inputs'!AC30) -> 1772.0568 | T6: =SUM('SwapDesk — Financials · Profit'!T11,'SwapDesk — Financials · Profit'!U11,'SwapDesk — Financials · Profit'!V11) -> 4739.0906 | U6: =SUM('Model inputs'!AD31,'Model inputs'!AE31,'Model inputs'!AF31) -> 15915.872 | V6: =SUM('Model inputs'!AD30,'Model inputs'!AE30,'Model inputs'!AF30) -> 1896.472 | W6: =SUM('SwapDesk — Financials · Profit'!W11,'SwapDesk — Financials · Profit'!X11,'SwapDesk — Financials · Profit'!Y11) -> 5166.4908 | X6: =SUM('Model inputs'!AG31,'Model inputs'!AH31,'Model inputs'!AI31) -> 17739.537 | Y6: =SUM('Model inputs'!AG30,'Model inputs'!AH30,'Model inputs'!AI30) -> 2001.4901
A7: Operating profit | B7: =SUM('SwapDesk — Financials · Profit'!B18,'SwapDesk — Financials · Profit'!C18,'SwapDesk — Financials · Profit'!D18) -> 345.5717 | C7: =SUM('Model inputs'!L46,'Model inputs'!M46,'Model inputs'!N46) -> 486.16215 | D7: =SUM('Model inputs'!L45,'Model inputs'!M45,'Model inputs'!N45) -> -363.20358 | E7: =SUM('SwapDesk — Financials · Profit'!E18,'SwapDesk — Financials · Profit'!F18,'SwapDesk — Financials · Profit'!G18) -> -4995.2893 | F7: =SUM('Model inputs'!O46,'Model inputs'!P46,'Model inputs'!Q46) -> -3038.7298 | G7: =SUM('Model inputs'!O45,'Model inputs'!P45,'Model inputs'!Q45) -> -6071.7579 | H7: =SUM('SwapDesk — Financials · Profit'!H18,'SwapDesk — Financials · Profit'!I18,'SwapDesk — Financials · Profit'!J18) -> -4382.4065 | I7: =SUM('Model inputs'!R46,'Model inputs'!S46,'Model inputs'!T46) -> -686.78456 | J7: =SUM('Model inputs'!R45,'Model inputs'!S45,'Model inputs'!T45) -> -5826.0596 | K7: =SUM('SwapDesk — Financials · Profit'!K18,'SwapDesk — Financials · Profit'!L18,'SwapDesk — Financials · Profit'!M18) -> -3812.4051 | L7: =SUM('Model inputs'!U46,'Model inputs'!V46,'Model inputs'!W46) -> 1548.2481 | M7: =SUM('Model inputs'!U45,'Model inputs'!V45,'Model inputs'!W45) -> -5618.8757 | N7: =SUM('SwapDesk — Financials · Profit'!N18,'SwapDesk — Financials · Profit'!O18,'SwapDesk — Financials · Profit'!P18) -> -3282.1662 | O7: =SUM('Model inputs'!X46,'Model inputs'!Y46,'Model inputs'!Z46) -> 3672.295 | P7: =SUM('Model inputs'!X45,'Model inputs'!Y45,'Model inputs'!Z45) -> -5444.125 | Q7: =SUM('SwapDesk — Financials · Profit'!Q18,'SwapDesk — Financials · Profit'!R18,'SwapDesk — Financials · Profit'!S18) -> -2788.8064 | R7: =SUM('Model inputs'!AA46,'Model inputs'!AB46,'Model inputs'!AC46) -> 5690.9763 | S7: =SUM('Model inputs'!AA45,'Model inputs'!AB45,'Model inputs'!AC45) -> -5296.6932 | T7: =SUM('SwapDesk — Financials · Profit'!T18,'SwapDesk — Financials · Profit'!U18,'SwapDesk — Financials · Profit'!V18) -> -2329.6594 | U7: =SUM('Model inputs'!AD46,'Model inputs'!AE46,'Model inputs'!AF46) -> 7609.6221 | V7: =SUM('Model inputs'!AD45,'Model inputs'!AE45,'Model inputs'!AF45) -> -5172.278 | W7: =SUM('SwapDesk — Financials · Profit'!W18,'SwapDesk — Financials · Profit'!X18,'SwapDesk — Financials · Profit'!Y18) -> -1902.2592 | X7: =SUM('Model inputs'!AG46,'Model inputs'!AH46,'Model inputs'!AI46) -> 9433.287 | Y7: =SUM('Model inputs'!AG45,'Model inputs'!AH45,'Model inputs'!AI45) -> -5067.2599
A8: Ending cash | B8: =IF('SwapDesk — Financials · Profit'!D22="","",'SwapDesk — Financials · Profit'!D22) -> 15345.572 | C8: =IF('Model inputs'!N16="","",'Model inputs'!N16) -> 15486.162 | D8: =IF('Model inputs'!N15="","",'Model inputs'!N15) -> 14636.796 | E8: =IF('SwapDesk — Financials · Profit'!G22="","",'SwapDesk — Financials · Profit'!G22) -> 10350.282 | F8: =IF('Model inputs'!Q16="","",'Model inputs'!Q16) -> 12447.432 | G8: =IF('Model inputs'!Q15="","",'Model inputs'!Q15) -> 8565.0385 | H8: =IF('SwapDesk — Financials · Profit'!J22="","",'SwapDesk — Financials · Profit'!J22) -> 5967.8759 | I8: =IF('Model inputs'!T16="","",'Model inputs'!T16) -> 11760.648 | J8: =IF('Model inputs'!T15="","",'Model inputs'!T15) -> 2738.9789 | K8: =IF('SwapDesk — Financials · Profit'!M22="","",'SwapDesk — Financials · Profit'!M22) -> 2155.4708 | L8: =IF('Model inputs'!W16="","",'Model inputs'!W16) -> 13308.896 | M8: =IF('Model inputs'!W15="","",'Model inputs'!W15) -> -2879.8969 | N8: =IF('SwapDesk — Financials · Profit'!P22="","",'SwapDesk — Financials · Profit'!P22) -> -1126.6955 | O8: =IF('Model inputs'!Z16="","",'Model inputs'!Z16) -> 16981.191 | P8: =IF('Model inputs'!Z15="","",'Model inputs'!Z15) -> -8324.0219 | Q8: =IF('SwapDesk — Financials · Profit'!S22="","",'SwapDesk — Financials · Profit'!S22) -> -3915.5019 | R8: =IF('Model inputs'!AC16="","",'Model inputs'!AC16) -> 22672.167 | S8: =IF('Model inputs'!AC15="","",'Model inputs'!AC15) -> -13620.715 | T8: =IF('SwapDesk — Financials · Profit'!V22="","",'SwapDesk — Financials · Profit'!V22) -> -6245.1613 | U8: =IF('Model inputs'!AF16="","",'Model inputs'!AF16) -> 30281.789 | V8: =IF('Model inputs'!AF15="","",'Model inputs'!AF15) -> -18792.993 | W8: =IF('SwapDesk — Financials · Profit'!Y22="","",'SwapDesk — Financials · Profit'!Y22) -> -8147.4205 | X8: =IF('Model inputs'!AI16="","",'Model inputs'!AI16) -> 39715.076 | Y8: =IF('Model inputs'!AI15="","",'Model inputs'!AI15) -> -23860.253

Sheet Model inputs
A1: Model inputs
A2: Integration values are aggregated snapshots; raw source records are not included.
A4: Variables
A5: Variable / segment | B5: Value | C5: 2026-01 | D5: 2026-02 | E5: 2026-03 | F5: 2026-04 | G5: 2026-05 | H5: 2026-06 | I5: 2026-07 | J5: 2026-08 | K5: 2026-09 | L5: 2026-10 | M5: 2026-11 | N5: 2026-12 | O5: 2027-01 | P5: 2027-02 | Q5: 2027-03 | R5: 2027-04 | S5: 2027-05 | T5: 2027-06 | U5: 2027-07 | V5: 2027-08 | W5: 2027-09 | X5: 2027-10 | Y5: 2027-11 | Z5: 2027-12 | AA5: 2028-01 | AB5: 2028-02 | AC5: 2028-03 | AD5: 2028-04 | AE5: 2028-05 | AF5: 2028-06 | AG5: 2028-07 | AH5: 2028-08 | AI5: 2028-09 | AJ5: Value
A6: Cases per store | B6: 0
A7: Cases per store > Growing shop | B7: ='SwapDesk — Assumptions · Mercha'!D5 -> 400
A8: Cases per store > Small shop | B8: ='SwapDesk — Assumptions · Mercha'!D6 -> 120
A9: Cash collections | C9: 0 | D9: 0 | E9: 0 | F9: 0 | G9: 0 | H9: 0 | I9: 0 | J9: 0 | K9: 0 | L9: =IF('Model inputs'!L55="","",'Model inputs'!L55) -> 603.99 | M9: =IF('Model inputs'!M55="","",'Model inputs'!M55) -> 702.5437 | N9: =IF('Model inputs'!N55="","",'Model inputs'!N55) -> 798.72232 | O9: =IF('Model inputs'!O55="","",'Model inputs'!O55) -> 892.58548 | P9: =IF('Model inputs'!P55="","",'Model inputs'!P55) -> 984.19126 | Q9: =IF('Model inputs'!Q55="","",'Model inputs'!Q55) -> 1073.5962 | R9: =IF('Model inputs'!R55="","",'Model inputs'!R55) -> 1160.8554 | S9: =IF('Model inputs'!S55="","",'Model inputs'!S55) -> 1246.0224 | ... AI9: =IF('Model inputs'!AI55="","",'Model inputs'!AI55) -> 2362.9455
A10: Cash payments | C10: 0 | D10: 0 | E10: 0 | F10: 0 | G10: 0 | H10: 0 | I10: 0 | J10: 0 | K10: 0 | L10: ='Model inputs'!L11+'Model inputs'!L44 -> 565.0395 | M10: ='Model inputs'!M11+'Model inputs'!M44 -> 586.73739 | N10: ='Model inputs'!N11+'Model inputs'!N44 -> 607.90742 | O10: ='Model inputs'!O11+'Model inputs'!O44 -> 2628.563 | P10: ='Model inputs'!P11+'Model inputs'!P44 -> 2648.717 | Q10: ='Model inputs'!Q11+'Model inputs'!Q44 -> 2668.3823 | R10: ='Model inputs'!R11+'Model inputs'!R44 -> 2687.5711 | S10: ='Model inputs'!S11+'Model inputs'!S44 -> 2706.2955 | ... AI10: ='Model inputs'!AI11+'Model inputs'!AI44 -> 2951.4068
A11: Cost of service | C11: 0 | D11: 0 | E11: 0 | F11: 0 | G11: 0 | H11: 0 | I11: 0 | J11: 0 | K11: 0 | L11: ='Model inputs'!L114+'Model inputs'!L94+'Model inputs'!L103+'Model inputs'!L26 -> 208.7895 | M11: ='Model inputs'!M114+'Model inputs'!M94+'Model inputs'!M103+'Model inputs'!M26 -> 230.48739 | N11: ='Model inputs'!N114+'Model inputs'!N94+'Model inputs'!N103+'Model inputs'!N26 -> 251.65742 | O11: ='Model inputs'!O114+'Model inputs'!O94+'Model inputs'!O103+'Model inputs'!O26 -> 272.31295 | P11: ='Model inputs'!P114+'Model inputs'!P94+'Model inputs'!P103+'Model inputs'!P26 -> 292.46702 | Q11: ='Model inputs'!Q114+'Model inputs'!Q94+'Model inputs'!Q103+'Model inputs'!Q26 -> 312.13229 | R11: ='Model inputs'!R114+'Model inputs'!R94+'Model inputs'!R103+'Model inputs'!R26 -> 331.32111 | S11: ='Model inputs'!S114+'Model inputs'!S94+'Model inputs'!S103+'Model inputs'!S26 -> 350.04552 | ... AI11: ='Model inputs'!AI114+'Model inputs'!AI94+'Model inputs'!AI103+'Model inputs'!AI26 -> 595.15683
A12: Cost per execution · SwapDesk — Operations · Merchant and execution forecast | B12: ='SwapDesk — Assumptions · Commer'!B8 -> 0.03
A13: Customer acquisition cost | B13: ='SwapDesk — Assumptions · Commer'!B11 -> 100
A14: Ending cash · SwapDesk — Financials · Profit and cash forecast · Main Scenario | C14: =IF('SwapDesk — Assumptions · Commer'!B15="","",'SwapDesk — Assumptions · Commer'!B15) -> 15000 | D14: =IF('SwapDesk — Assumptions · Commer'!B15="","",'SwapDesk — Assumptions · Commer'!B15) -> 15000 | E14: =IF('SwapDesk — Assumptions · Commer'!B15="","",'SwapDesk — Assumptions · Commer'!B15) -> 15000 | F14: =IF('SwapDesk — Assumptions · Commer'!B15="","",'SwapDesk — Assumptions · Commer'!B15) -> 15000 | G14: =IF('SwapDesk — Assumptions · Commer'!B15="","",'SwapDesk — Assumptions · Commer'!B15) -> 15000 | H14: =IF('SwapDesk — Assumptions · Commer'!B15="","",'SwapDesk — Assumptions · Commer'!B15) -> 15000 | I14: =IF('SwapDesk — Assumptions · Commer'!B15="","",'SwapDesk — Assumptions · Commer'!B15) -> 15000 | J14: =IF('SwapDesk — Assumptions · Commer'!B15="","",'SwapDesk — Assumptions · Commer'!B15) -> 15000 | K14: =IF('SwapDesk — Assumptions · Commer'!B15="","",'SwapDesk — Assumptions · Commer'!B15) -> 15000 | L14: ='Model inputs'!K14+'Model inputs'!L39 -> 15038.951 | M14: ='Model inputs'!L14+'Model inputs'!M39 -> 15154.757 | N14: ='Model inputs'!M14+'Model inputs'!N39 -> 15345.572 | O14: ='Model inputs'!N14+'Model inputs'!O39 -> 13609.594 | P14: ='Model inputs'!O14+'Model inputs'!P39 -> 11945.068 | Q14: ='Model inputs'!P14+'Model inputs'!Q39 -> 10350.282 | R14: ='Model inputs'!Q14+'Model inputs'!R39 -> 8823.5666 | S14: ='Model inputs'!R14+'Model inputs'!S39 -> 7363.2935 | ... AI14: ='Model inputs'!AH14+'Model inputs'!AI39 -> -8147.4205
A15: Ending cash · Bad Reliability | C15: =IF('Model inputs'!B121="","",'Model inputs'!B121) -> 15000 | D15: =IF('Model inputs'!B121="","",'Model inputs'!B121) -> 15000 | E15: =IF('Model inputs'!B121="","",'Model inputs'!B121) -> 15000 | F15: =IF('Model inputs'!B121="","",'Model inputs'!B121) -> 15000 | G15: =IF('Model inputs'!B121="","",'Model inputs'!B121) -> 15000 | H15: =IF('Model inputs'!B121="","",'Model inputs'!B121) -> 15000 | I15: =IF('Model inputs'!B121="","",'Model inputs'!B121) -> 15000 | J15: =IF('Model inputs'!B121="","",'Model inputs'!B121) -> 15000 | K15: =IF('Model inputs'!B121="","",'Model inputs'!B121) -> 15000 | L15: ='Model inputs'!K15+'Model inputs'!L119 -> 14843.388 | M15: ='Model inputs'!L15+'Model inputs'!M119 -> 14722.989 | N15: ='Model inputs'!M15+'Model inputs'!N119 -> 14636.796 | O15: ='Model inputs'!N15+'Model inputs'!O119 -> 12582.916 | P15: ='Model inputs'!O15+'Model inputs'!P119 -> 10559.56 | Q15: ='Model inputs'!P15+'Model inputs'!Q119 -> 8565.0385 | R15: ='Model inputs'!Q15+'Model inputs'!R119 -> 6597.7576 | S15: ='Model inputs'!R15+'Model inputs'!S119 -> 4656.2117 | ... AI15: ='Model inputs'!AH15+'Model inputs'!AI119 -> -23860.253
A16: Ending cash · Growth | C16: =IF('Model inputs'!B122="","",'Model inputs'!B122) -> 15000 | D16: =IF('Model inputs'!B122="","",'Model inputs'!B122) -> 15000 | E16: =IF('Model inputs'!B122="","",'Model inputs'!B122) -> 15000 | F16: =IF('Model inputs'!B122="","",'Model inputs'!B122) -> 15000 | G16: =IF('Model inputs'!B122="","",'Model inputs'!B122) -> 15000 | H16: =IF('Model inputs'!B122="","",'Model inputs'!B122) -> 15000 | I16: =IF('Model inputs'!B122="","",'Model inputs'!B122) -> 15000 | J16: =IF('Model inputs'!B122="","",'Model inputs'!B122) -> 15000 | K16: =IF('Model inputs'!B122="","",'Model inputs'!B122) -> 15000 | L16: ='Model inputs'!K16+'Model inputs'!L120 -> 14879.172 | M16: ='Model inputs'!L16+'Model inputs'!M120 -> 15042.827 | N16: ='Model inputs'!M16+'Model inputs'!N120 -> 15486.162 | O16: ='Model inputs'!N16+'Model inputs'!O120 -> 14204.455 | P16: ='Model inputs'!O16+'Model inputs'!P120 -> 13193.065 | Q16: ='Model inputs'!P16+'Model inputs'!Q120 -> 12447.432 | R16: ='Model inputs'!Q16+'Model inputs'!R120 -> 11963.076 | S16: ='Model inputs'!R16+'Model inputs'!S120 -> 11735.591 | ... AI16: ='Model inputs'!AH16+'Model inputs'!AI120 -> 39715.076
A17: Ending stores | C17: =SUM('Model inputs'!C18,'Model inputs'!C19) -> 0 | D17: =SUM('Model inputs'!D18,'Model inputs'!D19) -> 0 | E17: =SUM('Model inputs'!E18,'Model inputs'!E19) -> 0 | F17: =SUM('Model inputs'!F18,'Model inputs'!F19) -> 0 | G17: =SUM('Model inputs'!G18,'Model inputs'!G19) -> 0 | H17: =SUM('Model inputs'!H18,'Model inputs'!H19) -> 0 | I17: =SUM('Model inputs'!I18,'Model inputs'!I19) -> 0 | J17: =SUM('Model inputs'!J18,'Model inputs'!J19) -> 0 | ... AI17: =SUM('Model inputs'!AI18,'Model inputs'!AI19) -> 30.530231
A18: Ending stores > Growing shop | C18: =0 -> 0 | D18: =0 -> 0 | E18: =0 -> 0 | F18: =0 -> 0 | G18: =0 -> 0 | H18: =0 -> 0 | I18: =0 -> 0 | J18: =0 -> 0 | K18: ='SwapDesk — Operations · Merchan'!B15 -> 2 | L18: ='Model inputs'!L77+'Model inputs'!L74-'Model inputs'!L71 -> 2.46 | M18: ='Model inputs'!M77+'Model inputs'!M74-'Model inputs'!M71 -> 2.9108 | N18: ='Model inputs'!N77+'Model inputs'!N74-'Model inputs'!N71 -> 3.352584 | O18: ='Model inputs'!O77+'Model inputs'!O74-'Model inputs'!O71 -> 3.7855323 | P18: ='Model inputs'!P77+'Model inputs'!P74-'Model inputs'!P71 -> 4.2098217 | Q18: ='Model inputs'!Q77+'Model inputs'!Q74-'Model inputs'!Q71 -> 4.6256252 | R18: ='Model inputs'!R77+'Model inputs'!R74-'Model inputs'!R71 -> 5.0331127 | S18: ='Model inputs'!S77+'Model inputs'!S74-'Model inputs'!S71 -> 5.4324505 | ... AI18: ='Model inputs'!AI77+'Model inputs'!AI74-'Model inputs'!AI71 -> 10.837052
A19: Ending stores > Small shop | C19: =0 -> 0 | D19: =0 -> 0 | E19: =0 -> 0 | F19: =0 -> 0 | G19: =0 -> 0 | H19: =0 -> 0 | I19: =0 -> 0 | J19: =0 -> 0 | K19: ='SwapDesk — Operations · Merchan'!B16 -> 5 | L19: ='Model inputs'!L78+'Model inputs'!L75-'Model inputs'!L72 -> 5.85 | M19: ='Model inputs'!M78+'Model inputs'!M75-'Model inputs'!M72 -> 6.6745 | N19: ='Model inputs'!N78+'Model inputs'!N75-'Model inputs'!N72 -> 7.474265 | O19: ='Model inputs'!O78+'Model inputs'!O75-'Model inputs'!O72 -> 8.250037 | P19: ='Model inputs'!P78+'Model inputs'!P75-'Model inputs'!P72 -> 9.0025359 | Q19: ='Model inputs'!Q78+'Model inputs'!Q75-'Model inputs'!Q72 -> 9.7324599 | R19: ='Model inputs'!R78+'Model inputs'!R75-'Model inputs'!R72 -> 10.440486 | S19: ='Model inputs'!S78+'Model inputs'!S75-'Model inputs'!S72 -> 11.127271 | ... AI19: ='Model inputs'!AI78+'Model inputs'!AI75-'Model inputs'!AI72 -> 19.693179
A20: Extra execution factor | AJ20: 0
A21: Extra execution factor > Growing shop | AJ21: ='SwapDesk — Assumptions · Mercha'!F5 -> 0.15
A22: Extra execution factor > Small shop | AJ22: ='SwapDesk — Assumptions · Mercha'!F6 -> 0.15
A23: Extra execution factor | B23: 0
A24: Extra execution factor > Growing shop | B24: ='SwapDesk — Assumptions · Mercha'!F5 -> 0.15
A25: Extra execution factor > Small shop | B25: ='SwapDesk — Assumptions · Mercha'!F6 -> 0.15
A26: Fixed hosting | C26: 0 | D26: 0 | E26: 0 | F26: 0 | G26: 0 | H26: 0 | I26: 0 | J26: 0 | K26: 0 | L26: =IF('Model inputs'!B27="","",'Model inputs'!B27) -> 75 | M26: =IF('Model inputs'!B27="","",'Model inputs'!B27) -> 75 | N26: =IF('Model inputs'!B27="","",'Model inputs'!B27) -> 75 | O26: =IF('Model inputs'!B27="","",'Model inputs'!B27) -> 75 | P26: =IF('Model inputs'!B27="","",'Model inputs'!B27) -> 75 | Q26: =IF('Model inputs'!B27="","",'Model inputs'!B27) -> 75 | R26: =IF('Model inputs'!B27="","",'Model inputs'!B27) -> 75 | S26: =IF('Model inputs'!B27="","",'Model inputs'!B27) -> 75 | T26: =IF('Model inputs'!B27="","",'Model inputs'!B27) -> 75 | U26: =IF('Model inputs'!B27="","",'Model inputs'!B27) -> 75 | V26: =IF('Model inputs'!B27="","",'Model inputs'!B27) -> 75 | W26: =IF('Model inputs'!B27="","",'Model inputs'!B27) -> 75 | X26: =IF('Model inputs'!B27="","",'Model inputs'!B27) -> 75 | Y26: =IF('Model inputs'!B27="","",'Model inputs'!B27) -> 75 | Z26: =IF('Model inputs'!B27="","",'Model inputs'!B27) -> 75 | AA26: =IF('Model inputs'!B27="","",'Model inputs'!B27) -> 75 | AB26: =IF('Model inputs'!B27="","",'Model inputs'!B27) -> 75 | AC26: =IF('Model inputs'!B27="","",'Model inputs'!B27) -> 75 | AD26: =IF('Model inputs'!B27="","",'Model inputs'!B27) -> 75 | AE26: =IF('Model inputs'!B27="","",'Model inputs'!B27) -> 75 | AF26: =IF('Model inputs'!B27="","",'Model inputs'!B27) -> 75 | AG26: =IF('Model inputs'!B27="","",'Model inputs'!B27) -> 75 | AH26: =IF('Model inputs'!B27="","",'Model inputs'!B27) -> 75 | AI26: =IF('Model inputs'!B27="","",'Model inputs'!B27) -> 75
A27: Fixed infrastructure cost | B27: ='SwapDesk — Assumptions · Commer'!B12 -> 75
A28: Founder start date
A29: Founder start date > Placeholder founder 1 | B29: =DATE(2027,1,1) -> 46388
A30: Gross profit · Bad Reliability | C30: 0 | D30: 0 | E30: 0 | F30: 0 | G30: 0 | H30: 0 | I30: 0 | J30: 0 | K30: 0 | L30: ='Model inputs'!L53-'Model inputs'!L117 -> 199.638 | M30: ='Model inputs'!M53-'Model inputs'!M117 -> 235.85092 | N30: ='Model inputs'!N53-'Model inputs'!N117 -> 270.0575 | O30: ='Model inputs'!O53-'Model inputs'!O117 -> 302.36981 | P30: ='Model inputs'!P53-'Model inputs'!P117 -> 332.89359 | Q30: ='Model inputs'!Q53-'Model inputs'!Q117 -> 361.72865 | R30: ='Model inputs'!R53-'Model inputs'!R117 -> 388.96917 | S30: ='Model inputs'!S53-'Model inputs'!S117 -> 414.70404 | ... AI30: ='Model inputs'!AI53-'Model inputs'!AI117 -> 677.76571
A31: Gross profit · Growth | C31: 0 | D31: 0 | E31: 0 | F31: 0 | G31: 0 | H31: 0 | I31: 0 | J31: 0 | K31: 0 | L31: ='Model inputs'!L54-'Model inputs'!L118 -> 647.922 | M31: ='Model inputs'!M54-'Model inputs'!M118 -> 932.40547 | N31: ='Model inputs'!N54-'Model inputs'!N118 -> 1212.0847 | O31: ='Model inputs'!O54-'Model inputs'!O118 -> 1487.0425 | P31: ='Model inputs'!P54-'Model inputs'!P118 -> 1757.3601 | Q31: ='Model inputs'!Q54-'Model inputs'!Q118 -> 2023.1176 | R31: ='Model inputs'!R54-'Model inputs'!R118 -> 2284.3934 | S31: ='Model inputs'!S54-'Model inputs'!S118 -> 2541.2647 | ... AI31: ='Model inputs'!AI54-'Model inputs'!AI118 -> 6110.1455
A32: Gross profit · SwapDesk — Financials · Profit and cash forecast · Main Scenario | L32: ='Model inputs'!L55-'Model inputs'!L11 -> 395.2005 | M32: ='Model inputs'!M55-'Model inputs'!M11 -> 472.0563 | N32: ='Model inputs'!N55-'Model inputs'!N11 -> 547.0649 | O32: ='Model inputs'!O55-'Model inputs'!O11 -> 620.27253 | P32: ='Model inputs'!P55-'Model inputs'!P11 -> 691.72424 | Q32: ='Model inputs'!Q55-'Model inputs'!Q11 -> 761.4639 | R32: ='Model inputs'!R55-'Model inputs'!R11 -> 829.53425 | S32: ='Model inputs'!S55-'Model inputs'!S11 -> 895.97689 | ... AI32: ='Model inputs'!AI55-'Model inputs'!AI11 -> 1767.7887
A33: Gross profit · SwapDesk — Business Plan · Quarterly scenario comparison · Main Scenario | C33: 0 | D33: 0 | E33: 0 | F33: 0 | G33: 0 | H33: 0 | I33: 0 | J33: 0 | K33: 0 | L33: =IF('Model inputs'!L32="","",'Model inputs'!L32) -> 395.2005 | M33: =IF('Model inputs'!M32="","",'Model inputs'!M32) -> 472.0563 | N33: =IF('Model inputs'!N32="","",'Model inputs'!N32) -> 547.0649 | O33: =IF('Model inputs'!O32="","",'Model inputs'!O32) -> 620.27253 | P33: =IF('Model inputs'!P32="","",'Model inputs'!P32) -> 691.72424 | Q33: =IF('Model inputs'!Q32="","",'Model inputs'!Q32) -> 761.4639 | R33: =IF('Model inputs'!R32="","",'Model inputs'!R32) -> 829.53425 | S33: =IF('Model inputs'!S32="","",'Model inputs'!S32) -> 895.97689 | ... AI33: =IF('Model inputs'!AI32="","",'Model inputs'!AI32) -> 1767.7887
A34: Included resolutions · SwapDesk — Operations · Merchant and execution forecast | B34: ='SwapDesk — Assumptions · Commer'!B6 -> 100
A35: Infrastructure cost per store · SwapDesk — Operations · Merchant and execution forecast | B35: ='SwapDesk — Assumptions · Commer'!B13 -> 1
A36: Monthly store churn | B36: 0
A37: Monthly store churn > Growing shop | B37: ='SwapDesk — Assumptions · Mercha'!C5 -> 0.02
A38: Monthly store churn > Small shop | B38: ='SwapDesk — Assumptions · Mercha'!C6 -> 0.03
A39: Net cash flow | C39: 0 | D39: 0 | E39: 0 | F39: 0 | G39: 0 | H39: 0 | I39: 0 | J39: 0 | K39: 0 | L39: ='Model inputs'!L9-'Model inputs'!L10 -> 38.9505 | M39: ='Model inputs'!M9-'Model inputs'!M10 -> 115.8063 | N39: ='Model inputs'!N9-'Model inputs'!N10 -> 190.8149 | O39: ='Model inputs'!O9-'Model inputs'!O10 -> -1735.9775 | P39: ='Model inputs'!P9-'Model inputs'!P10 -> -1664.5258 | Q39: ='Model inputs'!Q9-'Model inputs'!Q10 -> -1594.7861 | R39: ='Model inputs'!R9-'Model inputs'!R10 -> -1526.7158 | S39: ='Model inputs'!S9-'Model inputs'!S10 -> -1460.2731 | ... AI39: ='Model inputs'!AI9-'Model inputs'!AI10 -> -588.46133
A40: New stores per month | B40: 0
A41: New stores per month > Growing shop | B41: ='SwapDesk — Assumptions · Mercha'!B5 -> 0.5
A42: New stores per month > Small shop | B42: ='SwapDesk — Assumptions · Mercha'!B6 -> 1
A43: Onboarding minutes | B43: ='SwapDesk — Assumptions · Commer'!B10 -> 90
A44: Operating expenses | C44: 0 | D44: 0 | E44: 0 | F44: 0 | G44: 0 | H44: 0 | I44: 0 | J44: 0 | K44: 0 | L44: ='Model inputs'!L88+'Model inputs'!L79+'Model inputs'!L112+'Model inputs'!L49 -> 356.25 | M44: ='Model inputs'!M88+'Model inputs'!M79+'Model inputs'!M112+'Model inputs'!M49 -> 356.25 | N44: ='Model inputs'!N88+'Model inputs'!N79+'Model inputs'!N112+'Model inputs'!N49 -> 356.25 | O44: ='Model inputs'!O88+'Model inputs'!O79+'Model inputs'!O112+'Model inputs'!O49 -> 2356.25 | P44: ='Model inputs'!P88+'Model inputs'!P79+'Model inputs'!P112+'Model inputs'!P49 -> 2356.25 | Q44: ='Model inputs'!Q88+'Model inputs'!Q79+'Model inputs'!Q112+'Model inputs'!Q49 -> 2356.25 | R44: ='Model inputs'!R88+'Model inputs'!R79+'Model inputs'!R112+'Model inputs'!R49 -> 2356.25 | S44: ='Model inputs'!S88+'Model inputs'!S79+'Model inputs'!S112+'Model inputs'!S49 -> 2356.25 | ... AI44: ='Model inputs'!AI88+'Model inputs'!AI79+'Model inputs'!AI112+'Model inputs'!AI49 -> 2356.25
A45: Operating profit · Bad Reliability | C45: 0 | D45: 0 | E45: 0 | F45: 0 | G45: 0 | H45: 0 | I45: 0 | J45: 0 | K45: 0 | L45: ='Model inputs'!L30-'Model inputs'!L123 -> -156.612 | M45: ='Model inputs'!M30-'Model inputs'!M123 -> -120.39908 | N45: ='Model inputs'!N30-'Model inputs'!N123 -> -86.192495 | O45: ='Model inputs'!O30-'Model inputs'!O123 -> -2053.8802 | P45: ='Model inputs'!P30-'Model inputs'!P123 -> -2023.3564 | Q45: ='Model inputs'!Q30-'Model inputs'!Q123 -> -1994.5214 | R45: ='Model inputs'!R30-'Model inputs'!R123 -> -1967.2808 | S45: ='Model inputs'!S30-'Model inputs'!S123 -> -1941.546 | ... AI45: ='Model inputs'!AI30-'Model inputs'!AI123 -> -1678.4843
A46: Operating profit · Growth | C46: 0 | D46: 0 | E46: 0 | F46: 0 | G46: 0 | H46: 0 | I46: 0 | J46: 0 | K46: 0 | L46: ='Model inputs'!L31-'Model inputs'!L124 -> -120.828 | M46: ='Model inputs'!M31-'Model inputs'!M124 -> 163.65547 | N46: ='Model inputs'!N31-'Model inputs'!N124 -> 443.33468 | O46: ='Model inputs'!O31-'Model inputs'!O124 -> -1281.7075 | P46: ='Model inputs'!P31-'Model inputs'!P124 -> -1011.3899 | Q46: ='Model inputs'!Q31-'Model inputs'!Q124 -> -745.63238 | R46: ='Model inputs'!R31-'Model inputs'!R124 -> -484.35655 | S46: ='Model inputs'!S31-'Model inputs'!S124 -> -227.48527 | ... AI46: ='Model inputs'!AI31-'Model inputs'!AI124 -> 3341.3955
A47: Operating profit · Main Scenario | C47: 0 | D47: 0 | E47: 0 | F47: 0 | G47: 0 | H47: 0 | I47: 0 | J47: 0 | K47: 0 | L47: ='Model inputs'!L32-'Model inputs'!L44 -> 38.9505 | M47: ='Model inputs'!M32-'Model inputs'!M44 -> 115.8063 | N47: ='Model inputs'!N32-'Model inputs'!N44 -> 190.8149 | O47: ='Model inputs'!O32-'Model inputs'!O44 -> -1735.9775 | P47: ='Model inputs'!P32-'Model inputs'!P44 -> -1664.5258 | Q47: ='Model inputs'!Q32-'Model inputs'!Q44 -> -1594.7861 | R47: ='Model inputs'!R32-'Model inputs'!R44 -> -1526.7158 | S47: ='Model inputs'!S32-'Model inputs'!S44 -> -1460.2731 | ... AI47: ='Model inputs'!AI32-'Model inputs'!AI44 -> -588.46133
A48: Other monthly overhead | B48: ='SwapDesk — Assumptions · Commer'!B14 -> 150
A49: Other overhead | C49: 0 | D49: 0 | E49: 0 | F49: 0 | G49: 0 | H49: 0 | I49: 0 | J49: 0 | K49: 0 | L49: =IF('Model inputs'!B48="","",'Model inputs'!B48) -> 150 | M49: =IF('Model inputs'!B48="","",'Model inputs'!B48) -> 150 | N49: =IF('Model inputs'!B48="","",'Model inputs'!B48) -> 150 | O49: =IF('Model inputs'!B48="","",'Model inputs'!B48) -> 150 | P49: =IF('Model inputs'!B48="","",'Model inputs'!B48) -> 150 | Q49: =IF('Model inputs'!B48="","",'Model inputs'!B48) -> 150 | R49: =IF('Model inputs'!B48="","",'Model inputs'!B48) -> 150 | S49: =IF('Model inputs'!B48="","",'Model inputs'!B48) -> 150 | T49: =IF('Model inputs'!B48="","",'Model inputs'!B48) -> 150 | U49: =IF('Model inputs'!B48="","",'Model inputs'!B48) -> 150 | V49: =IF('Model inputs'!B48="","",'Model inputs'!B48) -> 150 | W49: =IF('Model inputs'!B48="","",'Model inputs'!B48) -> 150 | X49: =IF('Model inputs'!B48="","",'Model inputs'!B48) -> 150 | Y49: =IF('Model inputs'!B48="","",'Model inputs'!B48) -> 150 | Z49: =IF('Model inputs'!B48="","",'Model inputs'!B48) -> 150 | AA49: =IF('Model inputs'!B48="","",'Model inputs'!B48) -> 150 | AB49: =IF('Model inputs'!B48="","",'Model inputs'!B48) -> 150 | AC49: =IF('Model inputs'!B48="","",'Model inputs'!B48) -> 150 | AD49: =IF('Model inputs'!B48="","",'Model inputs'!B48) -> 150 | AE49: =IF('Model inputs'!B48="","",'Model inputs'!B48) -> 150 | AF49: =IF('Model inputs'!B48="","",'Model inputs'!B48) -> 150 | AG49: =IF('Model inputs'!B48="","",'Model inputs'!B48) -> 150 | AH49: =IF('Model inputs'!B48="","",'Model inputs'!B48) -> 150 | AI49: =IF('Model inputs'!B48="","",'Model inputs'!B48) -> 150
A50: Overage price · SwapDesk — Operations · Merchant and execution forecast | B50: ='SwapDesk — Assumptions · Commer'!B7 -> 0.5
A51: Planned annual compensation | B51: =IF('Model inputs'!AJ69="","",'Model inputs'!AJ69) -> 24000
A52: Planned annual compensation > Placeholder founder 1 | B52: =IF('Model inputs'!AJ69="","",'Model inputs'!AJ69) -> 24000
A53: Revenue · Bad Reliability | C53: =SUM('Model inputs'!C126,'Model inputs'!C127) -> 0 | D53: =SUM('Model inputs'!D126,'Model inputs'!D127) -> 0 | E53: =SUM('Model inputs'!E126,'Model inputs'!E127) -> 0 | F53: =SUM('Model inputs'!F126,'Model inputs'!F127) -> 0 | G53: =SUM('Model inputs'!G126,'Model inputs'!G127) -> 0 | H53: =SUM('Model inputs'!H126,'Model inputs'!H127) -> 0 | I53: =SUM('Model inputs'!I126,'Model inputs'!I127) -> 0 | J53: =SUM('Model inputs'!J126,'Model inputs'!J127) -> 0 | ... AI53: =SUM('Model inputs'!AI126,'Model inputs'!AI127) -> 1369.2879
A54: Revenue · Growth | C54: =SUM('Model inputs'!C129,'Model inputs'!C130) -> 0 | D54: =SUM('Model inputs'!D129,'Model inputs'!D130) -> 0 | E54: =SUM('Model inputs'!E129,'Model inputs'!E130) -> 0 | F54: =SUM('Model inputs'!F129,'Model inputs'!F130) -> 0 | G54: =SUM('Model inputs'!G129,'Model inputs'!G130) -> 0 | H54: =SUM('Model inputs'!H129,'Model inputs'!H130) -> 0 | I54: =SUM('Model inputs'!I129,'Model inputs'!I130) -> 0 | J54: =SUM('Model inputs'!J129,'Model inputs'!J130) -> 0 | ... AI54: =SUM('Model inputs'!AI129,'Model inputs'!AI130) -> 7715.1575
A55: Revenue | C55: =SUM('Model inputs'!C56,'Model inputs'!C57) -> 0 | D55: =SUM('Model inputs'!D56,'Model inputs'!D57) -> 0 | E55: =SUM('Model inputs'!E56,'Model inputs'!E57) -> 0 | F55: =SUM('Model inputs'!F56,'Model inputs'!F57) -> 0 | G55: =SUM('Model inputs'!G56,'Model inputs'!G57) -> 0 | H55: =SUM('Model inputs'!H56,'Model inputs'!H57) -> 0 | I55: =SUM('Model inputs'!I56,'Model inputs'!I57) -> 0 | J55: =SUM('Model inputs'!J56,'Model inputs'!J57) -> 0 | ... AI55: =SUM('Model inputs'!AI56,'Model inputs'!AI57) -> 2362.9455
A56: Revenue > Growing shop | C56: =0 -> 0 | D56: =0 -> 0 | E56: =0 -> 0 | F56: =0 -> 0 | G56: =0 -> 0 | H56: =0 -> 0 | I56: =0 -> 0 | J56: =0 -> 0 | K56: ='SwapDesk — Operations · Merchan'!B39 -> 0 | L56: ='Model inputs'!L92+'Model inputs'!L83 -> 317.34 | M56: ='Model inputs'!M92+'Model inputs'!M83 -> 375.4932 | N56: ='Model inputs'!N92+'Model inputs'!N83 -> 432.48334 | O56: ='Model inputs'!O92+'Model inputs'!O83 -> 488.33367 | P56: ='Model inputs'!P92+'Model inputs'!P83 -> 543.067 | Q56: ='Model inputs'!Q92+'Model inputs'!Q83 -> 596.70566 | R56: ='Model inputs'!R92+'Model inputs'!R83 -> 649.27154 | S56: ='Model inputs'!S92+'Model inputs'!S83 -> 700.78611 | ... AI56: ='Model inputs'!AI92+'Model inputs'!AI83 -> 1397.9797
A57: Revenue > Small shop | C57: =0 -> 0 | D57: =0 -> 0 | E57: =0 -> 0 | F57: =0 -> 0 | G57: =0 -> 0 | H57: =0 -> 0 | I57: =0 -> 0 | J57: =0 -> 0 | K57: ='SwapDesk — Operations · Merchan'!B40 -> 0 | L57: ='Model inputs'!L93+'Model inputs'!L84 -> 286.65 | M57: ='Model inputs'!M93+'Model inputs'!M84 -> 327.0505 | N57: ='Model inputs'!N93+'Model inputs'!N84 -> 366.23899 | O57: ='Model inputs'!O93+'Model inputs'!O84 -> 404.25182 | P57: ='Model inputs'!P93+'Model inputs'!P84 -> 441.12426 | Q57: ='Model inputs'!Q93+'Model inputs'!Q84 -> 476.89053 | R57: ='Model inputs'!R93+'Model inputs'!R84 -> 511.58382 | S57: ='Model inputs'!S93+'Model inputs'!S84 -> 545.2363 | ... AI57: ='Model inputs'!AI93+'Model inputs'!AI84 -> 964.96576
A58: Subscription price · SwapDesk — Operations · Merchant and execution forecast | B58: ='SwapDesk — Assumptions · Commer'!B5 -> 49
